Workbook
Name _XP231: #REF!
Name _XP231: #REF!
Name _XP231: #REF!
Name A_impresión_IM: #REF!
Name A_impresión_IM: #REF!
Name A_impresión_IM: #REF!
Name accesorios: #REF!
Name accesorios: #REF!
Name accesorios: #REF!
Name AREA: #REF!
Name AREA: #REF!
Name AREA: #REF!
Name calculo: #REF!
Name calculo: #REF!
Name calculo: #REF!
Name CERECITA: #REF!
Name CODIGO: #REF!
Name CODIGO: #REF!
Name CODIGO: #REF!
Name lista: #REF!
Name lista: #REF!
Name lista: #REF!
Name mama: #REF!
Name mama: #REF!
Name mama: #REF!
Name OK: '[1]APU (SISTEMA_AGUA-VARIOS_PERS)'!#REF!
Name papa: #REF!
Name papa: #REF!
Name papa: #REF!
Name tuberia: #REF!
Name tuberia: #REF!
Name tuberia: #REF!

Sheet PRESUPUESTO
A1: FORMATO PARA PRESUPUESTO
A2: PROYECTO DE CONSTRUCCIÓN DE:
A3: NÚMERO DE TRÁMITE:
A4: FECHA: DD/MM/AA
A5: AREA DE CONSTRUCCIÓN: m²
A6: RUBRO | B6: DETALLE | C6: UNIDAD | D6: CANTIDAD | E6: COSTO UNITARIO (incluido iva) | F6: SUBTOTAL | G6: TOTAL | H6: % | J6: 1 | K6: 1 | L6: TOTAL
J7: AU | K7: M/O | L7: M/O
A9: 1.0 | B9: OBRA GRIS | G9: =SUM(F11:F78) -> 81220.85 | H9: =ROUND(G9/$F$182,4) -> 0.5189
A11: 1.1 | B11: INSTALACIONES PROVISIONALES | G11: =SUM(F11:F15) -> 1405.35 | H11: =ROUND(G11/$F$182,4) -> 0.009
A12: 1.1.01 | B12: Caseta de oficina, bodega y guardiania | C12: m2 | D12: 16 | E12: =IF($A12=0,"",ROUND(J12*$J$6,2)) -> 42.5 | F12: =IF($A12=0,"",ROUND(D12*E12,2)) -> 680 | J12: ='1.1'!$H$56 -> 42.5 | K12: ='1.1'!$H$26 -> 7.58 | L12: =ROUND(K12*D12,2) -> 121.28
A13: 1.1.02 | B13: Instalación eléctrica provisional | C13: Global | D13: 1 | E13: =IF($A13=0,"",ROUND(J13*$J$6,2)) -> 440.6 | F13: =IF($A13=0,"",ROUND(D13*E13,2)) -> 440.6 | J13: ='1.1'!$H$112 -> 440.6 | K13: ='1.1'!$H$82 -> 80.78 | L13: =ROUND(K13*D13,2) -> 80.78
A14: 1.1.03 | B14: Instalación AAPP provisional | C14: Global | D14: 1 | E14: =IF($A14=0,"",ROUND(J14*$J$6,2)) -> 284.75 | F14: =IF($A14=0,"",ROUND(D14*E14,2)) -> 284.75 | J14: ='1.1'!$H$168 -> 284.75 | K14: ='1.1'!$H$138 -> 80.78 | L14: =ROUND(K14*D14,2) -> 80.78
A15: 1.1.04 | B15: Cerramiento de Obra | C15: ml
A16: 1.2 | B16: MANTENIMIENTO DE OBRA | G16: =SUM(F16:F19) -> 2992.64 | H16: =ROUND(G16/$F$182,4) -> 0.0191
A17: 1.2.01 | B17: Limpieza general de la obra | C17: semana | D17: =8*4 -> 32 | E17: =IF($A17=0,"",ROUND(J17*$J$6,2)) -> 51.73 | F17: =IF($A17=0,"",ROUND(D17*E17,2)) -> 1655.36 | J17: ='1.2'!$H$56 -> 51.73 | K17: ='1.2'!$H$26 -> 50.22 | L17: =ROUND(K17*D17,2) -> 1607.04
A18: 1.2.02 | B18: Desalojo de limpieza | C18: viajes | D18: =8*4 -> 32 | E18: =IF($A18=0,"",ROUND(J18*$J$6,2)) -> 41.79 | F18: =IF($A18=0,"",ROUND(D18*E18,2)) -> 1337.28 | J18: ='1.2'!$H$112 -> 41.79 | K18: ='1.2'!$H$82 -> 13.39 | L18: =ROUND(K18*D18,2) -> 428.48
A20: 1.3 | B20: PREPARACION DEL TERRENO | G20: =SUM(F20:F23) -> 523.08 | H20: =ROUND(G20/$F$182,4) -> 0.0033
A21: 1.3.01 | B21: Limpieza del terreno | C21: m2 | D21: 523.09 | E21: =IF($A21=0,"",ROUND(J21*$J$6,2)) -> 0.56 | F21: =IF($A21=0,"",ROUND(D21*E21,2)) -> 292.93 | J21: ='1.3'!$H$56 -> 0.56 | K21: ='1.3'!$H$26 -> 0.54 | L21: =ROUND(K21*D21,2) -> 282.47
A22: 1.3.02 | B22: Replanteo y trazado de cimientos | C22: m2 | D22: 154.46 | E22: =IF($A22=0,"",ROUND(J22*$J$6,2)) -> 1.49 | F22: =IF($A22=0,"",ROUND(D22*E22,2)) -> 230.15 | J22: ='1.3'!$H$168 -> 1.49 | K22: ='1.3'!$H$138 -> 0.71 | L22: =ROUND(K22*D22,2) -> 109.67
A24: 1.4 | B24: MOVIMIENTOS DE TIERRA | G24: =SUM(F24:F27) -> 1991.29 | H24: =ROUND(G24/$F$182,4) -> 0.0127
A25: 1.4.01 | B25: Excavacion | C25: m3 | D25: =58.68*2.5 -> 146.7 | E25: =IF($A25=0,"",ROUND(J25*$J$6,2)) -> 4.04 | F25: =IF($A25=0,"",ROUND(D25*E25,2)) -> 592.67 | J25: ='1.4'!$H$280 -> 4.04 | K25: ='1.4'!$H$194 -> 4.69 | L25: =ROUND(K25*D25,2) -> 688.02
A26: 1.4.02 | B26: Relleno compactado con material importado | C26: m3 | D26: =58.68*2.5*0.9-D33 -> 113.34 | E26: =IF($A26=0,"",ROUND(J26*$J$6,2)) -> 12.34 | F26: =IF($A26=0,"",ROUND(D26*E26,2)) -> 1398.62 | J26: ='1.4'!$H$224 -> 12.34 | K26: ='1.4'!$H$194 -> 4.69 | L26: =ROUND(K26*D26,2) -> 531.56
A28: 1.5 | B28: ESTRUCTURAS DE HORMIGON SIMPLE | G28: =SUM(F28:F31) -> 999.96 | H28: =ROUND(G28/$F$182,4) -> 0.0064
A29: 1.5.01 | B29: Replantillo e= 10cm | C29: m3 | D29: =(58.68+5.76)*0.1 -> 6.444 | E29: =IF($A29=0,"",ROUND(J29*$J$6,2)) -> 113.61 | F29: =IF($A29=0,"",ROUND(D29*E29,2)) -> 732.1 | J29: ='1.5'!$H$56 -> 113.61 | K29: ='1.5'!$H$26 -> 41.74 | L29: =ROUND(K29*D29,2) -> 268.97
A30: 1.5.02 | B30: Muro Ciclopeo | C30: m3 | D30: =(2.1+4.5)*0.25*0.3+1.4 -> 1.895 | E30: =IF($A30=0,"",ROUND(J30*$J$6,2)) -> 141.35 | F30: =IF($A30=0,"",ROUND(D30*E30,2)) -> 267.86 | J30: ='1.5'!$H$112 -> 141.35 | K30: ='1.5'!$H$82 -> 53.92 | L30: =ROUND(K30*D30,2) -> 102.18
A32: 1.6 | B32: ESTRUCTURAS DE HORMIGON ARMADO | G32: =SUM(F32:F45) -> 31688.78 | H32: =ROUND(G32/$F$182,4) -> 0.2025
A33: 1.6.01 | B33: Zapatas y vigas: en cimientos | C33: m3 | D33: =15.94+2.75 -> 18.69 | E33: =IF($A33=0,"",ROUND(J33*$J$6,2)) -> 375.27 | F33: =IF($A33=0,"",ROUND(D33*E33,2)) -> 7013.8 | J33: ='1.6b'!$H$112 -> 375.27 | K33: ='1.6b'!$H$82 -> 98.98 | L33: =ROUND(K33*D33,2) -> 1849.94
A34: 1.6.02 | B34: Riostras | C34: m3 | D34: =0.4+1.12 -> 1.52 | E34: =IF($A34=0,"",ROUND(J34*$J$6,2)) -> 410.9 | F34: =IF($A34=0,"",ROUND(D34*E34,2)) -> 624.57 | J34: ='1.6b'!$H$224 -> 410.9 | K34: ='1.6b'!$H$194 -> 119.93 | L34: =ROUND(K34*D34,2) -> 182.29
A35: 1.6.03 | B35: Columnas cimiento a losa vivienda | C35: m3 | D35: 5.45 | E35: =IF($A35=0,"",ROUND(J35*$J$6,2)) -> 537.64 | F35: =IF($A35=0,"",ROUND(D35*E35,2)) -> 2930.14 | J35: ='1.6b'!$H$280 -> 537.64 | K35: ='1.6b'!$H$250 -> 197.3 | L35: =ROUND(K35*D35,2) -> 1075.29
A36: 1.6.04 | B36: Columnas losa a cubierta | C36: m3 | D36: 3.22 | E36: =IF($A36=0,"",ROUND(J36*$J$6,2)) -> 531.85 | F36: =IF($A36=0,"",ROUND(D36*E36,2)) -> 1712.56 | J36: ='1.6b'!$H$336 -> 531.85 | K36: ='1.6b'!$H$306 -> 184.1 | L36: =ROUND(K36*D36,2) -> 592.8
A37: 1.6.05 | B37: Columnas cimiento a losa garaje | C37: m3 | D37: 0.89 | E37: =IF($A37=0,"",ROUND(J37*$J$6,2)) -> 537.64 | F37: =IF($A37=0,"",ROUND(D37*E37,2)) -> 478.5 | J37: ='1.6b'!$H$280 -> 537.64 | K37: ='1.6b'!$H$250 -> 197.3 | L37: =ROUND(K37*D37,2) -> 175.6
A38: 1.6.06 | B38: Vigas losa entrepiso | C38: m3 | D38: 9.84 | E38: =IF($A38=0,"",ROUND(J38*$J$6,2)) -> 442.28 | F38: =IF($A38=0,"",ROUND(D38*E38,2)) -> 4352.04 | J38: ='1.6b'!$H$448 -> 442.28 | K38: ='1.6b'!$H$418 -> 128.3 | L38: =ROUND(K38*D38,2) -> 1262.47
A39: 1.6.07 | B39: Losa entrepiso e= 25cm | C39: m2 | D39: 130.1 | E39: =IF($A39=0,"",ROUND(J39*$J$6,2)) -> 43.69 | F39: =IF($A39=0,"",ROUND(D39*E39,2)) -> 5684.07 | H39: ='1.6b'!$H$1064*130.22 -> 5689.3118 | J39: ='1.6b'!$H$1064 -> 43.69 | K39: ='1.6b'!$H$586 -> 161.18 | L39: =ROUND(K39*D39,2) -> 20969.52
A40: 1.6.08 | B40: Escaleras de hormigon | C40: m3 | D40: 1.6 | E40: =IF($A40=0,"",ROUND(J40*$J$6,2)) -> 428.47 | F40: =IF($A40=0,"",ROUND(D40*E40,2)) -> 685.55 | J40: ='1.6b'!$H$784 -> 428.47 | K40: ='1.6b'!$H$754 -> 135.66 | L40: =ROUND(K40*D40,2) -> 217.06
A41: 1.6.09 | B41: Vigas de cubierta | C41: m3 | D41: 5.75 | E41: =IF($A41=0,"",ROUND(J41*$J$6,2)) -> 534.58 | F41: =IF($A41=0,"",ROUND(D41*E41,2)) -> 3073.84 | J41: ='1.6b'!$H$504 -> 534.58 | K41: ='1.6b'!$H$474 -> 155.41 | L41: =ROUND(K41*D41,2) -> 893.61
A42: 1.6.10 | B42: Vigas losa de garaje | C42: m3 | D42: 1.9 | E42: =IF($A42=0,"",ROUND(J42*$J$6,2)) -> 442.28 | F42: =IF($A42=0,"",ROUND(D42*E42,2)) -> 840.33 | J42: ='1.6b'!$H$448 -> 442.28 | K42: ='1.6b'!$H$418 -> 128.3 | L42: =ROUND(K42*D42,2) -> 243.77
A43: 1.6.11 | B43: Losa garaje e= 25cm | C43: m2 | D43: 24.91 | E43: =IF($A43=0,"",ROUND(J43*$J$6,2)) -> 43.69 | F43: =IF($A43=0,"",ROUND(D43*E43,2)) -> 1088.32 | J43: ='1.6b'!$H$1064 -> 43.69 | K43: ='1.6b'!$H$586 -> 161.18 | L43: =ROUND(K43*D43,2) -> 4014.99
A44: 1.6.12 | B44: Cisterna | C44: m3 | D44: 6.26 | E44: =IF($A44=0,"",ROUND(J44*$J$6,2)) -> 511.99 | F44: =IF($A44=0,"",ROUND(D44*E44,2)) -> 3205.06 | J44: ='1.6b'!$H$952 -> 511.99 | K44: ='1.6b'!$H$922 -> 155.44 | L44: =ROUND(K44*D44,2) -> 973.05
A46: 1.7 | B46: ESTRUCTURAS METALICAS Y CUBIERTAS | G46: =SUM(F46:F50) -> 9632.67 | H46: =ROUND(G46/$F$182,4) -> 0.0615
A47: 1.7.01 | B47: Estructuras metalicas: de cubierta | C47: kg | D47: =(155*1.05+7.8)*8 -> 1364.4 | E47: =IF($A47=0,"",ROUND(J47*$J$6,2)) -> 2.69 | F47: =IF($A47=0,"",ROUND(D47*E47,2)) -> 3670.24 | J47: ='1.7'!$H$56 -> 2.69 | K47: ='1.7'!$H$26 -> 0.71 | L47: =ROUND(K47*D47,2) -> 968.72
A48: 1.7.02 | B48: Cubierta Eternit | C48: m2 | D48: =155*1.05+7.8 -> 170.55 | E48: =IF($A48=0,"",ROUND(J48*$J$6,2)) -> 13.5 | F48: =IF($A48=0,"",ROUND(D48*E48,2)) -> 2302.43 | J48: ='1.7'!$H$112 -> 13.5 | K48: ='1.7'!$H$138 -> 2.81 | L48: =ROUND(K48*D48,2) -> 479.25
A49: 1.7.03 | B49: Tejas sobre cubierta | C49: m2 | D49: =155*1.05+7.8 -> 170.55 | E49: =IF($A49=0,"",ROUND(J49*$J$6,2)) -> 21.46 | F49: =IF($A49=0,"",ROUND(D49*E49,2)) -> 3660 | J49: ='1.7'!$H$280 -> 21.46 | K49: ='1.7'!$H$250 -> 6.45 | L49: =ROUND(K49*D49,2) -> 1100.05
A51: 1.8 | B51: CONTRAPISOS | G51: =SUM(F51:F53) -> 1403.06 | H51: =ROUND(G51/$F$182,4) -> 0.009
A52: 1.8.01 | B52: Contrapiso interior hormigon simple e= 10cm | C52: m2 | D52: 146 | E52: =IF($A52=0,"",ROUND(J52*$J$6,2)) -> 9.61 | F52: =IF($A52=0,"",ROUND(D52*E52,2)) -> 1403.06 | J52: ='1.8'!$H$56 -> 9.61 | K52: ='1.8'!$H$26 -> 2.22 | L52: =ROUND(K52*D52,2) -> 324.12
A54: 1.9 | B54: ALBAÑILERIAS | G54: =SUM(F54:F78) -> 30584.02 | H54: =ROUND(G54/$F$182,4) -> 0.1954
A55: 1.9.01 | B55: Pared mamposteria bloque e= 19cm | C55: m2 | D55: 174.56 | E55: =IF($A55=0,"",ROUND(J55*$J$6,2)) -> 14.59 | F55: =IF($A55=0,"",ROUND(D55*E55,2)) -> 2546.83 | J55: ='1.9'!$H$56 -> 14.59 | K55: ='1.9'!$H$26 -> 5.06 | L55: =ROUND(K55*D55,2) -> 883.27
A56: 1.9.02 | B56: Pared mamposteria bloque e= 9cm | C56: m2 | D56: 389.33 | E56: =IF($A56=0,"",ROUND(J56*$J$6,2)) -> 10.88 | F56: =IF($A56=0,"",ROUND(D56*E56,2)) -> 4235.91 | J56: ='1.9'!$H$168 -> 10.88 | K56: ='1.9'!$H$138 -> 4.06 | L56: =ROUND(K56*D56,2) -> 1580.68
A57: 1.9.03 | B57: Viguetas y pilaretes h. armado 19x20cm | C57: ml | D57: =66.02*2 -> 132.04 | E57: =IF($A57=0,"",ROUND(J57*$J$6,2)) -> 18.22 | F57: =IF($A57=0,"",ROUND(D57*E57,2)) -> 2405.77 | J57: ='1.9'!$H$280 -> 18.22 | K57: ='1.9'!$H$250 -> 6.89 | L57: =ROUND(K57*D57,2) -> 909.76
A58: 1.9.04 | B58: Viguetas y pilaretes h. armado 9x20cm | C58: ml | D58: =139.93*2 -> 279.86 | E58: =IF($A58=0,"",ROUND(J58*$J$6,2)) -> 10.54 | F58: =IF($A58=0,"",ROUND(D58*E58,2)) -> 2949.72 | J58: ='1.9'!$H$392 -> 10.54 | K58: ='1.9'!$H$362 -> 4.61 | L58: =ROUND(K58*D58,2) -> 1290.15
A59: 1.9.05 | B59: Enlucido interior | C59: m2 | D59: 854.18 | E59: =IF($A59=0,"",ROUND(J59*$J$6,2)) -> 5.6 | F59: =IF($A59=0,"",ROUND(D59*E59,2)) -> 4783.41 | J59: ='1.9'!$H$784 -> 5.6 | K59: ='1.9'!$H$754 -> 4.06 | L59: =ROUND(K59*D59,2) -> 3467.97
A60: 1.9.06 | B60: Enlucido exterior | C60: m2 | D60: 340.18 | E60: =IF($A60=0,"",ROUND(J60*$J$6,2)) -> 6.71 | F60: =IF($A60=0,"",ROUND(D60*E60,2)) -> 2282.61 | J60: ='1.9'!$H$840 -> 6.71 | K60: ='1.9'!$H$810 -> 4.45 | L60: =ROUND(K60*D60,2) -> 1513.8
A61: 1.9.07 | B61: Enlucido de columnas | C61: m2 | D61: 115.47 | E61: =IF($A61=0,"",ROUND(J61*$J$6,2)) -> 6.63 | F61: =IF($A61=0,"",ROUND(D61*E61,2)) -> 765.57 | J61: ='1.9'!$H$896 -> 6.63 | K61: ='1.9'!$H$866 -> 5.06 | L61: =ROUND(K61*D61,2) -> 584.28
A62: 1.9.08 | B62: Enlucido de tumbado de losa | C62: m2 | D62: =24.3+1+11+29.65 -> 65.95 | E62: =IF($A62=0,"",ROUND(J62*$J$6,2)) -> 6.93 | F62: =IF($A62=0,"",ROUND(D62*E62,2)) -> 457.03 | J62: ='1.9'!$H$952 -> 6.93 | K62: ='1.9'!$H$922 -> 4.45 | L62: =ROUND(K62*D62,2) -> 293.48
A63: 1.9.09 | B63: Enlucido sobre losas de cubierta | C63: m2 | D63: =24.3+1+11+29.65 -> 65.95 | E63: =IF($A63=0,"",ROUND(J63*$J$6,2)) -> 6.93 | F63: =IF($A63=0,"",ROUND(D63*E63,2)) -> 457.03 | J63: ='1.9'!$H$952 -> 6.93 | K63: ='1.9'!$H$922 -> 4.45 | L63: =ROUND(K63*D63,2) -> 293.48
A64: 1.9.10 | B64: Enlucido de escalera (rampa y escalones) | C64: m2 | D64: =9.77*2 -> 19.54 | E64: =IF($A64=0,"",ROUND(J64*$J$6,2)) -> 7.43 | F64: =IF($A64=0,"",ROUND(D64*E64,2)) -> 145.18 | J64: ='1.9'!$H$1120 -> 7.43 | K64: ='1.9'!$H$1090 -> 5.47 | L64: =ROUND(K64*D64,2) -> 106.88
A65: 1.9.11 | B65: Filos de columnas y paredes | C65: ml | D65: =+D66*2 -> 367.2 | E65: =IF($A65=0,"",ROUND(J65*$J$6,2)) -> 1.86 | F65: =IF($A65=0,"",ROUND(D65*E65,2)) -> 682.99 | J65: ='1.9'!$H$1232 -> 1.86 | K65: ='1.9'!$H$1202 -> 1.31 | L65: =ROUND(K65*D65,2) -> 481.03
A66: 1.9.12 | B66: Cuadrada de boquetes | C66: ml | D66: 183.6 | E66: =IF($A66=0,"",ROUND(J66*$J$6,2)) -> 3.94 | F66: =IF($A66=0,"",ROUND(D66*E66,2)) -> 723.38 | J66: ='1.9'!$H$1288 -> 3.94 | K66: ='1.9'!$H$1258 -> 2.83 | L66: =ROUND(K66*D66,2) -> 519.59
A67: 1.9.13 | B67: Molduras en cubiertas | C67: ml | D67: =58.6+3.83+4.59 -> 67.02 | E67: =IF($A67=0,"",ROUND(J67*$J$6,2)) -> 31.74 | F67: =IF($A67=0,"",ROUND(D67*E67,2)) -> 2127.21 | J67: ='1.9'!$H$1344 -> 31.74 | K67: ='1.9'!$H$1314 -> 12.96 | L67: =ROUND(K67*D67,2) -> 868.58
A68: 1.9.14 | B68: Molduras en ventanas | C68: ml | D68: =(2.5*2+2+7+1.6+6.5*2+2.1*4+3.4+3.5)+(3.6+2.4+3.85+3.1+2.3*2+2.1*2+3.5*2+2.1*2+0.7+1.6)+(2.3+3.1+1.4+1.35+6.45+0.5+0.5+0.8+0.8)+(0.8+1.6+0.6+1+0.7) -> 101.05 | E68: =IF($A68=0,"",ROUND(J68*$J$6,2)) -> 14.93 | F68: =IF($A68=0,"",ROUND(D68*E68,2)) -> 1508.68 | J68: ='1.9'!$H$1400 -> 14.93 | K68: ='1.9'!$H$1314 -> 12.96 | L68: =ROUND(K68*D68,2) -> 1309.61
A69: 1.9.15 | B69: Meson de h. armado en cocina | C69: ml | D69: =2.85+1.75+3.15 -> 7.75 | E69: =IF($A69=0,"",ROUND(J69*$J$6,2)) -> 96.15 | F69: =IF($A69=0,"",ROUND(D69*E69,2)) -> 745.16 | J69: ='1.9'!$H$1568 -> 96.15 | K69: ='1.9'!$H$1538 -> 60.7 | L69: =ROUND(K69*D69,2) -> 470.43
A70: 1.9.16 | B70: Meson de h. armado en baños | C70: ml | D70: =1+0.9+0.9+2.25 -> 5.05 | E70: =IF($A70=0,"",ROUND(J70*$J$6,2)) -> 61.17 | F70: =IF($A70=0,"",ROUND(D70*E70,2)) -> 308.91 | J70: ='1.9'!$H$1512 -> 61.17 | K70: ='1.9'!$H$1482 -> 35.41 | L70: =ROUND(K70*D70,2) -> 178.82
A71: 1.9.17 | B71: Muro de tina de baño (inc. EnlucIdo) | C71: ml | D71: =1.4*3 -> 4.2 | E71: =IF($A71=0,"",ROUND(J71*$J$6,2)) -> 49.66 | F71: =IF($A71=0,"",ROUND(D71*E71,2)) -> 208.57 | J71: ='1.9'!$H$1736 -> 49.66 | K71: ='1.9'!$H$1650 -> 8.09 | L71: =ROUND(K71*D71,2) -> 33.98
A72: 1.9.18 | B72: Cajas de registro (h. simple) AA.SS. | C72: u | D72: 7 | E72: =IF($A72=0,"",ROUND(J72*$J$6,2)) -> 199.7 | F72: =IF($A72=0,"",ROUND(D72*E72,2)) -> 1397.9 | J72: ='1.9'!$H$1792 -> 199.7 | K72: ='1.9'!$H$1762 -> 109.78 | L72: =ROUND(K72*D72,2) -> 768.46
A73: 1.9.19 | B73: Cajas de registro (h. simple) AA.LL. | C73: u | D73: 2 | E73: =IF($A73=0,"",ROUND(J73*$J$6,2)) -> 138.63 | F73: =IF($A73=0,"",ROUND(D73*E73,2)) -> 277.26 | J73: ='1.9'!$H$1848 -> 138.63 | K73: ='1.9'!$H$1818 -> 89.06 | L73: =ROUND(K73*D73,2) -> 178.12
A74: 1.9.20 | B74: Sumidero (h. simple) AA.LL. | C74: u | D74: 1 | E74: =IF($A74=0,"",ROUND(J74*$J$6,2)) -> 180.63 | F74: =IF($A74=0,"",ROUND(D74*E74,2)) -> 180.63 | J74: ='1.9'!$H$1848+42 -> 180.63 | K74: ='1.9'!$H$1818 -> 89.06 | L74: =ROUND(K74*D74,2) -> 89.06
A75: 1.9.21 | B75: Cajas de paso (mamposteria.) Electrica | C75: u | D75: 2 | E75: =IF($A75=0,"",ROUND(J75*$J$6,2)) -> 69.27 | F75: =IF($A75=0,"",ROUND(D75*E75,2)) -> 138.54 | J75: =('1.9'!$H$2128)/2 -> 69.27 | K75: =K73/2 -> 44.53 | L75: =ROUND(K75*D75,2) -> 89.06
A76: 1.9.22 | B76: Enlucido cisterna | C76: m2 | D76: 24 | E76: =IF($A76=0,"",ROUND(J76*$J$6,2)) -> 6.71 | F76: =IF($A76=0,"",ROUND(D76*E76,2)) -> 161.04 | J76: ='1.9'!$H$840 -> 6.71 | K76: ='1.9'!$H$810 -> 4.45 | L76: =ROUND(K76*D76,2) -> 106.8
A77: 1.9.23 | B77: Impermeabilizacion en losa de cubiertas y cisterna | C77: m2 | D77: =24.3+1+11+29.65+24 -> 89.95 | E77: =IF($A77=0,"",ROUND(J77*$J$6,2)) -> 12.17 | F77: =IF($A77=0,"",ROUND(D77*E77,2)) -> 1094.69 | J77: ='1.9'!$H$1904 -> 12.17 | K77: ='1.9'!$H$1874 -> 3.04 | L77: =ROUND(K77*D77,2) -> 273.45
A80: 2.0 | B80: OBRAS DE ACABADOS | G80: =SUM(F82:F123) -> 53908.76 | H80: =ROUND(G80/$F$182,4) -> 0.3444
A82: 2.1 | B82: REVESTIMIENTOS | G82: =SUM(F82:F93) -> 19496.41 | H82: =ROUND(G82/$F$182,4) -> 0.1246
A83: 2.1.01 | B83: Pintura Interior: caucho (paredes) | C83: m2 | D83: =D59-D86 -> 675.68 | E83: =IF($A83=0,"",ROUND(J83*$J$6,2)) -> 5.7 | F83: =IF($A83=0,"",ROUND(D83*E83,2)) -> 3851.38 | J83: ='2.1'!$H$56 -> 5.7 | K83: ='2.1'!$H$26 -> 1.97 | L83: =ROUND(K83*D83,2) -> 1331.09
A84: 2.1.02 | B84: Pintura Interior: caucho (tumbado) | C84: m2 | D84: =D62 -> 65.95 | E84: =IF($A84=0,"",ROUND(J84*$J$6,2)) -> 5.7 | F84: =IF($A84=0,"",ROUND(D84*E84,2)) -> 375.92 | J84: ='2.1'!$H$56 -> 5.7 | K84: ='2.1'!$H$26 -> 1.97 | L84: =ROUND(K84*D84,2) -> 129.92
A85: 2.1.03 | B85: Pintura exterior: elastomérica | C85: m2 | D85: =D60 -> 340.18 | E85: =IF($A85=0,"",ROUND(J85*$J$6,2)) -> 5.73 | F85: =IF($A85=0,"",ROUND(D85*E85,2)) -> 1949.23 | J85: ='2.1'!$H$112 -> 5.73 | K85: ='2.1'!$H$82 -> 2.25 | L85: =ROUND(K85*D85,2) -> 765.41
A86: 2.1.04 | B86: Cerámica en paredes | C86: m2 | D86: 178.5 | E86: =IF($A86=0,"",ROUND(J86*$J$6,2)) -> 19.99 | F86: =IF($A86=0,"",ROUND(D86*E86,2)) -> 3568.22 | J86: ='2.1'!$H$168 -> 19.99 | K86: ='2.1'!$H$138 -> 5.06 | L86: =ROUND(K86*D86,2) -> 903.21
A87: 2.1.05 | B87: Revestimiento de meson en cocina | C87: ml | D87: =2.85+1.75+3.15 -> 7.75 | E87: =IF($A87=0,"",ROUND(J87*$J$6,2)) -> 87.71 | F87: =IF($A87=0,"",ROUND(D87*E87,2)) -> 679.75 | J87: ='2.1'!$H$336 -> 87.71 | K87: ='2.1'!$H$306 -> 33.66 | L87: =ROUND(K87*D87,2) -> 260.87
A88: 2.1.06 | B88: Revestimiento de meson en baños | C88: ml | D88: =1+0.9+0.9+2.25 -> 5.05 | E88: =IF($A88=0,"",ROUND(J88*$J$6,2)) -> 87.71 | F88: =IF($A88=0,"",ROUND(D88*E88,2)) -> 442.94 | J88: ='2.1'!$H$336 -> 87.71 | K88: ='2.1'!$H$306 -> 33.66 | L88: =ROUND(K88*D88,2) -> 169.98
A89: 2.1.07 | B89: Porcelanato en pisos | C89: m2 | D89: =127.03+92.71 -> 219.74 | E89: =IF($A89=0,"",ROUND(J89*$J$6,2)) -> 28.54 | F89: =IF($A89=0,"",ROUND(D89*E89,2)) -> 6271.38 | J89: ='2.1'!$H$392 -> 28.54 | K89: ='2.1'!$H$362 -> 5.56 | L89: =ROUND(K89*D89,2) -> 1221.75
A90: 2.1.08 | B90: Cerámica en pisos de baños, servicio, bodega, lavanderia | C90: m2 | D90: =18.34+22.52 -> 40.86 | E90: =IF($A90=0,"",ROUND(J90*$J$6,2)) -> 21.08 | F90: =IF($A90=0,"",ROUND(D90*E90,2)) -> 861.33 | J90: ='2.1'!$H$448 -> 21.08 | K90: ='2.1'!$H$418 -> 5.06 | L90: =ROUND(K90*D90,2) -> 206.75
A91: 2.1.09 | B91: Revestimiento de escalera | C91: m2 | D91: 9.77 | E91: =IF($A91=0,"",ROUND(J91*$J$6,2)) -> 39.56 | F91: =IF($A91=0,"",ROUND(D91*E91,2)) -> 386.5 | J91: ='2.1'!$H$504 -> 39.56 | K91: ='2.1'!$H$474 -> 8.08 | L91: =ROUND(K91*D91,2) -> 78.94
A92: 2.1.10 | B92: Rastreras de porcelanato; sala-comedor-estar-dormitorios | C92: ml | D92: =(51.7-1.6-0.8-0.7-0.8)+(15.8)+(17.48-0.8*4)+(17.6-0.8-0.7)+(14.2-0.8-1)+(12.48-0.8-0.7)+(15.4-0.8-0.7-0.7) -> 130.56 | E92: =IF($A92=0,"",ROUND(J92*$J$6,2)) -> 8.5 | F92: =IF($A92=0,"",ROUND(D92*E92,2)) -> 1109.76 | J92: 8.5 | K92: ='2.1'!$H$474 -> 8.08 | L92: =ROUND(K92*D92,2) -> 1054.92
A94: 2.2 | B94: CIELOS RASOS | G94: =SUM(F94:F96) -> 5930.35 | H94: =ROUND(G94/$F$182,4) -> 0.0379
A95: 2.2.01 | B95: Gypsum (tipo losa) | C95: m2 | D95: =148.4-6.17+133.6 -> 275.83 | E95: =IF($A95=0,"",ROUND(J95*$J$6,2)) -> 21.5 | F95: =IF($A95=0,"",ROUND(D95*E95,2)) -> 5930.35 | J95: 21.5 | K95: 3.38 | L95: =ROUND(K95*D95,2) -> 932.31
A97: 2.3 | B97: CARPINTERIA: ALUMINIO - VIDRIO | G97: =SUM(F97:F101) -> 8369.21 | H97: =ROUND(G97/$F$182,4) -> 0.0535
A98: 2.3.01 | B98: Ventanas aluminio y vidrio | C98: m2 | D98: 70.89 | E98: =IF($A98=0,"",ROUND(J98*$J$6,2)) -> 70.89 | F98: =IF($A98=0,"",ROUND(D98*E98,2)) -> 5025.39 | J98: ='2.3'!$H$56 -> 70.89 | L98: =ROUND(K98*D98,2) -> 0
A99: 2.3.02 | B99: Puertas aluminio y vidrio | C99: m2 | D99: 15.29 | E99: =IF($A99=0,"",ROUND(J99*$J$6,2)) -> 130.4 | F99: =IF($A99=0,"",ROUND(D99*E99,2)) -> 1993.82 | J99: 130.4 | L99: =ROUND(K99*D99,2) -> 0
A100: 2.3.03 | B100: Pasamanos | C100: ml | D100: =2.6+4.9 -> 7.5 | E100: =IF($A100=0,"",ROUND(J100*$J$6,2)) -> 180 | F100: =IF($A100=0,"",ROUND(D100*E100,2)) -> 1350 | J100: 180 | L100: =ROUND(K100*D100,2) -> 0
A102: 2.4 | B102: CARPINTERIA: MADERA | G102: =SUM(F102:F111) -> 9203.31 | H102: =ROUND(G102/$F$182,4) -> 0.0588
A103: 2.4.01 | B103: Puertas madera (1,60m x 2. 50m) Principal | C103: u | D103: 1 | E103: =IF($A103=0,"",ROUND(J103*$J$6,2)) -> 663.2 | F103: =IF($A103=0,"",ROUND(D103*E103,2)) -> 663.2 | J103: ='2.5'!$H$56*2+100 -> 663.2 | K103: 48 | L103: =ROUND(K103*D103,2) -> 48
A104: 2.4.02 | B104: Puertas madera (0.80m x 2. 00m) Cocina | C104: u | D104: 1 | E104: =IF($A104=0,"",ROUND(J104*$J$6,2)) -> 305.95 | F104: =IF($A104=0,"",ROUND(D104*E104,2)) -> 305.95 | J104: ='2.5'!$H$280 -> 305.95 | K104: ='2.5'!$H$82 -> 50.58 | L104: =ROUND(K104*D104,2) -> 50.58
A105: 2.4.03 | B105: Puertas madera (0.80m x 2. 00m) | C105: u | D105: =3+4 -> 7 | E105: =IF($A105=0,"",ROUND(J105*$J$6,2)) -> 266.4 | F105: =IF($A105=0,"",ROUND(D105*E105,2)) -> 1864.8 | J105: ='2.5'!$H$112 -> 266.4 | K105: ='2.5'!$H$82 -> 50.58 | L105: =ROUND(K105*D105,2) -> 354.06
A106: 2.4.04 | B106: Puertas madera (0.70m x 2. 00m) | C106: u | D106: =3+5 -> 8 | E106: =IF($A106=0,"",ROUND(J106*$J$6,2)) -> 258.47 | F106: =IF($A106=0,"",ROUND(D106*E106,2)) -> 2067.76 | J106: ='2.5'!$H$168 -> 258.47 | K106: ='2.5'!$H$82 -> 50.58 | L106: =ROUND(K106*D106,2) -> 404.64
A107: 2.4.05 | B107: Puertas madera (0.60m x 2. 00m) | C107: u | D107: 1 | E107: =IF($A107=0,"",ROUND(J107*$J$6,2)) -> 253.32 | F107: =IF($A107=0,"",ROUND(D107*E107,2)) -> 253.32 | J107: ='2.5'!$H$224 -> 253.32 | K107: ='2.5'!$H$82 -> 50.58 | L107: =ROUND(K107*D107,2) -> 50.58
A108: 2.4.06 | B108: Closets | C108: Global | D108: 1 | E108: =IF($A108=0,"",ROUND(J108*$J$6,2)) -> 1490.3 | F108: =IF($A108=0,"",ROUND(D108*E108,2)) -> 1490.3 | J108: 1490.3 | K108: ='2.5'!$H$82 -> 50.58 | L108: =ROUND(K108*D108,2) -> 50.58
A109: 2.4.07 | B109: Anaqueles de cocina bajo meson | C109: ml | D109: =1.15+1.15+1.17+1.16+0.63 -> 5.26 | E109: =IF($A109=0,"",ROUND(J109*$J$6,2)) -> 229.4 | F109: =IF($A109=0,"",ROUND(D109*E109,2)) -> 1206.64 | J109: 229.4 | K109: ='2.5'!$H$82 -> 50.58 | L109: =ROUND(K109*D109,2) -> 266.05
A110: 2.4.08 | B110: Anaqueles de cocina sobre meson | C110: ml | D110: =3.5+3.17 -> 6.67 | E110: =IF($A110=0,"",ROUND(J110*$J$6,2)) -> 202.6 | F110: =IF($A110=0,"",ROUND(D110*E110,2)) -> 1351.34 | J110: 202.6 | K110: ='2.5'!$H$82 -> 50.58 | L110: =ROUND(K110*D110,2) -> 337.37
A112: 2.5 | B112: OBRAS ADICIONALES | G112: =SUM(F112:F123) -> 10909.48 | H112: =ROUND(G112/$F$182,4) -> 0.0697
A113: 2.5.01 | B113: Cerramiento (inc. Mamposteria y estructura) | C113: m2 | D113: =((1.8+2.66+9.03+3.88)+(20.09+25.78))*2.4 -> 151.776 | E113: =IF($A113=0,"",ROUND(J113*$J$6,2)) -> 30.61 | F113: =IF($A113=0,"",ROUND(D113*E113,2)) -> 4645.86 | J113: 30.61 | K113: ='1.9'!H2069/2.6 -> 0 | L113: =ROUND(K113*D113,2) -> 0
A114: 2.5.02 | B114: Enlucido Cerramiento ( lateral 1 lado) | C114: m2 | D114: =((20.09+25.78))*2.4 -> 110.088 | E114: =IF($A114=0,"",ROUND(J114*$J$6,2)) -> 6.71 | F114: =IF($A114=0,"",ROUND(D114*E114,2)) -> 738.69 | J114: ='1.9'!$H$840 -> 6.71 | K114: ='1.9'!$H$810 -> 4.45 | L114: =ROUND(K114*D114,2) -> 489.89
A115: 2.5.03 | B115: Enlucido Cerramiento (frontal 2 lados) | C115: m2 | D115: =((1.8+2.66+9.03+3.88)*2)*2.4 -> 83.376 | E115: =IF($A115=0,"",ROUND(J115*$J$6,2)) -> 6.71 | F115: =IF($A115=0,"",ROUND(D115*E115,2)) -> 559.45 | J115: ='1.9'!$H$840 -> 6.71 | K115: ='1.9'!$H$810 -> 4.45 | L115: =ROUND(K115*D115,2) -> 371.02
A116: 2.5.04 | B116: Pintura cerramiento: ( lateral 1 lado+frontal 2 lados) | C116: m2 | D116: =((1.8+2.66+9.03+3.88)*2+(20.09+25.78))*2.4 -> 193.464 | E116: =IF($A116=0,"",ROUND(J116*$J$6,2)) -> 5.73 | F116: =IF($A116=0,"",ROUND(D116*E116,2)) -> 1108.55 | J116: ='2.1'!$H$112 -> 5.73 | K116: ='2.1'!$H$82 -> 2.25 | L116: =ROUND(K116*D116,2) -> 435.29
...

Sheet CRONOGRAMA
B1: =PRESUPUESTO!A1 -> FORMATO PARA PRESUPUESTO
B2: =PRESUPUESTO!B3 -> 0 | F2: …. | G2: …. | H2: …. | I2: …. | J2: …. | K2: …. | L2: …. | M2: …. | N2: …. | O2: …. | P2: …. | Q2: …. | R2: …. | S2: …. | T2: …. | U2: …. | V2: …. | W2: …. | X2: …. | Y2: …. | Z2: …. | AA2: …. | AB2: …. | AC2: …. | AD2: …. | AE2: …. | AF2: …. | AG2: …. | AH2: …. | AI2: …. | AJ2: …. | AK2: ….
B3: CRONOGRAMA VALORADO
F4: 2024
F5: Abril | J5: Mayo | N5: Junio | R5: Julio | V5: Agosto | Z5: Septiembre | AD5: Octubre | AH5: Noviembre
C6: RUBROS | F6: MES 1 | J6: MES 2 | N6: MES 3 | R6: MES 4 | V6: MES 5 | Z6: MES 6 | AD6: MES 7 | AH6: MES 8
F7: 1 | G7: 2 | H7: 3 | I7: 4 | J7: 1 | K7: 2 | L7: 3 | M7: 4 | N7: 1 | O7: 2 | P7: 3 | Q7: 4 | R7: 1 | S7: 2 | T7: 3 | U7: 4 | V7: 1 | W7: 2 | X7: 3 | Y7: 4 | Z7: 1 | AA7: 2 | AB7: 3 | AC7: 4 | AD7: 1 | AE7: 2 | AF7: 3 | AG7: 4 | AH7: 1 | AI7: 2 | AJ7: 3 | AK7: 4
B8: 1.1 | C8: INSTALACIONES PROVISIONALES | D8: =VLOOKUP(C8,PRESUPUESTO!$B$10:$G$180,6,FALSE) -> 1405.35 | E8: 1 | F8: =ROUND($D8/$E8,2) -> 1405.35 | AM8: =SUM(F8:AL8) -> 1405.35 | AO8: =+D8-AM8 -> 0
B9: 1.2 | C9: MANTENIMIENTO DE OBRA | D9: =VLOOKUP(C9,PRESUPUESTO!$B$10:$G$180,6,FALSE) -> 2992.64 | E9: 32 | F9: =ROUND($D9/$E9,2) -> 93.52 | G9: =ROUND($D9/$E9,2) -> 93.52 | H9: =ROUND($D9/$E9,2) -> 93.52 | I9: =ROUND($D9/$E9,2) -> 93.52 | J9: =ROUND($D9/$E9,2) -> 93.52 | K9: =ROUND($D9/$E9,2) -> 93.52 | L9: =ROUND($D9/$E9,2) -> 93.52 | M9: =ROUND($D9/$E9,2) -> 93.52 | ... AK9: =ROUND($D9/$E9,2) -> 93.52 | AM9: =SUM(F9:AL9) -> 2992.64 | AO9: =+D9-AM9 -> 0
B10: 1.3 | C10: PREPARACION DEL TERRENO | D10: =VLOOKUP(C10,PRESUPUESTO!$B$10:$G$180,6,FALSE) -> 523.08 | E10: 1 | F10: =ROUND($D10/$E10,2) -> 523.08 | AM10: =SUM(F10:AL10) -> 523.08 | AO10: =+D10-AM10 -> 0
B11: 1.4 | C11: MOVIMIENTOS DE TIERRA | D11: =VLOOKUP(C11,PRESUPUESTO!$B$10:$G$180,6,FALSE) -> 1991.29 | E11: 2 | F11: =ROUND($D11/$E11,2) -> 995.65 | G11: =ROUND($D11/$E11,2) -> 995.65 | AM11: =SUM(F11:AL11) -> 1991.3 | AO11: =+D11-AM11 -> -0.01
C12: Excavación para cimientos (Manual) | AM12: =SUM(F12:AL12) -> 0 | AO12: =+D12-AM12 -> 0
C13: Relleno compactado con material importado | AM13: =SUM(F13:AL13) -> 0 | AO13: =+D13-AM13 -> 0
C14: Desalojo | AM14: =SUM(F14:AL14) -> 0 | AO14: =+D14-AM14 -> 0
B15: 1.5 | C15: ESTRUCTURAS DE HORMIGON SIMPLE | D15: =VLOOKUP(C15,PRESUPUESTO!$B$10:$G$180,6,FALSE) -> 999.96 | E15: 4 | G15: =ROUND($D15/$E15,2) -> 249.99 | H15: =ROUND($D15/$E15,2) -> 249.99 | I15: =ROUND($D15/$E15,2) -> 249.99 | J15: =ROUND($D15/$E15,2) -> 249.99 | AM15: =SUM(F15:AL15) -> 999.96 | AO15: =+D15-AM15 -> 0
C16: Replantillo | AM16: =SUM(F16:AL16) -> 0 | AO16: =+D16-AM16 -> 0
C17: Muro Ciclopeo | AM17: =SUM(F17:AL17) -> 0 | AO17: =+D17-AM17 -> 0
B18: 1.6 | C18: ESTRUCTURAS DE HORMIGON ARMADO | D18: =VLOOKUP(C18,PRESUPUESTO!$B$10:$G$180,6,FALSE) -> 31688.78 | E18: 12 | I18: =ROUND($D18/$E18,2) -> 2640.73 | J18: =ROUND($D18/$E18,2) -> 2640.73 | K18: =ROUND($D18/$E18,2) -> 2640.73 | L18: =ROUND($D18/$E18,2) -> 2640.73 | M18: =ROUND($D18/$E18,2) -> 2640.73 | N18: =ROUND($D18/$E18,2) -> 2640.73 | O18: =ROUND($D18/$E18,2) -> 2640.73 | P18: =ROUND($D18/$E18,2) -> 2640.73 | ... T18: =ROUND($D18/$E18,2) -> 2640.73 | AM18: =SUM(F18:AL18) -> 31688.76 | AO18: =+D18-AM18 -> 0.02
C19: Zapata y viga de cimentacion, Riostras | AM19: =SUM(F19:AL19) -> 0 | AO19: =+D19-AM19 -> 0
C20: Columnas: cimiento a losa; losa a cubierta, Garaje | AM20: =SUM(F20:AL20) -> 0 | AO20: =+D20-AM20 -> 0
C21: Hormigon armado en Losa e= 25cm,Macizos y Vigas de losa, Escalera | AM21: =SUM(F21:AL21) -> 0 | AO21: =+D21-AM21 -> 0
C22: Cisterna | AM22: =SUM(F22:AL22) -> 0 | AO22: =+D22-AM22 -> 0
C23: Vigas de cubierta; Hormigon armado en Losa garaje | AM23: =SUM(F23:AL23) -> 0 | AO23: =+D23-AM23 -> 0
B24: 1.7 | C24: ESTRUCTURAS METALICAS Y CUBIERTAS | D24: =VLOOKUP(C24,PRESUPUESTO!$B$10:$G$180,6,FALSE) -> 9632.67 | E24: 10 | M24: =ROUND($D24/$E24,2) -> 963.27 | N24: =ROUND($D24/$E24,2) -> 963.27 | O24: =ROUND($D24/$E24,2) -> 963.27 | P24: =ROUND($D24/$E24,2) -> 963.27 | Q24: =ROUND($D24/$E24,2) -> 963.27 | R24: =ROUND($D24/$E24,2) -> 963.27 | S24: =ROUND($D24/$E24,2) -> 963.27 | T24: =ROUND($D24/$E24,2) -> 963.27 | ... V24: =ROUND($D24/$E24,2) -> 963.27 | AM24: =SUM(F24:AL24) -> 9632.7 | AO24: =+D24-AM24 -> -0.03
C25: Estructuras metalicas: de cubierta | AM25: =SUM(F25:AL25) -> 0 | AO25: =+D25-AM25 -> 0
C26: Cubierta Eternit | AM26: =SUM(F26:AL26) -> 0 | AO26: =+D26-AM26 -> 0
C27: Tejas sobre cubierta | AM27: =SUM(F27:AL27) -> 0 | AO27: =+D27-AM27 -> 0
B28: 1.8 | C28: CONTRAPISOS | D28: =VLOOKUP(C28,PRESUPUESTO!$B$10:$G$180,6,FALSE) -> 1403.06 | E28: 2 | K28: =ROUND($D28/$E28,2) -> 701.53 | L28: =ROUND($D28/$E28,2) -> 701.53 | AM28: =SUM(F28:AL28) -> 1403.06 | AO28: =+D28-AM28 -> 0
B29: 1.9 | C29: ALBAÑILERIA | E29: 12 | N29: =ROUND($D29/$E29,2) -> 0 | O29: =ROUND($D29/$E29,2) -> 0 | P29: =ROUND($D29/$E29,2) -> 0 | Q29: =ROUND($D29/$E29,2) -> 0 | R29: =ROUND($D29/$E29,2) -> 0 | S29: =ROUND($D29/$E29,2) -> 0 | T29: =ROUND($D29/$E29,2) -> 0 | U29: =ROUND($D29/$E29,2) -> 0 | ... Y29: =ROUND($D29/$E29,2) -> 0 | AM29: =SUM(F29:AL29) -> 0 | AO29: =+D29-AM29 -> 0
C30: Mamposterias y Viguetas | AM30: =SUM(F30:AL30) -> 0 | AO30: =+D30-AM30 -> 0
C31: Enlucidos | AM31: =SUM(F31:AL31) -> 0 | AO31: =+D31-AM31 -> 0
C32: Mesones, muros de tina, Cajas | AM32: =SUM(F32:AL32) -> 0 | AO32: =+D32-AM32 -> 0
C33: Impermeabilizaciones | AM33: =SUM(F33:AL33) -> 0 | AO33: =+D33-AM33 -> 0
B34: 2.1 | C34: REVESTIMIENTOS Y ACABADOS | D34: =VLOOKUP(C34,PRESUPUESTO!$B$10:$G$180,6,FALSE) -> #N/A | E34: 14 | V34: =ROUND($D34/$E34,2) -> #N/A | W34: =ROUND($D34/$E34,2) -> #N/A | X34: =ROUND($D34/$E34,2) -> #N/A | Y34: =ROUND($D34/$E34,2) -> #N/A | Z34: =ROUND($D34/$E34,2) -> #N/A | AA34: =ROUND($D34/$E34,2) -> #N/A | AB34: =ROUND($D34/$E34,2) -> #N/A | AC34: =ROUND($D34/$E34,2) -> #N/A | ... AI34: =ROUND($D34/$E34,2) -> #N/A | AM34: =SUM(F34:AL34) -> #N/A | AO34: =+D34-AM34 -> #N/A
C35: Ceramicas y porcelanatos en pisos | AM35: =SUM(F35:AL35) -> 0 | AO35: =+D35-AM35 -> 0
C36: Revestimiento de mesones y escalera | AM36: =SUM(F36:AL36) -> 0 | AO36: =+D36-AM36 -> 0
C37: Pintura interior y exterior | AM37: =SUM(F37:AL37) -> 0 | AO37: =+D37-AM37 -> 0
B38: 2.2 | C38: CIELOS RASOS | D38: =VLOOKUP(C38,PRESUPUESTO!$B$10:$G$180,6,FALSE) -> 5930.35 | E38: 7 | AA38: =ROUND($D38/$E38,2) -> 847.19 | AB38: =ROUND($D38/$E38,2) -> 847.19 | AC38: =ROUND($D38/$E38,2) -> 847.19 | AD38: =ROUND($D38/$E38,2) -> 847.19 | AE38: =ROUND($D38/$E38,2) -> 847.19 | AF38: =ROUND($D38/$E38,2) -> 847.19 | AG38: =ROUND($D38/$E38,2) -> 847.19 | AM38: =SUM(F38:AL38) -> 5930.33 | AO38: =+D38-AM38 -> 0.02
B39: 2.3 | C39: CARPINTERIA: ALUMINIO / VIDRIO | D39: =VLOOKUP(C39,PRESUPUESTO!$B$10:$G$180,6,FALSE) -> #N/A | E39: 7 | AC39: =ROUND($D39/$E39,2) -> #N/A | AD39: =ROUND($D39/$E39,2) -> #N/A | AE39: =ROUND($D39/$E39,2) -> #N/A | AF39: =ROUND($D39/$E39,2) -> #N/A | AG39: =ROUND($D39/$E39,2) -> #N/A | AH39: =ROUND($D39/$E39,2) -> #N/A | AI39: =ROUND($D39/$E39,2) -> #N/A | AM39: =SUM(F39:AL39) -> #N/A | AO39: =+D39-AM39 -> #N/A
B40: 2.4 | C40: CARPINTERIA: MADERA | D40: =VLOOKUP(C40,PRESUPUESTO!$B$10:$G$180,6,FALSE) -> 9203.31 | E40: 6 | AF40: =ROUND($D40/$E40,2) -> 1533.89 | AG40: =ROUND($D40/$E40,2) -> 1533.89 | AH40: =ROUND($D40/$E40,2) -> 1533.89 | AI40: =ROUND($D40/$E40,2) -> 1533.89 | AJ40: =ROUND($D40/$E40,2) -> 1533.89 | AK40: =ROUND($D40/$E40,2) -> 1533.89 | AM40: =SUM(F40:AL40) -> 9203.34 | AO40: =+D40-AM40 -> -0.03
B41: 2.5 | C41: OBRAS EXTERIORES | D41: =VLOOKUP(C41,PRESUPUESTO!$B$10:$G$180,6,FALSE) -> #N/A | E41: 12 | Z41: =ROUND($D41/$E41,2) -> #N/A | AA41: =ROUND($D41/$E41,2) -> #N/A | AB41: =ROUND($D41/$E41,2) -> #N/A | AC41: =ROUND($D41/$E41,2) -> #N/A | AD41: =ROUND($D41/$E41,2) -> #N/A | AE41: =ROUND($D41/$E41,2) -> #N/A | AF41: =ROUND($D41/$E41,2) -> #N/A | AG41: =ROUND($D41/$E41,2) -> #N/A | ... AK41: =ROUND($D41/$E41,2) -> #N/A | AM41: =SUM(F41:AL41) -> #N/A | AO41: =+D41-AM41 -> #N/A
B42: 3.0 | C42: SISTEMA HIDRÁULICO SANITARIO | D42: =VLOOKUP(C42,PRESUPUESTO!$B$10:$G$180,6,FALSE) -> 9768.36 | E42: 26 | J42: =ROUND($D42/$E42,2) -> 375.71 | K42: =ROUND($D42/$E42,2) -> 375.71 | L42: =ROUND($D42/$E42,2) -> 375.71 | M42: =ROUND($D42/$E42,2) -> 375.71 | N42: =ROUND($D42/$E42,2) -> 375.71 | O42: =ROUND($D42/$E42,2) -> 375.71 | P42: =ROUND($D42/$E42,2) -> 375.71 | Q42: =ROUND($D42/$E42,2) -> 375.71 | ... AI42: =ROUND($D42/$E42,2) -> 375.71 | AM42: =SUM(F42:AL42) -> 9768.46 | AO42: =+D42-AM42 -> -0.1
C43: PIEZAS SANITARIAS | D43: =VLOOKUP(C43,PRESUPUESTO!$B$10:$G$180,6,FALSE) -> 5007.08 | E43: 4 | AH43: =ROUND($D43/$E43,2) -> 1251.77 | AI43: =ROUND($D43/$E43,2) -> 1251.77 | AJ43: =ROUND($D43/$E43,2) -> 1251.77 | AK43: =ROUND($D43/$E43,2) -> 1251.77 | AM43: =SUM(F43:AL43) -> 5007.08 | AO43: =+D43-AM43 -> 0
B44: 4.0 | C44: SISTEMA INSTALACIONES ELECTRICAS | D44: =VLOOKUP(C44,PRESUPUESTO!$B$10:$G$180,6,FALSE) -> 11623.77 | E44: 26 | L44: =ROUND($D44/$E44,2) -> 447.07 | M44: =ROUND($D44/$E44,2) -> 447.07 | N44: =ROUND($D44/$E44,2) -> 447.07 | O44: =ROUND($D44/$E44,2) -> 447.07 | P44: =ROUND($D44/$E44,2) -> 447.07 | Q44: =ROUND($D44/$E44,2) -> 447.07 | R44: =ROUND($D44/$E44,2) -> 447.07 | S44: =ROUND($D44/$E44,2) -> 447.07 | ... AK44: =ROUND($D44/$E44,2) -> 447.07 | AM44: =SUM(F44:AL44) -> 11623.82 | AO44: =+D44-AM44 -> -0.05
D45: =VLOOKUP(C45,PRESUPUESTO!$B$10:$G$180,6,FALSE) -> #N/A | AM45: =SUM(F45:AL45) -> 0 | AO45: =+D45-AM45 -> #N/A
C46: COSTOS DIRECTOS | D46: =SUM(D8:D45) -> #N/A | F46: =SUM(F8:I45) -> 7684.51 | J46: =SUM(J8:M45) -> 15950.3 | N46: =SUM(N8:Q45) -> 18081.2 | R46: =SUM(R8:U45) -> 15440.47 | V46: =SUM(V8:Y45) -> #N/A | Z46: =SUM(Z8:AC45) -> #N/A | AD46: =SUM(AD8:AG45) -> #N/A | AH46: =SUM(AH8:AK45) -> #N/A
B47: =PRESUPUESTO!$E$183 -> 0.2 | C47: COSTOS INDIRECTOS | D47: =ROUND(D46*$B$47,2) -> #N/A | F47: =ROUND(F46*$B$47,2) -> 1536.9 | G47: =ROUND(G46*$B$47,2) -> 0 | H47: =ROUND(H46*$B$47,2) -> 0 | I47: =ROUND(I46*$B$47,2) -> 0 | J47: =ROUND(J46*$B$47,2) -> 3190.06 | K47: =ROUND(K46*$B$47,2) -> 0 | L47: =ROUND(L46*$B$47,2) -> 0 | M47: =ROUND(M46*$B$47,2) -> 0 | ... AK47: =ROUND(AK46*$B$47,2) -> 0
C48: TOTAL COSTOS DIRECTOS + INDIRECTOS | D48: =SUM(D46:D47) -> #N/A | F48: =SUM(F46:I47) -> 9221.41 | J48: =SUM(J46:M47) -> 19140.36 | N48: =SUM(N46:Q47) -> 21697.44 | R48: =SUM(R46:U47) -> 18528.56 | V48: =SUM(V46:V47) -> #N/A | Z48: =SUM(Z46:Z47) -> #N/A | AD48: =SUM(AD46:AD47) -> #N/A | AH48: =SUM(AH46:AH47) -> #N/A
C50: COSTO DE LA OBRA | D50: =SUM(D48:D49) -> #N/A | F50: =SUM(F48:I49) -> 9221.41 | J50: =SUM(J48:M49) -> 19140.36 | N50: =SUM(N48:Q49) -> 21697.44 | R50: =SUM(R48:U49) -> 18528.56 | V50: =SUM(V48:V49) -> #N/A | Z50: =SUM(Z48:Z49) -> #N/A | AD50: =SUM(AD48:AD49) -> #N/A | AH50: =SUM(AH48:AH49) -> #N/A
C53: FLUJO PARCIAL | F53: =F50 -> 9221.41 | J53: =J50 -> 19140.36 | N53: =N50 -> 21697.44 | R53: =R50 -> 18528.56 | V53: =V50 -> #N/A | Z53: =Z50 -> #N/A | AD53: =AD50 -> #N/A | AH53: =AH50 -> #N/A
C54: PORCENTAJE PARCIAL | F54: =ROUND(F50*1/$D$50,4) -> #N/A | J54: =ROUND(J50*1/$D$50,4) -> #N/A | N54: =ROUND(N50*1/$D$50,4) -> #N/A | R54: =ROUND(R50*1/$D$50,4) -> #N/A | V54: =ROUND(V50*1/$D$50,4) -> #N/A | Z54: =ROUND(Z50*1/$D$50,4) -> #N/A | AD54: =ROUND(AD50*1/$D$50,4) -> #N/A | AH54: =ROUND(AH50*1/$D$50,4)-0.0001 -> #N/A
C55: FLUJO ACUMULADO | D55: =D50 -> #N/A | F55: =F53 -> 9221.41 | J55: =J53+F55 -> 28361.77 | N55: =N53+J55 -> 50059.21 | R55: =R53+N55 -> 68587.77 | V55: =V53+R55 -> #N/A | Z55: =Z53+V55 -> #N/A | AD55: =AD53+Z55 -> #N/A | AH55: =AH53+AD55 -> #N/A
C56: PORCENTAJE ACUMULADO | F56: =+F54 -> #N/A | J56: =+F56+J54 -> #N/A | N56: =+J56+N54 -> #N/A | R56: =+N56+R54 -> #N/A | V56: =+R56+V54 -> #N/A | Z56: =+V56+Z54 -> #N/A | AD56: =+Z56+AD54 -> #N/A | AH56: =+AD56+AH54 -> #N/A
B61: CRONOGRAMA DE AVANCE DE OBRA (%)
B63: PRESUPUESTO | E63: TIEMPO EN SEMANAS | AC63: TIEMPO EN SEMANAS | BA63: SUMA
B64: ÍTEM | C64: DESCRIPCIÓN | D64: PRECIO TOTAL | E64: 1 | F64: 2 | G64: 3 | H64: 4 | I64: 5 | J64: 6 | K64: 7 | L64: 8 | M64: 9 | N64: 10 | O64: 11 | P64: 12 | Q64: 13 | R64: 14 | S64: 15 | T64: 16 | U64: 17 | V64: 18 | W64: 19 | X64: 20 | Y64: 21 | Z64: 22 | AA64: 23 | AB64: 24 | AC64: 25 | AD64: 26 | AE64: 27 | AF64: 28 | AG64: 29 | AH64: 30 | AI64: 31 | AJ64: 32 | AK64: 33 | AL64: 34 | AM64: 35 | AN64: 36 | AO64: 37 | AP64: 38 | AQ64: 39 | AR64: 40 | AS64: 41 | AT64: 42 | AU64: 43 | AV64: 44 | AW64: 45 | AX64: 46 | AY64: 47 | AZ64: 48
B65: 1 | C65: =+PRESUPUESTO!B9 -> OBRA GRIS | D65: =+PRESUPUESTO!G9 -> 81220.85 | E65: 0.2 | F65: 0.2 | H65: 0.2 | J65: 0.2 | M65: 0.2 | BA65: =SUM(E65:AZ65) -> 1
B66: 2 | C66: =+PRESUPUESTO!B10 -> 0 | D66: =+PRESUPUESTO!G10 -> 0 | G66: 0.06 | H66: 0.02 | I66: 0.06 | J66: 0.02 | K66: 0.06 | L66: 0.11 | P66: 0.13 | T66: 0.13 | X66: 0.13 | AB66: 0.13 | AF66: 0.13 | AV66: 0.02 | BA66: =SUM(E66:AZ66) -> 1
B67: 3 | C67: =+PRESUPUESTO!B11 -> INSTALACIONES PROVISIONALES | D67: =+PRESUPUESTO!G11 -> 1405.35 | Q67: 0.2 | U67: 0.2 | Y67: 0.2 | AC67: 0.2 | AG67: 0.1 | AK67: 0.1 | BA67: =SUM(E67:AZ67) -> 1
B68: 4 | C68: =+PRESUPUESTO!B12 -> Caseta de oficina, bodega y guardiania | D68: =+PRESUPUESTO!G12 -> 0 | AE68: 0.15 | AF68: 0.15 | AG68: 0.15 | AH68: 0.15 | AI68: 0.15 | AJ68: 0.1 | AL68: 0.1 | AN68: 0.05 | BA68: =SUM(E68:AZ68) -> 1
B69: 5 | C69: =+PRESUPUESTO!B13 -> Instalación eléctrica provisional | D69: =+PRESUPUESTO!G13 -> 0 | E69: 0.2 | AI69: 0.15 | AK69: 0.15 | AM69: 0.15 | AO69: 0.15 | AQ69: 0.1 | AS69: 0.1 | BA69: =SUM(E69:AZ69) -> 1
B70: 6 | C70: =+PRESUPUESTO!B14 -> Instalación AAPP provisional | D70: =+PRESUPUESTO!G14 -> 0 | AJ70: 0.05 | AR70: 0.2 | AT70: 0.2 | AU70: 0.2 | AW70: 0.2 | AX70: 0.15 | BA70: =SUM(E70:AZ70) -> 1
B71: 7 | C71: =+PRESUPUESTO!B15 -> Cerramiento de Obra | D71: =+PRESUPUESTO!G15 -> 0 | E71: 0.2 | AH71: 0.12 | AJ71: 0.12 | AL71: 0.12 | AN71: 0.12 | AP71: 0.12 | AR71: 0.12 | AV71: 0.06 | AX71: 0.02 | BA71: =SUM(E71:AZ71) -> 1
B72: 8 | C72: =+PRESUPUESTO!B16 -> MANTENIMIENTO DE OBRA | D72: =+PRESUPUESTO!G16 -> 2992.64 | R72: 0.2 | S72: 0.2 | AE72: 0.1 | AG72: 0.3 | AK72: 0.1 | AO72: 0.1 | BA72: =SUM(E72:AZ72) -> 1
B73: 9 | C73: =+PRESUPUESTO!B17 -> Limpieza general de la obra | D73: =+PRESUPUESTO!G17 -> 0 | G73: 0.16 | AO73: 0.12 | AP73: 0.12 | AQ73: 0.12 | AR73: 0.12 | AS73: 0.12 | AT73: 0.12 | AU73: 0.12 | BA73: =SUM(E73:AZ73) -> 1
B74: 10 | C74: =+PRESUPUESTO!B18 -> Desalojo de limpieza | D74: =+PRESUPUESTO!G18 -> 0 | AS74: 0.04 | AT74: 0.03 | AU74: 0.02 | AV74: 0.18 | AW74: 0.18 | AX74: 0.3 | AY74: 0.25 | BA74: =SUM(E74:AZ74) -> 1
B75: 11 | C75: =+PRESUPUESTO!B19 -> 0 | D75: =+PRESUPUESTO!G19 -> 0 | G75: 0.15 | AO75: 0.2 | AP75: 0.2 | AQ75: 0.2 | AW75: 0.2 | AX75: 0.05 | BA75: =SUM(E75:AZ75) -> 1
B76: 12 | C76: =+PRESUPUESTO!B20 -> PREPARACION DEL TERRENO | D76: =+PRESUPUESTO!G20 -> 523.08 | G76: 0.15 | I76: 0.09 | K76: 0.09 | L76: 0.18 | P76: 0.09 | T76: 0.09 | X76: 0.09 | AB76: 0.06 | AD76: 0.04 | AE76: 0.04 | AF76: 0.04 | AG76: 0.04 | BA76: =SUM(E76:AZ76) -> 1
B77: 13 | C77: =+PRESUPUESTO!B21 -> Limpieza del terreno | D77: =+PRESUPUESTO!G21 -> 0 | F77: 0.35 | J77: 0.2 | N77: 0.1 | R77: 0.05 | V77: 0.1 | Z77: 0.1 | AL77: 0.05 | AN77: 0.05 | BA77: =SUM(E77:AZ77) -> 1
B78: 14 | C78: =+PRESUPUESTO!B22 -> Replanteo y trazado de cimientos | D78: =+PRESUPUESTO!G22 -> 0 | H78: 0.3 | J78: 0.3 | L78: 0.3 | AZ78: 0.1 | BA78: =SUM(E78:AZ78) -> 1
B79: VALOR DEL PRESUPUESTO | D79: =+SUM(D65:D78) -> 86141.92
B81: CRONOGRAMA VALORADO DE OBRA
B83: PRESUPUESTO | E83: TIEMPO EN SEMANAS | AC83: TIEMPO EN SEMANAS | BA83: SUMA
B84: ÍTEM | C84: DESCRIPCIÓN | D84: PRECIO TOTAL | E84: 1 | F84: 2 | G84: 3 | H84: 4 | I84: 5 | J84: 6 | K84: 7 | L84: 8 | M84: 9 | N84: 10 | O84: 11 | P84: 12 | Q84: 13 | R84: 14 | S84: 15 | T84: 16 | U84: 17 | V84: 18 | W84: 19 | X84: 20 | Y84: 21 | Z84: 22 | AA84: 23 | AB84: 24 | AC84: 25 | AD84: 26 | AE84: 27 | AF84: 28 | AG84: 29 | AH84: 30 | AI84: 31 | AJ84: 32 | AK84: 33 | AL84: 34 | AM84: 35 | AN84: 36 | AO84: 37 | AP84: 38 | AQ84: 39 | AR84: 40 | AS84: 41 | AT84: 42 | AU84: 43 | AV84: 44 | AW84: 45 | AX84: 46 | AY84: 47 | AZ84: 48
B85: 1 | C85: TRABAJOS DE CAMPO Y MOVIMIENTOS DE TIERRA | D85: =D65 -> 81220.85 | E85: =E65*$C$5 -> 0 | F85: =F65*$C$5 -> 0 | G85: =G65*$C$5 -> 0 | H85: =H65*$C$5 -> 0 | I85: =I65*$C$5 -> 0 | J85: =J65*$C$5 -> 0 | K85: =K65*$C$5 -> 0 | L85: =L65*$C$5 -> 0 | ... AZ85: =AZ65*$C$5 -> 0 | BA85: =SUM(E85:AZ85) -> 0
B86: 2 | C86: HORMIGONES / ESTRUCTURA | D86: =D66 -> 0 | E86: =E66*$C$6 -> #VALUE! | F86: =F66*$C$6 -> #VALUE! | G86: =G66*$C$6 -> #VALUE! | H86: =H66*$C$6 -> #VALUE! | I86: =I66*$C$6 -> #VALUE! | J86: =J66*$C$6 -> #VALUE! | K86: =K66*$C$6 -> #VALUE! | L86: =L66*$C$6 -> #VALUE! | ... AZ86: =AZ66*$C$6 -> #VALUE! | BA86: =SUM(E86:AZ86) -> #VALUE!
B87: 3 | C87: MAMPOSTERIAS | D87: =D67 -> 1405.35 | E87: =E67*$C$7 -> 0 | F87: =F67*$C$7 -> 0 | G87: =G67*$C$7 -> 0 | H87: =H67*$C$7 -> 0 | I87: =I67*$C$7 -> 0 | J87: =J67*$C$7 -> 0 | K87: =K67*$C$7 -> 0 | L87: =L67*$C$7 -> 0 | ... AZ87: =AZ67*$C$7 -> 0 | BA87: =SUM(E87:AZ87) -> 0
B88: 4 | C88: ENLUCIDOS | D88: =D68 -> 0 | E88: =E68*$C$8 -> #VALUE! | F88: =F68*$C$8 -> #VALUE! | G88: =G68*$C$8 -> #VALUE! | H88: =H68*$C$8 -> #VALUE! | I88: =I68*$C$8 -> #VALUE! | J88: =J68*$C$8 -> #VALUE! | K88: =K68*$C$8 -> #VALUE! | L88: =L68*$C$8 -> #VALUE! | ... AZ88: =AZ68*$C$8 -> #VALUE! | BA88: =SUM(E88:AZ88) -> #VALUE!
B89: 5 | C89: PISOS | D89: =D69 -> 0 | E89: =E69*$C$9 -> #VALUE! | F89: =F69*$C$9 -> #VALUE! | G89: =G69*$C$9 -> #VALUE! | H89: =H69*$C$9 -> #VALUE! | I89: =I69*$C$9 -> #VALUE! | J89: =J69*$C$9 -> #VALUE! | K89: =K69*$C$9 -> #VALUE! | L89: =L69*$C$9 -> #VALUE! | ... AZ89: =AZ69*$C$9 -> #VALUE! | BA89: =SUM(E89:AZ89) -> #VALUE!
B90: 6 | C90: CARPINTERIA METAL/MADERA | D90: =D70 -> 0 | E90: =E70*$C$10 -> #VALUE! | F90: =F70*$C$10 -> #VALUE! | G90: =G70*$C$10 -> #VALUE! | H90: =H70*$C$10 -> #VALUE! | I90: =I70*$C$10 -> #VALUE! | J90: =J70*$C$10 -> #VALUE! | K90: =K70*$C$10 -> #VALUE! | L90: =L70*$C$10 -> #VALUE! | ... AZ90: =AZ70*$C$10 -> #VALUE! | BA90: =SUM(E90:AZ90) -> #VALUE!
B91: 7 | C91: RECUBRIMIENTOS | D91: =D71 -> 0 | E91: =E71*$C$11 -> #VALUE! | F91: =F71*$C$11 -> #VALUE! | G91: =G71*$C$11 -> #VALUE! | H91: =H71*$C$11 -> #VALUE! | I91: =I71*$C$11 -> #VALUE! | J91: =J71*$C$11 -> #VALUE! | K91: =K71*$C$11 -> #VALUE! | L91: =L71*$C$11 -> #VALUE! | ... AZ91: =AZ71*$C$11 -> #VALUE! | BA91: =SUM(E91:AZ91) -> #VALUE!
B92: 8 | C92: CUBIERTA | D92: =D72 -> 2992.64 | E92: =E72*$C$12 -> #VALUE! | F92: =F72*$C$12 -> #VALUE! | G92: =G72*$C$12 -> #VALUE! | H92: =H72*$C$12 -> #VALUE! | I92: =I72*$C$12 -> #VALUE! | J92: =J72*$C$12 -> #VALUE! | K92: =K72*$C$12 -> #VALUE! | L92: =L72*$C$12 -> #VALUE! | ... AZ92: =AZ72*$C$12 -> #VALUE! | BA92: =SUM(E92:AZ92) -> #VALUE!
B93: 9 | C93: INSTALACIONES SANITARIAS | D93: =D73 -> 0 | E93: =E73*$C$13 -> #VALUE! | F93: =F73*$C$13 -> #VALUE! | G93: =G73*$C$13 -> #VALUE! | H93: =H73*$C$13 -> #VALUE! | I93: =I73*$C$13 -> #VALUE! | J93: =J73*$C$13 -> #VALUE! | K93: =K73*$C$13 -> #VALUE! | L93: =L73*$C$13 -> #VALUE! | ... AZ93: =AZ73*$C$13 -> #VALUE! | BA93: =SUM(E93:AZ93) -> #VALUE!
B94: 10 | C94: PIEZAS SANITARIAS | D94: =D74 -> 0 | E94: =E74*$C$14 -> #VALUE! | F94: =F74*$C$14 -> #VALUE! | G94: =G74*$C$14 -> #VALUE! | H94: =H74*$C$14 -> #VALUE! | I94: =I74*$C$14 -> #VALUE! | J94: =J74*$C$14 -> #VALUE! | K94: =K74*$C$14 -> #VALUE! | L94: =L74*$C$14 -> #VALUE! | ... AZ94: =AZ74*$C$14 -> #VALUE! | BA94: =SUM(E94:AZ94) -> #VALUE!
B95: 11 | C95: INSTALACIONES HIDROSANITARIAS | D95: =D75 -> 0 | E95: =E75*$C$15 -> #VALUE! | F95: =F75*$C$15 -> #VALUE! | G95: =G75*$C$15 -> #VALUE! | H95: =H75*$C$15 -> #VALUE! | I95: =I75*$C$15 -> #VALUE! | J95: =J75*$C$15 -> #VALUE! | K95: =K75*$C$15 -> #VALUE! | L95: =L75*$C$15 -> #VALUE! | ... AZ95: =AZ75*$C$15 -> #VALUE! | BA95: =SUM(E95:AZ95) -> #VALUE!
B96: 12 | C96: INSTALACIONES ELECTRICAS | D96: =D76 -> 523.08 | E96: =E76*$C$16 -> #VALUE! | F96: =F76*$C$16 -> #VALUE! | G96: =G76*$C$16 -> #VALUE! | H96: =H76*$C$16 -> #VALUE! | I96: =I76*$C$16 -> #VALUE! | J96: =J76*$C$16 -> #VALUE! | K96: =K76*$C$16 -> #VALUE! | L96: =L76*$C$16 -> #VALUE! | ... AZ96: =AZ76*$C$16 -> #VALUE! | BA96: =SUM(E96:AZ96) -> #VALUE!
B97: 13 | C97: ADICIONALES / OBRAS EXTERIORES | D97: =D77 -> 0 | E97: =E77*$C$17 -> #VALUE! | F97: =F77*$C$17 -> #VALUE! | G97: =G77*$C$17 -> #VALUE! | H97: =H77*$C$17 -> #VALUE! | I97: =I77*$C$17 -> #VALUE! | J97: =J77*$C$17 -> #VALUE! | K97: =K77*$C$17 -> #VALUE! | L97: =L77*$C$17 -> #VALUE! | ... AZ97: =AZ77*$C$17 -> #VALUE! | BA97: =SUM(E97:AZ97) -> #VALUE!
B98: 14 | C98: IMPREVISTOS 3% | D98: =D78 -> 0 | E98: =E78*$C$18 -> #VALUE! | F98: =F78*$C$18 -> #VALUE! | G98: =G78*$C$18 -> #VALUE! | H98: =H78*$C$18 -> #VALUE! | I98: =I78*$C$18 -> #VALUE! | J98: =J78*$C$18 -> #VALUE! | K98: =K78*$C$18 -> #VALUE! | L98: =L78*$C$18 -> #VALUE! | ... AZ98: =AZ78*$C$18 -> #VALUE! | BA98: =SUM(E98:AZ98) -> #VALUE!
B99: VALOR DEL PRESUPUESTO | D99: =D79 -> 86141.92
B100: INVERSION SEMANAL ($) | E100: =SUM(E85:E98) -> #VALUE! | F100: =SUM(F85:F98) -> #VALUE! | G100: =SUM(G85:G98) -> #VALUE! | H100: =SUM(H85:H98) -> #VALUE! | I100: =SUM(I85:I98) -> #VALUE! | J100: =SUM(J85:J98) -> #VALUE! | K100: =SUM(K85:K98) -> #VALUE! | L100: =SUM(L85:L98) -> #VALUE! | ... AZ100: =SUM(AZ85:AZ98) -> #VALUE!
B101: PORCENTAJE SEMANAL (%) | E101: =E100/$C$39 -> #VALUE! | F101: =F100/$C$39 -> #VALUE! | G101: =G100/$C$39 -> #VALUE! | H101: =H100/$C$39 -> #VALUE! | I101: =I100/$C$39 -> #VALUE! | J101: =J100/$C$39 -> #VALUE! | K101: =K100/$C$39 -> #VALUE! | L101: =L100/$C$39 -> #VALUE! | ... AZ101: =AZ100/$C$39 -> #VALUE!
B102: INVERSION MENSUAL ($) | E102: =+E100+F100+G100+H100 -> #VALUE! | I102: =+I100+J100+K100+L100 -> #VALUE! | M102: =+M100+N100+O100+P100 -> #VALUE! | Q102: =+Q100+R100+S100+T100 -> #VALUE! | U102: =+U100+V100+W100+X100 -> #VALUE! | Y102: =+Y100+Z100+AA100+AB100 -> #VALUE! | AC102: =+AC100+AD100+AE100+AF100 -> #VALUE! | AG102: =+AG100+AH100+AI100+AJ100 -> #VALUE! | AK102: =+AK100+AL100+AM100+AN100 -> #VALUE! | AO102: =+AO100+AP100+AQ100+AR100 -> #VALUE! | AS102: =+AS100+AT100+AU100+AV100 -> #VALUE! | AW102: =+AW100+AX100+AY100+AZ100 -> #VALUE!
B103: PORCENTAJE MENSUAL (%) | E103: =E102/$C$39 -> #VALUE! | I103: =I102/$C$39 -> #VALUE! | M103: =M102/$C$39 -> #VALUE! | Q103: =Q102/$C$39 -> #VALUE! | U103: =U102/$C$39 -> #VALUE! | Y103: =Y102/$C$39 -> #VALUE! | AC103: =AC102/$C$39 -> #VALUE! | AG103: =AG102/$C$39 -> #VALUE! | AK103: =AK102/$C$39 -> #VALUE! | AO103: =AO102/$C$39 -> #VALUE! | AS103: =AS102/$C$39 -> #VALUE! | AW103: =AW102/$C$39 -> #VALUE!
B105: FLUJO DE CAJA DE OBRA
B107: PRESUPUESTO | E107: TIEMPO EN SEMANAS | AC107: TIEMPO EN SEMANAS | BA107: SUMA
B108: ÍTEM | C108: DESCRIPCIÓN | D108: PRECIO TOTAL | E108: 1 | F108: 2 | G108: 3 | H108: 4 | I108: 5 | J108: 6 | K108: 7 | L108: 8 | M108: 9 | N108: 10 | O108: 11 | P108: 12 | Q108: 13 | R108: 14 | S108: 15 | T108: 16 | U108: 17 | V108: 18 | W108: 19 | X108: 20 | Y108: 21 | Z108: 22 | AA108: 23 | AB108: 24 | AC108: 25 | AD108: 26 | AE108: 27 | AF108: 28 | AG108: 29 | AH108: 30 | AI108: 31 | AJ108: 32 | AK108: 33 | AL108: 34 | AM108: 35 | AN108: 36 | AO108: 37 | AP108: 38 | AQ108: 39 | AR108: 40 | AS108: 41 | AT108: 42 | AU108: 43 | AV108: 44 | AW108: 45 | AX108: 46 | AY108: 47 | AZ108: 48
B109: FLUJO PARCIAL SEMANAL ($) | E109: =E100 -> #VALUE! | F109: =F100 -> #VALUE! | G109: =G100 -> #VALUE! | H109: =H100 -> #VALUE! | I109: =I100 -> #VALUE! | J109: =J100 -> #VALUE! | K109: =K100 -> #VALUE! | L109: =L100 -> #VALUE! | ... AZ109: =AZ100 -> #VALUE! | BA109: =SUM(E109:AZ109) -> #VALUE!
B110: FLUJO ACUMULADO ($) | E110: =E109 -> #VALUE! | F110: =F109+E110 -> #VALUE! | G110: =G109+F110 -> #VALUE! | H110: =H109+G110 -> #VALUE! | I110: =I109+H110 -> #VALUE! | J110: =J109+I110 -> #VALUE! | K110: =K109+J110 -> #VALUE! | L110: =L109+K110 -> #VALUE! | M110: =M109+L110 -> #VALUE! | ... AZ110: =AZ109+AY110 -> #VALUE!
B111: AVANCE PARCIAL (%) | E111: =E109/$C$39 -> #VALUE! | F111: =F109/$C$39 -> #VALUE! | G111: =G109/$C$39 -> #VALUE! | H111: =H109/$C$39 -> #VALUE! | I111: =I109/$C$39 -> #VALUE! | J111: =J109/$C$39 -> #VALUE! | K111: =K109/$C$39 -> #VALUE! | L111: =L109/$C$39 -> #VALUE! | ... AZ111: =AZ109/$C$39 -> #VALUE! | BA111: =SUM(E111:AZ111) -> #VALUE!
B112: AVANCE ACUMULADO (%) | E112: =E109/$C$39 -> #VALUE! | F112: =F111+E112 -> #VALUE! | G112: =G111+F112 -> #VALUE! | H112: =H111+G112 -> #VALUE! | I112: =I111+H112 -> #VALUE! | J112: =J111+I112 -> #VALUE! | K112: =K111+J112 -> #VALUE! | L112: =L111+K112 -> #VALUE! | M112: =M111+L112 -> #VALUE! | ... AZ112: =AZ111+AY112 -> #VALUE!
...

Sheet CALCULO 
A1: AREAS
A2: TOTAL | B2: =SUM(C4:C63) -> 59.18 | C2: M2
A4: REPLANTEO | C4: =ROUND(E4*G4,2) -> 0 | E4: 1 | F4: M2 | G4: =SUM(H4:AP4) -> 0
A5: PISO 1 | C5: =ROUND(E5*G5,2) -> 0 | E5: 1 | F5: ML | G5: =SUM(H5:AP5) -> 0
A6: PISO 2 | C6: =ROUND(E6*G6,2) -> 0 | E6: 1 | F6: ML | G6: =SUM(H6:AP6) -> 0
G7: =SUM(H7:AP7) -> 0
A8: EXCAVACION MANUAL | G8: =SUM(H8:AG8) -> 0
A9: TOTAL | B9: =SUM(C11:C15)-B10 -> 0 | C9: M3 | G9: =SUM(H9:AG9) -> 0
G10: =SUM(H10:AG10) -> 0
A11: PLINTOS | C11: =ROUND(E11*G11,2) -> 0 | E11: 0.8 | F11: M2 | G11: =SUM(H11:AG11) -> 0
A12: RIOSTRAS | C12: =ROUND(E12*G12,2) -> 0 | E12: =0.8*0.7 -> 0.56 | F12: ML | G12: =SUM(H12:AG12) -> 0
A13: PLINTOS ESCALERA | C13: =ROUND(E13*G13,2) -> 0 | E13: 0.8 | F13: M2 | G13: =SUM(H13:AG13) -> 0
A14: RIOSTRAS ESCALERA | C14: =ROUND(E14*G14,2) -> 0 | E14: 0.8 | F14: M2 | G14: =SUM(H14:AG14) -> 0
G15: =SUM(H15:AG15) -> 0
A16: REPLANTILLO | G16: =SUM(H16:AG16) -> 0
A17: TOTAL | B17: =SUM(C19:C20) -> 5.81 | C17: M3 | G17: =SUM(H17:AG17) -> 0
G18: =SUM(H18:AG18) -> 0
A19: REPLANTILLO EN PLINTOS | C19: =ROUND(E19*G19,2) -> 3.95 | E19: 0.05 | F19: M2 | G19: =SUM(H19:AG19) -> 78.96 | H19: 211.75 | I19: 3.27 | J19: -11 | K19: -10.8 | L19: -9.9 | M19: -12.75 | N19: -1.3 | O19: -7.49 | P19: -9.36 | Q19: -8.58 | R19: -10.12 | S19: -2.2 | T19: -11.8 | U19: -14.04 | V19: -12.87 | W19: -13.85
A20: REPLANTILLO EN PLINTOS | C20: =ROUND(E20*G20,2) -> 1.86 | E20: 0.05 | F20: M3 | G20: =SUM(H20:AG20) -> 37.23 | H20: =0.9*0.9*4 -> 3.24 | I20: =1.1*1.1*5 -> 6.05 | J20: =1.4*1.4*8 -> 15.68 | K20: =1.7*1.7*2 -> 5.78 | L20: =1.8*1.8*2 -> 6.48
A21: REPLANTILLO EN PARQUEOS | C21: =ROUND(E21*G21,2) -> 0.16 | E21: 0.05 | F21: M3 | G21: =SUM(H21:AG21) -> 3.23 | H21: =0.9*0.9 -> 0.81 | I21: =1.1*1.1*2 -> 2.42
A22: cimientos | G22: =SUM(H22:AG22) -> 0
A23: TOTAL | B23: =SUM(C25:C33) -> 5.27 | C23: M3 | D23: =7.65/2.05 -> 3.7317073 | E23: =25.37/8.9 -> 2.8505618 | G23: =SUM(H23:AG23) -> 0
G24: =SUM(H24:AG24) -> 0
A25: plintos | B25: =SUM(C25:C29) -> 2.75 | C25: =ROUND(E25*G25,2) -> 2.75 | E25: =(0.44+0.8)*0.1*0.5+0.15 -> 0.212 | F25: M2 | G25: =SUM(H25:AG25) -> 12.96 | H25: =1.8*1.8 -> 3.24 | I25: =1.8*1.8 -> 3.24 | J25: =1.8*1.8 -> 3.24 | K25: =1.8*1.8 -> 3.24
C26: =ROUND(E26*G26,2) -> 0 | E26: =(0.44+1)*0.1*0.5+0.15 -> 0.222 | F26: M2 | G26: =SUM(H26:AG26) -> 0
C27: =ROUND(E27*G27,2) -> 0 | E27: =(0.44+1.3)*0.1*0.5+0.15 -> 0.237 | G27: =SUM(H27:AG27) -> 0
C28: =ROUND(E28*G28,2) -> 0 | E28: =(0.44+1.6)*0.1*0.5+0.15 -> 0.252 | G28: =SUM(H28:AG28) -> 0
C29: =ROUND(E29*G29,2) -> 0 | E29: =(0.44+1.7)*0.1*0.5+0.15 -> 0.257 | G29: =SUM(H29:AG29) -> 0
A30: riostras | C30: =ROUND(E30*G30,2) -> 1.12 | E30: =0.2*0.3 -> 0.06 | F30: M2 | G30: =SUM(H30:AG30) -> 18.7 | H30: 5.2 | I30: 5.2 | J30: 3.6 | K30: 4.7
A31: ciclopeo | C31: =ROUND(E31*G31,2) -> 1.4 | E31: =(0.2+0.3)*0.3*0.5 -> 0.075 | F31: M2 | G31: =SUM(H31:AG31) -> 18.7 | H31: 5.2 | I31: 5.2 | J31: 3.6 | K31: 4.7
A32: plintos parqueos | C32: =ROUND(E32*G32,2) -> 0 | E32: =(0.44+1)*0.1*0.5+0.15 -> 0.222 | F32: M2 | G32: =SUM(H32:AG32) -> 0
A33: riostras parqueo | C33: =ROUND(E33*G33,2) -> 0 | E33: =0.2*0.2 -> 0.04 | F33: M2 | G33: =SUM(H33:AG33) -> 0
G34: =SUM(H34:AG34) -> 0
A35: cimientos | G35: =SUM(H35:AG35) -> 0
A36: TOTAL | B36: =SUM(C38:C39) -> 15.94 | C36: M3 | G36: =SUM(H36:AG36) -> 0
G37: =SUM(H37:AG37) -> 0
A38: zapatas | C38: =ROUND(E38*G38,2) -> 10.56 | E38: 0.18 | F38: M2 | G38: =SUM(H38:AG38) -> 58.68 | H38: 8.9 | I38: 8.56 | J38: 2.39 | K38: 6.85 | L38: 5.1 | M38: 1.69 | N38: 2.05 | O38: 4.2 | P38: 2.81 | Q38: 2.89 | R38: 2.66 | S38: 1.4 | T38: 0.92 | U38: 0.98 | V38: 1.85 | W38: 1.42 | X38: 1 | Y38: 1.16 | Z38: 1.85
A39: vigas | C39: =ROUND(E39*G39,2) -> 5.38 | E39: =0.2*0.25 -> 0.05 | F39: M2 | G39: =SUM(H39:AG39) -> 107.62 | H39: 14.51 | I39: 14.17 | J39: 6.32 | K39: 8.5 | L39: 8.7 | M39: 4.63 | N39: 4.5 | O39: 8.2 | P39: 4.5 | Q39: 4.73 | R39: 4.3 | S39: 3.2 | T39: 2.17 | U39: 2.54 | V39: 4.2 | W39: 3.24 | X39: 2.35 | Y39: 2.81 | Z39: 4.05
A40: riostras | C40: =ROUND(E40*G40,2) -> 0.4 | E40: =0.2*0.3 -> 0.06 | F40: M2 | G40: =SUM(H40:AG40) -> 6.6 | H40: 4.5 | I40: 2.1
A41: ciclopeo | C41: =ROUND(E41*G41,2) -> 0.5 | E41: =(0.2+0.3)*0.3*0.5 -> 0.075 | F41: M2 | G41: =SUM(H41:AG41) -> 6.6 | H41: 4.5 | I41: 2.1
A42: zapatas parqueo | C42: =ROUND(E42*G42,2) -> 0 | E42: =0.1+0.05 -> 0.15 | F42: M2 | G42: =SUM(H42:AG42) -> 0
A43: vigas parqueo | C43: =ROUND(E43*G43,2) -> 0 | E43: =0.2*0.3 -> 0.06 | F43: M2 | G43: =SUM(H43:AG43) -> 0
A44: columnas | G44: =SUM(H44:AG44) -> 0
A45: TOTAL | B45: =SUM(C47:C48) -> 8.67 | C45: M3 | D45: =SUM(B47:B50) -> 137.427 | G45: =SUM(H45:AG45) -> 0
G46: =SUM(H46:AG46) -> 0
A47: cimientos a losa | B47: =H47*(0.2*2+0.35*2)*3.17 -> 73.227 | C47: =ROUND(E47*G47*D47,2) -> 5.45 | D47: =3.17+0.54 -> 3.71 | E47: =0.2*0.35 -> 0.07 | F47: M2 | G47: =SUM(H47:AG47) -> 21 | H47: 21
A48: losa a cubierta | B48: =H48*(0.2*2+0.3*2)*3.35 -> 53.6 | C48: =ROUND(E48*G48*D48,2) -> 3.22 | D48: 3.35 | E48: =0.2*0.3 -> 0.06 | F48: M2 | G48: =SUM(H48:AG48) -> 16 | H48: 16
A50: cimientos a losa PARQUEO | B50: =H50*(0.2*2+0.3*2)*2.65 -> 10.6 | C50: =ROUND(E50*G50*D50,2) -> 0.89 | D50: =3.17+0.54 -> 3.71 | E50: =0.2*0.3 -> 0.06 | F50: M2 | G50: =SUM(H50:AG50) -> 4 | H50: 4
A53: cisterna | E53: =0.2*0.3 -> 0.06 | F53: M2 | G53: =SUM(H53:AG53) -> 6.2625 | H53: =2.9*3.9*0.2 -> 2.262 | I53: =+(2*2+3.3*2)*0.15*1.8 -> 2.862 | J53: =3.3*2.3*0.15 -> 1.1385
G54: =SUM(H54:AG54) -> 24 | H54: =2*3 -> 6 | I54: =+(2*2+3*2)*1.8 -> 18
A55: losas
A56: TOTAL | C56: M3 | E56: 29.65 | F56: =+G58/F57 -> 0.84404978
F57: 154.28
A58: losa | C58: =ROUND(D58*E58*G58,2) -> 11.72 | D58: 1 | E58: =0.05+2*0.1*0.2 -> 0.09 | F58: M2 | G58: =SUM(H58:AG58) -> 130.22 | H58: 12.15 | I58: 10.17 | J58: 11.68 | K58: 12.05 | L58: 7.56 | M58: 3 | N58: 0.5 | O58: 8.36 | P58: 10.18 | Q58: 4.44 | R58: 6.1 | S58: 1.6 | T58: 3.23 | U58: 9.72 | V58: 15.9 | W58: 7.98 | X58: 1.7 | Y58: 1.02 | Z58: 1.68 | AA58: 0.95 | AB58: 0.25
C59: =ROUND(E59*G59,2) -> 0 | E59: 0.25 | F59: M2 | G59: =SUM(H59:AG59) -> 0
A60: vigas losa entre piso 25,x40 | B60: =SUM(C60:C62) -> 9.82 | C60: =ROUND(E60*G60,2) -> 1.56 | E60: =0.25*0.4 -> 0.1 | F60: ml | G60: =SUM(H60:AG60) -> 15.57 | H60: 15.57
A61: vigas losa entre piso 20x40 | C61: =ROUND(E61*G61,2) -> 5.54 | E61: =0.2*0.4 -> 0.08 | F61: ml | G61: =SUM(H61:AG61) -> 69.21 | H61: 4.9 | I61: 4.7 | J61: 8.6 | K61: 4.7 | L61: 8.8 | M61: 4.7 | N61: 9.53 | O61: 3.4 | P61: 2.2 | Q61: 7.84 | R61: 3 | S61: 3.44 | T61: 3.4
A62: vigas losa entre piso 20x35 | C62: =ROUND(E62*G62,2) -> 2.72 | E62: =0.2*0.35 -> 0.07 | F62: ml | G62: =SUM(H62:AG62) -> 38.84 | H62: 2.7 | I62: 2.26 | J62: 2.47 | K62: 3.29 | L62: 2.6 | M62: 0.7 | N62: 3.02 | O62: 1.31 | P62: 0.84 | Q62: 2.3 | R62: 2.26 | S62: 3.74 | T62: 1.9 | U62: 1.05 | V62: 2.26 | W62: 3.74 | X62: 1.9 | Y62: 0.5
A63: vigas cubierta posterior | C63: =ROUND(D63*E63*G63,2) -> 0 | D63: 0.15 | E63: 0.3 | F63: M2 | G63: =SUM(H63:AG63) -> 0
A64: vigas cubierta princiapl | C64: =ROUND(D64*E64*G64,2) -> 5.75 | D64: 0.15 | E64: 0.35 | F64: ml | G64: =SUM(H64:AH64) -> 109.55 | H64: 12.3 | I64: 12.4 | J64: 11.85 | K64: 3.7 | L64: 2.3 | M64: 10 | O64: 2.6 | P64: 2.6 | Q64: 3.2 | R64: 3.2 | S64: 3.2 | T64: 3.2 | U64: 4.6 | V64: 1.95 | W64: 2.1 | X64: 2.1 | Y64: 3.15 | Z64: 3.1 | AA64: 3.8 | AB64: 2.7 | AC64: 2.5 | AD64: 2 | AE64: 2 | AF64: 2.4 | AG64: 3.3 | AH64: 3.3
A65: vigas losa cubierta | C65: =ROUND(E65*G65,2) -> 0 | E65: 0.3 | F65: M2 | G65: =SUM(H65:AG65) -> 0
A66: losa de cubierta | C66: =ROUND(D66*E66*G66,2) -> 2.24 | D66: 1 | E66: =0.05+2*0.1*0.2 -> 0.09 | F66: M2 | G66: =SUM(H66:AG66) -> 24.906 | H66: =29.65*0.84 -> 24.906
A67: vigas parqueo | C67: =ROUND(E67*G67,2) -> 1.9 | E67: 0.4 | F67: ml | G67: =SUM(H67:AG67) -> 4.744 | H67: =(29.65-H66) -> 4.744
A68: CONTRAPISO | G68: =SUM(H68:AG68) -> 0
A69: TOTAL | B69: =SUM(C71:C75) -> 146 | C69: M2 | G69: =SUM(H69:AG69) -> 0
G70: =SUM(H70:AG70) -> 0
A71: CONTRAPISO INTERIOR | C71: =ROUND(E71*G71,2) -> 146 | E71: 1 | F71: m2 | G71: =SUM(H71:AG71) -> 146 | H71: 146
A72: PATIOS POSTERIORES | C72: =ROUND(E72*G72,2) -> 0 | E72: 1 | F72: m2 | G72: =SUM(H72:AG72) -> 0
A73: TERRAZA EXTERIOR | C73: =ROUND(E73*G73,2) -> 0 | E73: 1 | F73: m2 | G73: =SUM(H73:AG73) -> 0
A74: PAVIMENTO EN INGRESO Y PARQUEOS | C74: =ROUND(E74*G74,2) -> 0 | E74: 1 | F74: m2 | G74: =SUM(H74:AG74) -> 0
G75: =SUM(H75:AG75) -> 0
A76: PAREDES | G76: =SUM(H76:AG76) -> 0
A77: PARED E= 20cm | C77: M2 | D77: =E88+E94+E101+E107 -> 214.27 | E77: =-24.42-15.29 -> -39.71 | F77: =SUM(D77:E77) -> 174.56
A78: PARED E= 10cm | C78: M2 | D78: =E90+E92+E103+E105+E116 -> 461 | E78: =-9.09-37.38-25.2 -> -71.67 | F78: =SUM(D78:E78) -> 389.33
A79: viguetas 20x20 | C79: ml | D79: =G88+G94+G101+G107 -> 66.02
A80: viguetas 10x20 | C80: ml | D80: =G90+G92+G103+G105+G116 -> 139.93
G82: =SUM(H82:AG82) -> 0
A83: PLANTA BAJA
A84: PARED E= 10cm | C84: M2 | E84: =SUM(E88:E94) -> 277.86
A85: viguetas 20x20 | C85: ml | F85: ML
A86: viguetas 10x20 | C86: ml | F86: ML
A88: PARED E= 20cm EXTERIOR | C88: M2 | E88: =ROUND(F88*G88,2) -> 104.42 | F88: 3.17 | G88: =SUM(H88:AP88) -> 32.94 | H88: 4.6 | I88: 6.04 | J88: 4.5 | K88: 2.46 | L88: 3.9 | M88: 2.9 | N88: 4.7 | O88: 2.3 | P88: 0.25 | Q88: 1.29
A90: PARED E= 10cm EXTERIOR | C90: M2 | E90: =ROUND(F90*G90,2) -> 69.9 | F90: 3.17 | G90: =SUM(H90:AP90) -> 22.05 | H90: 2.21 | I90: 0.44 | M90: 1.1 | N90: 1.1 | O90: 2.3 | P90: 0.8 | Q90: 1.1 | R90: 1.6 | S90: 1.85 | T90: 0.4 | U90: 1.27 | V90: 3.18 | W90: 4.7
A92: PARED E= 10cm INTERIOR | C92: M2 | E92: =ROUND(F92*G92,2) -> 86.45 | F92: 3.17 | G92: =SUM(H92:AP92) -> 27.27 | H92: 4.89 | I92: 0.39 | J92: 1.11 | K92: 1.01 | L92: 1.61 | M92: 1.81 | N92: 6.49 | O92: 1.85 | P92: 2.1 | Q92: 2.1 | R92: 2 | S92: 1.91
A94: PARED E= 20cm InTERIOR | C94: M2 | E94: =ROUND(F94*G94,2) -> 17.09 | F94: 3.17 | G94: =SUM(H94:AP94) -> 5.39 | H94: 1.95 | I94: 1.74 | J94: 1.7
A96: PLANTA ALTA
A97: PARED E= 10cm | C97: M2 | E97: =SUM(E101:E106) -> 338.05 | F97: m2
A98: viguetas 20x20 | C98: ml | F98: ML
A99: viguetas 10x20 | C99: ml | F99: ML
A101: PARED E= 20cm EXTERIOR | C101: M2 | D101: =-24.42-15.29 -> -39.71 | E101: =ROUND(F101*G101,2) -> 71.32 | F101: 3.35 | G101: =SUM(H101:AP101) -> 21.29 | H101: 2.3 | I101: 1.05 | J101: 4.09 | K101: 0.9 | L101: 0.9 | M101: 0.5 | N101: 1.2 | O101: 3.55 | P101: 6.8
A103: PARED E= 10cm EXTERIOR | C103: M2 | E103: =ROUND(F103*G103,2) -> 109.51 | F103: 3.35 | G103: =SUM(H103:AP103) -> 32.69 | H103: 1.3 | I103: 0.2 | J103: 2.2 | K103: 0.75 | L103: 0.44 | M103: 2.21 | N103: 3.85 | O103: 1.3 | P103: 1.5 | Q103: 1.35 | R103: 0.51 | S103: 1.04 | T103: 2.4 | U103: 0.54 | V103: 3.5 | W103: 3.9 | X103: 0.72 | Y103: 2.98 | Z103: 2
A105: PARED E= 10cm INTERIOR | C105: M2 | E105: =ROUND(F105*G105,2) -> 157.22 | F105: 3.35 | G105: =SUM(H105:AP105) -> 46.93 | H105: 2.58 | I105: 1.36 | J105: 1.65 | K105: 3.6 | L105: 3.09 | M105: 5.25 | N105: 3.4 | O105: 5.01 | P105: 2.3 | Q105: 0.8 | R105: 2.4 | S105: 1.3 | T105: 2.39 | U105: 1.95 | V105: 1.4 | W105: 3.2 | X105: 3.4 | Y105: 1.45 | Z105: 0.4
A107: PARED E= 20cm InTERIOR | C107: M2 | E107: =ROUND(F107*G107,2) -> 21.44 | F107: 3.35 | G107: =SUM(H107:AP107) -> 6.4 | H107: 1.35 | I107: 1.5 | J107: 1.6 | K107: 1.95
A109: GARAJE
A110: PARED E= 10cm | B110: =SUM(E117:E117) -> 0 | C110: M2 | E110: =SUM(E115:E116) -> 37.92 | F110: m2 | G110: =SUM(H110:AP110) -> 0
A111: viguetas 20x20 | B111: =SUM(E118:E118) -> 0 | C111: ml | E111: =SUM(G118:G118) -> 0 | F111: ML | G111: =SUM(H111:AP111) -> 0
A112: viguetas 10x20 | B112: =SUM(E119:E119) -> 0 | C112: ml | E112: =SUM(G119:G119) -> 0 | F112: ML | G112: =SUM(H112:AP112) -> 0
A115: PARED E= 20cm EXTERIOR | C115: M2 | E115: =ROUND(F115*G115,2) -> 0 | F115: 1 | G115: =SUM(H115:AP115) -> 0
A116: PARED E= 10cm EXTERIOR | C116: M2 | E116: =ROUND(F116*G116,2) -> 37.92 | F116: 3.45 | G116: =SUM(H116:AP116) -> 10.99 | H116: 0.6 | I116: 0.5 | J116: 0.59 | K116: 0.2 | L116: 0.2 | M116: 0.4 | N116: 0.5 | O116: 3.4 | P116: 0.2 | Q116: 0.4 | R116: 0.9 | S116: 1.2 | T116: 0.55 | U116: 0.55 | V116: 0.4 | W116: 0.4
A120: VIGUETAS Y PILARETES 10x20
...

Sheet 1.1
B1: NOMBRE DEL PROPONENTE: | D1: ESPOL | H1: FORM. #3 | L1: =A5 -> 1 | M1: =C6 -> Caseta de oficina, bodega y guardiania | N1: =H5 -> m2 | O1: =H56 -> 42.5
B2: OBRA: | C2: =PRESUPUESTO!$B$3 -> 0 | G2: HOJA | I2: de
C3: =PRESUPUESTO!$B$4 -> 0
B4: ANALISIS DE PRECIOS UNITARIOS
A5: 1 | B5: RUBRO | C5: 1.1.1 | G5: UNIDAD: | H5: m2
B6: DETALLE | C6: Caseta de oficina, bodega y guardiania
B8: EQUIPOS
B9: DESCRIPCION | D9: CANTIDAD A | E9: TARIFA B | F9: COSTO HORA C= A*B | G9: RENDIMIENTO | H9: COSTO D=C*R
A10: 19015 | B10: =IF($A10=0,"",VLOOKUP($A10,'BASE EQUIPO'!$A:$D,2)) -> HERRAMIENTA MENOR | D10: 1 | E10: =IF($A10=0,"",VLOOKUP($A10,'BASE EQUIPO'!$A:$D,4)*H26) -> 0.2274 | F10: =IF($A10=0,"",ROUND(D10*E10,2)) -> 0.23 | G10: 1 | H10: =IF($A10=0,"",ROUND(G10*F10,2)) -> 0.23
B11: =IF($A11=0,"",VLOOKUP($A11,'BASE EQUIPO'!$A:$D,2)) | E11: =IF($A11=0,"",VLOOKUP($A11,'BASE EQUIPO'!$A:$D,4)) | F11: =IF($A11=0,"",ROUND(D11*E11,2)) | H11: =IF($A11=0,"",ROUND(G11*F11,2))
B12: =IF($A12=0,"",VLOOKUP($A12,'BASE EQUIPO'!$A:$D,2)) | E12: =IF($A12=0,"",VLOOKUP($A12,'BASE EQUIPO'!$A:$D,4)) | F12: =IF($A12=0,"",ROUND(D12*E12,2)) | H12: =IF($A12=0,"",ROUND(G12*F12,2))
B13: =IF($A13=0,"",VLOOKUP($A13,'BASE EQUIPO'!$A:$D,2)) | E13: =IF($A13=0,"",VLOOKUP($A13,'BASE EQUIPO'!$A:$D,4)) | F13: =IF($A13=0,"",ROUND(D13*E13,2)) | H13: =IF($A13=0,"",ROUND(G13*F13,2))
B14: =IF($A14=0,"",VLOOKUP($A14,'BASE EQUIPO'!$A:$D,2)) | E14: =IF($A14=0,"",VLOOKUP($A14,'BASE EQUIPO'!$A:$D,4)) | F14: =IF($A14=0,"",ROUND(D14*E14,2)) | H14: =IF($A14=0,"",ROUND(G14*F14,2))
B15: =IF($A15=0,"",VLOOKUP($A15,'BASE EQUIPO'!$A:$D,2)) | E15: =IF($A15=0,"",VLOOKUP($A15,'BASE EQUIPO'!$A:$D,4)) | F15: =IF($A15=0,"",ROUND(D15*E15,2)) | H15: =IF($A15=0,"",ROUND(G15*F15,2))
B16: SUBTOTAL M | H16: =ROUND(SUM(H9:H15),2) -> 0.23
B17: MANO DE OBRA
B18: DESCRIPCION (CATEG) | D18: CANTIDAD A | E18: JORNAL/HR B | F18: COSTO HORA C= A*B | G18: RENDIMIENTO | H18: COSTO D=C*R
A19: 20001 | B19: =IF($A19=0,"",VLOOKUP($A19,'BASE M-OBRA'!$A:$D,2)) -> MAESTRO | D19: 1 | E19: =IF($A19=0,"",VLOOKUP($A19,'BASE M-OBRA'!$A:$D,4)) -> 3.02 | F19: =IF($A19=0,"",ROUND(D19*E19,2)) -> 3.02 | G19: =IF($A19=0,"",ROUND(H19/F19,2)) -> 0.42 | H19: =IF($A19=0,"",ROUND(SUM(H20:H25)*'BASE M-OBRA'!$D$23,2)) -> 1.26
A20: 20004 | B20: =IF($A20=0,"",VLOOKUP($A20,'BASE M-OBRA'!$A:$D,2)) -> CARPINTERO | D20: 2 | E20: =IF($A20=0,"",VLOOKUP($A20,'BASE M-OBRA'!$A:$D,4)) -> 2.82 | F20: =IF($A20=0,"",ROUND(D20*E20,2)) -> 5.64 | G20: 0.75 | H20: =IF($A20=0,"",ROUND(G20*F20,2)) -> 4.23
A21: 20002 | B21: =IF($A21=0,"",VLOOKUP($A21,'BASE M-OBRA'!$A:$D,2)) -> PEON | D21: 1 | E21: =IF($A21=0,"",VLOOKUP($A21,'BASE M-OBRA'!$A:$D,4)) -> 2.79 | F21: =IF($A21=0,"",ROUND(D21*E21,2)) -> 2.79 | G21: =+G20 -> 0.75 | H21: =IF($A21=0,"",ROUND(G21*F21,2)) -> 2.09
B22: =IF($A22=0,"",VLOOKUP($A22,'BASE M-OBRA'!$A:$D,2)) | E22: =IF($A22=0,"",VLOOKUP($A22,'BASE M-OBRA'!$A:$D,4)) | F22: =IF($A22=0,"",ROUND(D22*E22,2)) | H22: =IF($A22=0,"",ROUND(G22*F22,2))
B23: =IF($A23=0,"",VLOOKUP($A23,'BASE M-OBRA'!$A:$D,2)) | E23: =IF($A23=0,"",VLOOKUP($A23,'BASE M-OBRA'!$A:$D,4)) | F23: =IF($A23=0,"",ROUND(D23*E23,2)) | H23: =IF($A23=0,"",ROUND(G23*F23,2))
B24: =IF($A24=0,"",VLOOKUP($A24,'BASE M-OBRA'!$A:$D,2)) | E24: =IF($A24=0,"",VLOOKUP($A24,'BASE M-OBRA'!$A:$D,4)) | F24: =IF($A24=0,"",ROUND(D24*E24,2)) | H24: =IF($A24=0,"",ROUND(G24*F24,2))
B25: =IF($A25=0,"",VLOOKUP($A25,'BASE M-OBRA'!$A:$D,2)) | E25: =IF($A25=0,"",VLOOKUP($A25,'BASE M-OBRA'!$A:$D,4)) | F25: =IF($A25=0,"",ROUND(D25*E25,2)) | H25: =IF($A25=0,"",ROUND(G25*F25,2))
B26: SUBTOTAL N | H26: =ROUND(SUM(H18:H25),2) -> 7.58
B27: MATERIALES
B28: DESCRIPCION | E28: UNIDAD | F28: CANTIDAD A | G28: UNITARIO B | H28: COSTO C=A*B
A29: 11008 | B29: =IF($A29=0,"",VLOOKUP($A29,'BASE MATERIAL'!$A:$D,2)) -> TABLA | E29: =IF($A29=0,"",VLOOKUP($A29,'BASE MATERIAL'!$A:$D,3)) -> U | F29: 3 | G29: =IF($A29=0,"",VLOOKUP($A29,'BASE MATERIAL'!$A:$D,4)) -> 3.5 | H29: =IF($A29=0,"",ROUND(F29*G29,2)) -> 10.5
A30: 11009 | B30: =IF($A30=0,"",VLOOKUP($A30,'BASE MATERIAL'!$A:$D,2)) -> CUARTON | E30: =IF($A30=0,"",VLOOKUP($A30,'BASE MATERIAL'!$A:$D,3)) -> U | F30: 1.15 | G30: =IF($A30=0,"",VLOOKUP($A30,'BASE MATERIAL'!$A:$D,4)) -> 2.42 | H30: =IF($A30=0,"",ROUND(F30*G30,2)) -> 2.78
A31: 11010 | B31: =IF($A31=0,"",VLOOKUP($A31,'BASE MATERIAL'!$A:$D,2)) -> TIRA | E31: =IF($A31=0,"",VLOOKUP($A31,'BASE MATERIAL'!$A:$D,3)) -> U | F31: 0.6 | G31: =IF($A31=0,"",VLOOKUP($A31,'BASE MATERIAL'!$A:$D,4)) -> 1.5 | H31: =IF($A31=0,"",ROUND(F31*G31,2)) -> 0.9
A32: 11007 | B32: =IF($A32=0,"",VLOOKUP($A32,'BASE MATERIAL'!$A:$D,2)) -> CLAVO 2 1/2" | E32: =IF($A32=0,"",VLOOKUP($A32,'BASE MATERIAL'!$A:$D,3)) -> KG | F32: 0.12 | G32: =IF($A32=0,"",VLOOKUP($A32,'BASE MATERIAL'!$A:$D,4)) -> 2.652 | H32: =IF($A32=0,"",ROUND(F32*G32,2)) -> 0.32
A33: 12012 | B33: =IF($A33=0,"",VLOOKUP($A33,'BASE MATERIAL'!$A:$D,2)) -> PLANCHA DE ZINC 8' REFORZADA | E33: =IF($A33=0,"",VLOOKUP($A33,'BASE MATERIAL'!$A:$D,3)) -> U | F33: 0.75 | G33: =IF($A33=0,"",VLOOKUP($A33,'BASE MATERIAL'!$A:$D,4)) -> 8.53 | H33: =IF($A33=0,"",ROUND(F33*G33,2)) -> 6.4
A34: 10016 | B34: =IF($A34=0,"",VLOOKUP($A34,'BASE MATERIAL'!$A:$D,2)) -> BISAGRA CROMADA | E34: =IF($A34=0,"",VLOOKUP($A34,'BASE MATERIAL'!$A:$D,3)) -> U | F34: 0.1 | G34: =IF($A34=0,"",VLOOKUP($A34,'BASE MATERIAL'!$A:$D,4)) -> 1.2 | H34: =IF($A34=0,"",ROUND(F34*G34,2)) -> 0.12
A35: 11016 | B35: =IF($A35=0,"",VLOOKUP($A35,'BASE MATERIAL'!$A:$D,2)) -> ARGOLLAS | E35: =IF($A35=0,"",VLOOKUP($A35,'BASE MATERIAL'!$A:$D,3)) -> U | F35: 0.08 | G35: =IF($A35=0,"",VLOOKUP($A35,'BASE MATERIAL'!$A:$D,4)) -> 0.77 | H35: =IF($A35=0,"",ROUND(F35*G35,2)) -> 0.06
A36: 11015 | B36: =IF($A36=0,"",VLOOKUP($A36,'BASE MATERIAL'!$A:$D,2)) -> CANDADO | E36: =IF($A36=0,"",VLOOKUP($A36,'BASE MATERIAL'!$A:$D,3)) -> U | F36: 0.08 | G36: =IF($A36=0,"",VLOOKUP($A36,'BASE MATERIAL'!$A:$D,4)) -> 6.39 | H36: =IF($A36=0,"",ROUND(F36*G36,2)) -> 0.51
A37: 11017 | B37: =IF($A37=0,"",VLOOKUP($A37,'BASE MATERIAL'!$A:$D,2)) -> PLYWOOD CASETA 9MM | E37: =IF($A37=0,"",VLOOKUP($A37,'BASE MATERIAL'!$A:$D,3)) -> U | F37: 0.5 | G37: =IF($A37=0,"",VLOOKUP($A37,'BASE MATERIAL'!$A:$D,4)) -> 24.17 | H37: =IF($A37=0,"",ROUND(F37*G37,2)) -> 12.09
B38: =IF($A38=0,"",VLOOKUP($A38,'BASE MATERIAL'!$A:$D,2)) | E38: =IF($A38=0,"",VLOOKUP($A38,'BASE MATERIAL'!$A:$D,3)) | G38: =IF($A38=0,"",VLOOKUP($A38,'BASE MATERIAL'!$A:$D,4)) | H38: =IF($A38=0,"",ROUND(F38*G38,2))
B39: =IF($A39=0,"",VLOOKUP($A39,'BASE MATERIAL'!$A:$D,2)) | E39: =IF($A39=0,"",VLOOKUP($A39,'BASE MATERIAL'!$A:$D,3)) | G39: =IF($A39=0,"",VLOOKUP($A39,'BASE MATERIAL'!$A:$D,4)) | H39: =IF($A39=0,"",ROUND(F39*G39,2))
B40: =IF($A40=0,"",VLOOKUP($A40,'BASE MATERIAL'!$A:$D,2)) | E40: =IF($A40=0,"",VLOOKUP($A40,'BASE MATERIAL'!$A:$D,3)) | G40: =IF($A40=0,"",VLOOKUP($A40,'BASE MATERIAL'!$A:$D,4)) | H40: =IF($A40=0,"",ROUND(F40*G40,2))
B41: =IF($A41=0,"",VLOOKUP($A41,'BASE MATERIAL'!$A:$D,2)) | E41: =IF($A41=0,"",VLOOKUP($A41,'BASE MATERIAL'!$A:$D,3)) | G41: =IF($A41=0,"",VLOOKUP($A41,'BASE MATERIAL'!$A:$D,4)) | H41: =IF($A41=0,"",ROUND(F41*G41,2))
B42: =IF($A42=0,"",VLOOKUP($A42,'BASE MATERIAL'!$A:$D,2)) | E42: =IF($A42=0,"",VLOOKUP($A42,'BASE MATERIAL'!$A:$D,3)) | G42: =IF($A42=0,"",VLOOKUP($A42,'BASE MATERIAL'!$A:$D,4)) | H42: =IF($A42=0,"",ROUND(F42*G42,2))
B43: =IF($A43=0,"",VLOOKUP($A43,'BASE MATERIAL'!$A:$D,2)) | E43: =IF($A43=0,"",VLOOKUP($A43,'BASE MATERIAL'!$A:$D,3)) | G43: =IF($A43=0,"",VLOOKUP($A43,'BASE MATERIAL'!$A:$D,4)) | H43: =IF($A43=0,"",ROUND(F43*G43,2))
B44: =IF($A44=0,"",VLOOKUP($A44,'BASE MATERIAL'!$A:$D,2)) | E44: =IF($A44=0,"",VLOOKUP($A44,'BASE MATERIAL'!$A:$D,3)) | G44: =IF($A44=0,"",VLOOKUP($A44,'BASE MATERIAL'!$A:$D,4)) | H44: =IF($A44=0,"",ROUND(E44*F44,2))
B45: SUBTOTAL O | H45: =ROUND(SUM(H28:H44),2) -> 33.68
B46: TRANSPORTE
B47: DESCRIPCION | E47: UNIDAD | F47: CANTIDAD A | G47: TARIFA B | H47: COSTO C=A*B
A48: 19019 | B48: =IF($A48=0,"",VLOOKUP($A48,'BASE EQUIPO'!$A:$D,2)) -> TRANSPORTE DE MATERIAL | E48: =IF($A48=0,"",VLOOKUP($A48,'BASE EQUIPO'!$A:$D,3)) -> GLOBAL | F48: 1 | G48: =IF($A48=0,"",VLOOKUP($A48,'BASE EQUIPO'!$A:$D,4)*H45) -> 1.0104 | H48: =IF($A48=0,"",ROUND(F48*G48,2)) -> 1.01
B49: =IF($A49=0,"",VLOOKUP($A49,'BASE EQUIPO'!$A:$D,2)) | E49: =IF($A49=0,"",VLOOKUP($A49,'BASE EQUIPO'!$A:$D,3)) | G49: =IF($A49=0,"",VLOOKUP($A49,'BASE EQUIPO'!$A:$D,4)*H46) | H49: =IF($A49=0,"",ROUND(F49*G49,2))
B50: =IF($A50=0,"",VLOOKUP($A50,'BASE EQUIPO'!$A:$D,2)) | E50: =IF($A50=0,"",VLOOKUP($A50,'BASE EQUIPO'!$A:$D,3)) | G50: =IF($A50=0,"",VLOOKUP($A50,'BASE EQUIPO'!$A:$D,4)*H47) | H50: =IF($A50=0,"",ROUND(F50*G50,2))
B51: SUBTOTAL P | H51: =ROUND(SUM(H47:H50),2) -> 1.01
D52: TOTAL COSTO DIRECTO (M+N+O+P) | H52: =ROUND(SUM(H51,H45,H26,H16),2) -> 42.5
A53: 40002 | D53: INDIRECTOS Y UTILIDADES % | G53: =IF($A53=0,"",VLOOKUP($A53,'BASE MATERIAL'!$M:$P,4)) -> 0 | H53: =IF($A53=0,"",ROUND(G53*H52,2)) -> 0
A54: 40003 | D54: OTROS INDIRECTOS % | G54: =IF($A54=0,"",VLOOKUP($A54,'BASE MATERIAL'!$M:$P,4)) -> 0 | H54: =IF($A54=0,"",ROUND(G54*H52,2)) -> 0
D55: COSTO TOTAL DEL RUBRO | H55: =ROUND(SUM(H52:H54),2) -> 42.5
D56: VALOR OFERTADO | H56: =ROUND(H55,2) -> 42.5
B57: NOMBRE DEL PROPONENTE: | D57: =$D$1 -> ESPOL | H57: FORM. #3 | L57: =A61 -> 2 | M57: =C62 -> Instalación eléctrica provisional | N57: =H61 -> Global | O57: =H112 -> 440.6
B58: OBRA: | C58: ='1.1'!$C$2 -> 0 | G58: HOJA | I58: de
C59: ='1.1'!$C$3 -> 0
B60: ANALISIS DE PRECIOS UNITARIOS
A61: 2 | B61: RUBRO | C61: 1.1.2 | G61: UNIDAD: | H61: Global
B62: DETALLE | C62: Instalación eléctrica provisional
B64: EQUIPOS
B65: DESCRIPCION | D65: CANTIDAD A | E65: TARIFA B | F65: COSTO HORA C= A*B | G65: RENDIMIENTO | H65: COSTO D=C*R
A66: 19015 | B66: =IF($A66=0,"",VLOOKUP($A66,'BASE EQUIPO'!$A:$D,2)) -> HERRAMIENTA MENOR | D66: 1 | E66: =IF($A66=0,"",VLOOKUP($A66,'BASE EQUIPO'!$A:$D,4)*H82) -> 2.4234 | F66: =IF($A66=0,"",ROUND(D66*E66,2)) -> 2.42 | G66: 1 | H66: =IF($A66=0,"",ROUND(G66*F66,2)) -> 2.42
B67: =IF($A67=0,"",VLOOKUP($A67,'BASE EQUIPO'!$A:$D,2)) | E67: =IF($A67=0,"",VLOOKUP($A67,'BASE EQUIPO'!$A:$D,4)) | F67: =IF($A67=0,"",ROUND(D67*E67,2)) | H67: =IF($A67=0,"",ROUND(G67*F67,2))
B68: =IF($A68=0,"",VLOOKUP($A68,'BASE EQUIPO'!$A:$D,2)) | E68: =IF($A68=0,"",VLOOKUP($A68,'BASE EQUIPO'!$A:$D,4)) | F68: =IF($A68=0,"",ROUND(D68*E68,2)) | H68: =IF($A68=0,"",ROUND(G68*F68,2))
B69: =IF($A69=0,"",VLOOKUP($A69,'BASE EQUIPO'!$A:$D,2)) | E69: =IF($A69=0,"",VLOOKUP($A69,'BASE EQUIPO'!$A:$D,4)) | F69: =IF($A69=0,"",ROUND(D69*E69,2)) | H69: =IF($A69=0,"",ROUND(G69*F69,2))
B70: =IF($A70=0,"",VLOOKUP($A70,'BASE EQUIPO'!$A:$D,2)) | E70: =IF($A70=0,"",VLOOKUP($A70,'BASE EQUIPO'!$A:$D,4)) | F70: =IF($A70=0,"",ROUND(D70*E70,2)) | H70: =IF($A70=0,"",ROUND(G70*F70,2))
B71: =IF($A71=0,"",VLOOKUP($A71,'BASE EQUIPO'!$A:$D,2)) | E71: =IF($A71=0,"",VLOOKUP($A71,'BASE EQUIPO'!$A:$D,4)) | F71: =IF($A71=0,"",ROUND(D71*E71,2)) | H71: =IF($A71=0,"",ROUND(G71*F71,2))
B72: SUBTOTAL M | H72: =ROUND(SUM(H65:H71),2) -> 2.42
B73: MANO DE OBRA
B74: DESCRIPCION (CATEG) | D74: CANTIDAD A | E74: JORNAL/HR B | F74: COSTO HORA C= A*B | G74: RENDIMIENTO | H74: COSTO D=C*R
A75: 20001 | B75: =IF($A75=0,"",VLOOKUP($A75,'BASE M-OBRA'!$A:$D,2)) -> MAESTRO | D75: 1 | E75: =IF($A75=0,"",VLOOKUP($A75,'BASE M-OBRA'!$A:$D,4)) -> 3.02 | F75: =IF($A75=0,"",ROUND(D75*E75,2)) -> 3.02 | G75: =IF($A75=0,"",ROUND(H75/F75,2)) -> 4.46 | H75: =IF($A75=0,"",ROUND(SUM(H76:H81)*'BASE M-OBRA'!$D$23,2)) -> 13.46
A76: 20017 | B76: =IF($A76=0,"",VLOOKUP($A76,'BASE M-OBRA'!$A:$D,2)) -> ELECTRICISTA | D76: 1 | E76: =IF($A76=0,"",VLOOKUP($A76,'BASE M-OBRA'!$A:$D,4)) -> 2.82 | F76: =IF($A76=0,"",ROUND(D76*E76,2)) -> 2.82 | G76: 12 | H76: =IF($A76=0,"",ROUND(G76*F76,2)) -> 33.84
A77: 20011 | B77: =IF($A77=0,"",VLOOKUP($A77,'BASE M-OBRA'!$A:$D,2)) -> AYUDANTE ESPECIALISTA | D77: 1 | E77: =IF($A77=0,"",VLOOKUP($A77,'BASE M-OBRA'!$A:$D,4)) -> 2.79 | F77: =IF($A77=0,"",ROUND(D77*E77,2)) -> 2.79 | G77: =+G76 -> 12 | H77: =IF($A77=0,"",ROUND(G77*F77,2)) -> 33.48
B78: =IF($A78=0,"",VLOOKUP($A78,'BASE M-OBRA'!$A:$D,2)) | E78: =IF($A78=0,"",VLOOKUP($A78,'BASE M-OBRA'!$A:$D,4)) | F78: =IF($A78=0,"",ROUND(D78*E78,2)) | H78: =IF($A78=0,"",ROUND(G78*F78,2))
B79: =IF($A79=0,"",VLOOKUP($A79,'BASE M-OBRA'!$A:$D,2)) | E79: =IF($A79=0,"",VLOOKUP($A79,'BASE M-OBRA'!$A:$D,4)) | F79: =IF($A79=0,"",ROUND(D79*E79,2)) | H79: =IF($A79=0,"",ROUND(G79*F79,2))
B80: =IF($A80=0,"",VLOOKUP($A80,'BASE M-OBRA'!$A:$D,2)) | E80: =IF($A80=0,"",VLOOKUP($A80,'BASE M-OBRA'!$A:$D,4)) | F80: =IF($A80=0,"",ROUND(D80*E80,2)) | H80: =IF($A80=0,"",ROUND(G80*F80,2))
B81: =IF($A81=0,"",VLOOKUP($A81,'BASE M-OBRA'!$A:$D,2)) | E81: =IF($A81=0,"",VLOOKUP($A81,'BASE M-OBRA'!$A:$D,4)) | F81: =IF($A81=0,"",ROUND(D81*E81,2)) | H81: =IF($A81=0,"",ROUND(G81*F81,2))
B82: SUBTOTAL N | H82: =ROUND(SUM(H74:H81),2) -> 80.78
B83: MATERIALES
B84: DESCRIPCION | E84: UNIDAD | F84: CANTIDAD A | G84: UNITARIO B | H84: COSTO C=A*B
A85: 18009 | B85: =IF($A85=0,"",VLOOKUP($A85,'BASE MATERIAL'!$A:$D,2)) -> CABLE # 6 | E85: =IF($A85=0,"",VLOOKUP($A85,'BASE MATERIAL'!$A:$D,3)) -> m | F85: 12 | G85: =IF($A85=0,"",VLOOKUP($A85,'BASE MATERIAL'!$A:$D,4)) -> 1.8942 | H85: =IF($A85=0,"",ROUND(F85*G85,2)) -> 22.73
A86: 18006 | B86: =IF($A86=0,"",VLOOKUP($A86,'BASE MATERIAL'!$A:$D,2)) -> CABLE # 8 | E86: =IF($A86=0,"",VLOOKUP($A86,'BASE MATERIAL'!$A:$D,3)) -> m | F86: =+F85*2 -> 24 | G86: =IF($A86=0,"",VLOOKUP($A86,'BASE MATERIAL'!$A:$D,4)) -> 1.1842 | H86: =IF($A86=0,"",ROUND(F86*G86,2)) -> 28.42
A87: 18004 | B87: =IF($A87=0,"",VLOOKUP($A87,'BASE MATERIAL'!$A:$D,2)) -> BREAKER GENERAL 70A 3P | E87: =IF($A87=0,"",VLOOKUP($A87,'BASE MATERIAL'!$A:$D,3)) -> U | F87: 1 | G87: =IF($A87=0,"",VLOOKUP($A87,'BASE MATERIAL'!$A:$D,4)) -> 23 | H87: =IF($A87=0,"",ROUND(F87*G87,2)) -> 23
A88: 18029 | B88: =IF($A88=0,"",VLOOKUP($A88,'BASE MATERIAL'!$A:$D,2)) -> MEDIDOR | E88: =IF($A88=0,"",VLOOKUP($A88,'BASE MATERIAL'!$A:$D,3)) -> U | F88: 1 | G88: =IF($A88=0,"",VLOOKUP($A88,'BASE MATERIAL'!$A:$D,4)) -> 133 | H88: =IF($A88=0,"",ROUND(F88*G88,2)) -> 133
A89: 18012 | B89: =IF($A89=0,"",VLOOKUP($A89,'BASE MATERIAL'!$A:$D,2)) -> CAJA BREAKER: 4/8 | E89: =IF($A89=0,"",VLOOKUP($A89,'BASE MATERIAL'!$A:$D,3)) -> U | F89: 1 | G89: =IF($A89=0,"",VLOOKUP($A89,'BASE MATERIAL'!$A:$D,4)) -> 24.21 | H89: =IF($A89=0,"",ROUND(F89*G89,2)) -> 24.21
A90: 18005 | B90: =IF($A90=0,"",VLOOKUP($A90,'BASE MATERIAL'!$A:$D,2)) -> BREAKER 20 AMP. 1P | E90: =IF($A90=0,"",VLOOKUP($A90,'BASE MATERIAL'!$A:$D,3)) -> U | F90: 1 | G90: =IF($A90=0,"",VLOOKUP($A90,'BASE MATERIAL'!$A:$D,4)) -> 4.5 | H90: =IF($A90=0,"",ROUND(F90*G90,2)) -> 4.5
A91: 18050 | B91: =IF($A91=0,"",VLOOKUP($A91,'BASE MATERIAL'!$A:$D,2)) -> BREAKER 40 AMP. 2P | E91: =IF($A91=0,"",VLOOKUP($A91,'BASE MATERIAL'!$A:$D,3)) -> U | F91: 1 | G91: =IF($A91=0,"",VLOOKUP($A91,'BASE MATERIAL'!$A:$D,4)) -> 10.68 | H91: =IF($A91=0,"",ROUND(F91*G91,2)) -> 10.68
A92: 18002 | B92: =IF($A92=0,"",VLOOKUP($A92,'BASE MATERIAL'!$A:$D,2)) -> ALAMBRE CU TWG Nº 12 | E92: =IF($A92=0,"",VLOOKUP($A92,'BASE MATERIAL'!$A:$D,3)) -> m | F92: =10*3 -> 30 | G92: =IF($A92=0,"",VLOOKUP($A92,'BASE MATERIAL'!$A:$D,4)) -> 0.4073 | H92: =IF($A92=0,"",ROUND(F92*G92,2)) -> 12.22
A93: 18051 | B93: =IF($A93=0,"",VLOOKUP($A93,'BASE MATERIAL'!$A:$D,2)) -> PUNTOS DE ILUMINACION 120V | E93: =IF($A93=0,"",VLOOKUP($A93,'BASE MATERIAL'!$A:$D,3)) -> U | F93: 3 | G93: =IF($A93=0,"",VLOOKUP($A93,'BASE MATERIAL'!$A:$D,4)) -> 12.86 | H93: =IF($A93=0,"",ROUND(F93*G93,2)) -> 38.58
A94: 18052 | B94: =IF($A94=0,"",VLOOKUP($A94,'BASE MATERIAL'!$A:$D,2)) -> PUNTOS DE TOMACORRIENTE 120V | E94: =IF($A94=0,"",VLOOKUP($A94,'BASE MATERIAL'!$A:$D,3)) -> U | F94: 3 | G94: =IF($A94=0,"",VLOOKUP($A94,'BASE MATERIAL'!$A:$D,4)) -> 13.75 | H94: =IF($A94=0,"",ROUND(F94*G94,2)) -> 41.25
A95: 18053 | B95: =IF($A95=0,"",VLOOKUP($A95,'BASE MATERIAL'!$A:$D,2)) -> FOCO | E95: =IF($A95=0,"",VLOOKUP($A95,'BASE MATERIAL'!$A:$D,3)) -> U | F95: 3 | G95: =IF($A95=0,"",VLOOKUP($A95,'BASE MATERIAL'!$A:$D,4)) -> 2.8 | H95: =IF($A95=0,"",ROUND(F95*G95,2)) -> 8.4
A96: 1 | B96: CONSUMO DE LUZ | E96: MES | F96: 0 | G96: 45 | H96: =IF($A96=0,"",ROUND(F96*G96,2)) -> 0
B97: =IF($A97=0,"",VLOOKUP($A97,'BASE MATERIAL'!$A:$D,2)) | E97: =IF($A97=0,"",VLOOKUP($A97,'BASE MATERIAL'!$A:$D,3)) | G97: =IF($A97=0,"",VLOOKUP($A97,'BASE MATERIAL'!$A:$D,4)) | H97: =IF($A97=0,"",ROUND(F97*G97,2))
B98: =IF($A98=0,"",VLOOKUP($A98,'BASE MATERIAL'!$A:$D,2)) | E98: =IF($A98=0,"",VLOOKUP($A98,'BASE MATERIAL'!$A:$D,3)) | G98: =IF($A98=0,"",VLOOKUP($A98,'BASE MATERIAL'!$A:$D,4)) | H98: =IF($A98=0,"",ROUND(F98*G98,2))
B99: =IF($A99=0,"",VLOOKUP($A99,'BASE MATERIAL'!$A:$D,2)) | E99: =IF($A99=0,"",VLOOKUP($A99,'BASE MATERIAL'!$A:$D,3)) | G99: =IF($A99=0,"",VLOOKUP($A99,'BASE MATERIAL'!$A:$D,4)) | H99: =IF($A99=0,"",ROUND(F99*G99,2))
B100: =IF($A100=0,"",VLOOKUP($A100,'BASE MATERIAL'!$A:$D,2)) | E100: =IF($A100=0,"",VLOOKUP($A100,'BASE MATERIAL'!$A:$D,3)) | G100: =IF($A100=0,"",VLOOKUP($A100,'BASE MATERIAL'!$A:$D,4)) | H100: =IF($A100=0,"",ROUND(E100*F100,2))
B101: SUBTOTAL O | H101: =ROUND(SUM(H84:H100),2) -> 346.99
B102: TRANSPORTE
...

Sheet 1.2
B1: NOMBRE DEL PROPONENTE: | D1: ='1.1'!$D$1 -> ESPOL | H1: FORM. #3 | L1: =A5 -> 1 | M1: =C6 -> Limpieza general de la obra | N1: =H5 -> SEMANA | O1: =H56 -> 51.73
B2: OBRA: | C2: ='1.1'!$C$2 -> 0 | G2: HOJA | I2: de
C3: ='1.1'!$C$3 -> 0
B4: ANALISIS DE PRECIOS UNITARIOS
A5: 1 | B5: RUBRO | C5: 1.2.1 | G5: UNIDAD: | H5: SEMANA
B6: DETALLE | C6: Limpieza general de la obra
B8: EQUIPOS
B9: DESCRIPCION | D9: CANTIDAD A | E9: TARIFA B | F9: COSTO HORA C= A*B | G9: RENDIMIENTO | H9: COSTO D=C*R
A10: 19015 | B10: =IF($A10=0,"",VLOOKUP($A10,'BASE EQUIPO'!$A:$D,2)) -> HERRAMIENTA MENOR | D10: 1 | E10: =IF($A10=0,"",VLOOKUP($A10,'BASE EQUIPO'!$A:$D,4)*H26) -> 1.5066 | F10: =IF($A10=0,"",ROUND(D10*E10,2)) -> 1.51 | G10: 1 | H10: =IF($A10=0,"",ROUND(G10*F10,2)) -> 1.51
B11: =IF($A11=0,"",VLOOKUP($A11,'BASE EQUIPO'!$A:$D,2)) | E11: =IF($A11=0,"",VLOOKUP($A11,'BASE EQUIPO'!$A:$D,4)) | F11: =IF($A11=0,"",ROUND(D11*E11,2)) | H11: =IF($A11=0,"",ROUND(G11*F11,2))
B12: =IF($A12=0,"",VLOOKUP($A12,'BASE EQUIPO'!$A:$D,2)) | E12: =IF($A12=0,"",VLOOKUP($A12,'BASE EQUIPO'!$A:$D,4)) | F12: =IF($A12=0,"",ROUND(D12*E12,2)) | H12: =IF($A12=0,"",ROUND(G12*F12,2))
B13: =IF($A13=0,"",VLOOKUP($A13,'BASE EQUIPO'!$A:$D,2)) | E13: =IF($A13=0,"",VLOOKUP($A13,'BASE EQUIPO'!$A:$D,4)) | F13: =IF($A13=0,"",ROUND(D13*E13,2)) | H13: =IF($A13=0,"",ROUND(G13*F13,2))
B14: =IF($A14=0,"",VLOOKUP($A14,'BASE EQUIPO'!$A:$D,2)) | E14: =IF($A14=0,"",VLOOKUP($A14,'BASE EQUIPO'!$A:$D,4)) | F14: =IF($A14=0,"",ROUND(D14*E14,2)) | H14: =IF($A14=0,"",ROUND(G14*F14,2))
B15: =IF($A15=0,"",VLOOKUP($A15,'BASE EQUIPO'!$A:$D,2)) | E15: =IF($A15=0,"",VLOOKUP($A15,'BASE EQUIPO'!$A:$D,4)) | F15: =IF($A15=0,"",ROUND(D15*E15,2)) | H15: =IF($A15=0,"",ROUND(G15*F15,2))
B16: SUBTOTAL M | H16: =ROUND(SUM(H9:H15),2) -> 1.51
B17: MANO DE OBRA
B18: DESCRIPCION (CATEG) | D18: CANTIDAD A | E18: JORNAL/HR B | F18: COSTO HORA C= A*B | G18: RENDIMIENTO | H18: COSTO D=C*R
A19: 20001 | B19: =IF($A19=0,"",VLOOKUP($A19,'BASE M-OBRA'!$A:$D,2)) -> MAESTRO | D19: 1 | E19: =IF($A19=0,"",VLOOKUP($A19,'BASE M-OBRA'!$A:$D,4)) -> 3.02 | F19: =IF($A19=0,"",ROUND(D19*E19,2)) -> 3.02 | G19: =IF($A19=0,"",ROUND(H19/F19,2)) -> 2.77 | H19: =IF($A19=0,"",ROUND(SUM(H20:H25)*'BASE M-OBRA'!$D$23,2)) -> 8.37
A20: 20002 | B20: =IF($A20=0,"",VLOOKUP($A20,'BASE M-OBRA'!$A:$D,2)) -> PEON | D20: 3 | E20: =IF($A20=0,"",VLOOKUP($A20,'BASE M-OBRA'!$A:$D,4)) -> 2.79 | F20: =IF($A20=0,"",ROUND(D20*E20,2)) -> 8.37 | G20: =5 -> 5 | H20: =IF($A20=0,"",ROUND(G20*F20,2)) -> 41.85
B21: =IF($A21=0,"",VLOOKUP($A21,'BASE M-OBRA'!$A:$D,2)) | E21: =IF($A21=0,"",VLOOKUP($A21,'BASE M-OBRA'!$A:$D,4)) | F21: =IF($A21=0,"",ROUND(D21*E21,2)) | H21: =IF($A21=0,"",ROUND(G21*F21,2))
B22: =IF($A22=0,"",VLOOKUP($A22,'BASE M-OBRA'!$A:$D,2)) | E22: =IF($A22=0,"",VLOOKUP($A22,'BASE M-OBRA'!$A:$D,4)) | F22: =IF($A22=0,"",ROUND(D22*E22,2)) | H22: =IF($A22=0,"",ROUND(G22*F22,2))
B23: =IF($A23=0,"",VLOOKUP($A23,'BASE M-OBRA'!$A:$D,2)) | E23: =IF($A23=0,"",VLOOKUP($A23,'BASE M-OBRA'!$A:$D,4)) | F23: =IF($A23=0,"",ROUND(D23*E23,2)) | H23: =IF($A23=0,"",ROUND(G23*F23,2))
B24: =IF($A24=0,"",VLOOKUP($A24,'BASE M-OBRA'!$A:$D,2)) | E24: =IF($A24=0,"",VLOOKUP($A24,'BASE M-OBRA'!$A:$D,4)) | F24: =IF($A24=0,"",ROUND(D24*E24,2)) | H24: =IF($A24=0,"",ROUND(G24*F24,2))
B25: =IF($A25=0,"",VLOOKUP($A25,'BASE M-OBRA'!$A:$D,2)) | E25: =IF($A25=0,"",VLOOKUP($A25,'BASE M-OBRA'!$A:$D,4)) | F25: =IF($A25=0,"",ROUND(D25*E25,2)) | H25: =IF($A25=0,"",ROUND(G25*F25,2))
B26: SUBTOTAL N | H26: =ROUND(SUM(H18:H25),2) -> 50.22
B27: MATERIALES
B28: DESCRIPCION | E28: UNIDAD | F28: CANTIDAD A | G28: UNITARIO B | H28: COSTO C=A*B
B29: =IF($A29=0,"",VLOOKUP($A29,'BASE MATERIAL'!$A:$D,2)) | E29: =IF($A29=0,"",VLOOKUP($A29,'BASE MATERIAL'!$A:$D,3)) | G29: =IF($A29=0,"",VLOOKUP($A29,'BASE MATERIAL'!$A:$D,4)) | H29: =IF($A29=0,"",ROUND(F29*G29,2))
B30: =IF($A30=0,"",VLOOKUP($A30,'BASE MATERIAL'!$A:$D,2)) | E30: =IF($A30=0,"",VLOOKUP($A30,'BASE MATERIAL'!$A:$D,3)) | G30: =IF($A30=0,"",VLOOKUP($A30,'BASE MATERIAL'!$A:$D,4)) | H30: =IF($A30=0,"",ROUND(F30*G30,2))
B31: =IF($A31=0,"",VLOOKUP($A31,'BASE MATERIAL'!$A:$D,2)) | E31: =IF($A31=0,"",VLOOKUP($A31,'BASE MATERIAL'!$A:$D,3)) | G31: =IF($A31=0,"",VLOOKUP($A31,'BASE MATERIAL'!$A:$D,4)) | H31: =IF($A31=0,"",ROUND(F31*G31,2))
B32: =IF($A32=0,"",VLOOKUP($A32,'BASE MATERIAL'!$A:$D,2)) | E32: =IF($A32=0,"",VLOOKUP($A32,'BASE MATERIAL'!$A:$D,3)) | G32: =IF($A32=0,"",VLOOKUP($A32,'BASE MATERIAL'!$A:$D,4)) | H32: =IF($A32=0,"",ROUND(F32*G32,2))
B33: =IF($A33=0,"",VLOOKUP($A33,'BASE MATERIAL'!$A:$D,2)) | E33: =IF($A33=0,"",VLOOKUP($A33,'BASE MATERIAL'!$A:$D,3)) | G33: =IF($A33=0,"",VLOOKUP($A33,'BASE MATERIAL'!$A:$D,4)) | H33: =IF($A33=0,"",ROUND(F33*G33,2))
B34: =IF($A34=0,"",VLOOKUP($A34,'BASE MATERIAL'!$A:$D,2)) | E34: =IF($A34=0,"",VLOOKUP($A34,'BASE MATERIAL'!$A:$D,3)) | G34: =IF($A34=0,"",VLOOKUP($A34,'BASE MATERIAL'!$A:$D,4)) | H34: =IF($A34=0,"",ROUND(F34*G34,2))
B35: =IF($A35=0,"",VLOOKUP($A35,'BASE MATERIAL'!$A:$D,2)) | E35: =IF($A35=0,"",VLOOKUP($A35,'BASE MATERIAL'!$A:$D,3)) | G35: =IF($A35=0,"",VLOOKUP($A35,'BASE MATERIAL'!$A:$D,4)) | H35: =IF($A35=0,"",ROUND(F35*G35,2))
B36: =IF($A36=0,"",VLOOKUP($A36,'BASE MATERIAL'!$A:$D,2)) | E36: =IF($A36=0,"",VLOOKUP($A36,'BASE MATERIAL'!$A:$D,3)) | G36: =IF($A36=0,"",VLOOKUP($A36,'BASE MATERIAL'!$A:$D,4)) | H36: =IF($A36=0,"",ROUND(F36*G36,2))
B37: =IF($A37=0,"",VLOOKUP($A37,'BASE MATERIAL'!$A:$D,2)) | E37: =IF($A37=0,"",VLOOKUP($A37,'BASE MATERIAL'!$A:$D,3)) | G37: =IF($A37=0,"",VLOOKUP($A37,'BASE MATERIAL'!$A:$D,4)) | H37: =IF($A37=0,"",ROUND(F37*G37,2))
B38: =IF($A38=0,"",VLOOKUP($A38,'BASE MATERIAL'!$A:$D,2)) | E38: =IF($A38=0,"",VLOOKUP($A38,'BASE MATERIAL'!$A:$D,3)) | G38: =IF($A38=0,"",VLOOKUP($A38,'BASE MATERIAL'!$A:$D,4)) | H38: =IF($A38=0,"",ROUND(F38*G38,2))
B39: =IF($A39=0,"",VLOOKUP($A39,'BASE MATERIAL'!$A:$D,2)) | E39: =IF($A39=0,"",VLOOKUP($A39,'BASE MATERIAL'!$A:$D,3)) | G39: =IF($A39=0,"",VLOOKUP($A39,'BASE MATERIAL'!$A:$D,4)) | H39: =IF($A39=0,"",ROUND(F39*G39,2))
B40: =IF($A40=0,"",VLOOKUP($A40,'BASE MATERIAL'!$A:$D,2)) | E40: =IF($A40=0,"",VLOOKUP($A40,'BASE MATERIAL'!$A:$D,3)) | G40: =IF($A40=0,"",VLOOKUP($A40,'BASE MATERIAL'!$A:$D,4)) | H40: =IF($A40=0,"",ROUND(F40*G40,2))
... B43: =IF($A43=0,"",VLOOKUP($A43,'BASE MATERIAL'!$A:$D,2)) | E43: =IF($A43=0,"",VLOOKUP($A43,'BASE MATERIAL'!$A:$D,3)) | G43: =IF($A43=0,"",VLOOKUP($A43,'BASE MATERIAL'!$A:$D,4)) | H43: =IF($A43=0,"",ROUND(F43*G43,2))
B44: =IF($A44=0,"",VLOOKUP($A44,'BASE MATERIAL'!$A:$D,2)) | E44: =IF($A44=0,"",VLOOKUP($A44,'BASE MATERIAL'!$A:$D,3)) | G44: =IF($A44=0,"",VLOOKUP($A44,'BASE MATERIAL'!$A:$D,4)) | H44: =IF($A44=0,"",ROUND(E44*F44,2))
B45: SUBTOTAL O | H45: =ROUND(SUM(H28:H44),2) -> 0
B46: TRANSPORTE
B47: DESCRIPCION | E47: UNIDAD | F47: CANTIDAD A | G47: TARIFA B | H47: COSTO C=A*B
B48: =IF($A48=0,"",VLOOKUP($A48,'BASE EQUIPO'!$A:$D,2)) | E48: =IF($A48=0,"",VLOOKUP($A48,'BASE EQUIPO'!$A:$D,3)) | G48: =IF($A48=0,"",VLOOKUP($A48,'BASE EQUIPO'!$A:$D,4)*H45) | H48: =IF($A48=0,"",ROUND(F48*G48,2))
B49: =IF($A49=0,"",VLOOKUP($A49,'BASE EQUIPO'!$A:$D,2)) | E49: =IF($A49=0,"",VLOOKUP($A49,'BASE EQUIPO'!$A:$D,3)) | G49: =IF($A49=0,"",VLOOKUP($A49,'BASE EQUIPO'!$A:$D,4)*H46) | H49: =IF($A49=0,"",ROUND(F49*G49,2))
B50: =IF($A50=0,"",VLOOKUP($A50,'BASE EQUIPO'!$A:$D,2)) | E50: =IF($A50=0,"",VLOOKUP($A50,'BASE EQUIPO'!$A:$D,3)) | G50: =IF($A50=0,"",VLOOKUP($A50,'BASE EQUIPO'!$A:$D,4)*H47) | H50: =IF($A50=0,"",ROUND(F50*G50,2))
B51: SUBTOTAL P | H51: =ROUND(SUM(H47:H50),2) -> 0
D52: TOTAL COSTO DIRECTO (M+N+O+P) | H52: =ROUND(SUM(H51,H45,H26,H16),2) -> 51.73
A53: 40002 | D53: INDIRECTOS Y UTILIDADES % | G53: =IF($A53=0,"",VLOOKUP($A53,'BASE MATERIAL'!$M:$P,4)) -> 0 | H53: =IF($A53=0,"",ROUND(G53*H52,2)) -> 0
A54: 40003 | D54: OTROS INDIRECTOS % | G54: =IF($A54=0,"",VLOOKUP($A54,'BASE MATERIAL'!$M:$P,4)) -> 0 | H54: =IF($A54=0,"",ROUND(G54*H52,2)) -> 0
D55: COSTO TOTAL DEL RUBRO | H55: =ROUND(SUM(H52:H54),2) -> 51.73
D56: VALOR OFERTADO | H56: =ROUND(H55,2) -> 51.73
B57: NOMBRE DEL PROPONENTE: | D57: =$D$1 -> ESPOL | H57: FORM. #3 | L57: =A61 -> 2 | M57: =C62 -> Desalojo de limpieza | N57: =H61 -> Global | O57: =H112 -> 41.79
B58: OBRA: | C58: ='1.1'!$C$2 -> 0 | G58: HOJA | I58: de
C59: ='1.1'!$C$3 -> 0
B60: ANALISIS DE PRECIOS UNITARIOS
A61: 2 | B61: RUBRO | C61: 1.2.2 | G61: UNIDAD: | H61: Global
B62: DETALLE | C62: Desalojo de limpieza
B64: EQUIPOS
B65: DESCRIPCION | D65: CANTIDAD A | E65: TARIFA B | F65: COSTO HORA C= A*B | G65: RENDIMIENTO | H65: COSTO D=C*R
A66: 19015 | B66: =IF($A66=0,"",VLOOKUP($A66,'BASE EQUIPO'!$A:$D,2)) -> HERRAMIENTA MENOR | D66: 1 | E66: =IF($A66=0,"",VLOOKUP($A66,'BASE EQUIPO'!$A:$D,4)*H82) -> 0.4017 | F66: =IF($A66=0,"",ROUND(D66*E66,2)) -> 0.4 | G66: 1 | H66: =IF($A66=0,"",ROUND(G66*F66,2)) -> 0.4
A67: 19009 | B67: =IF($A67=0,"",VLOOKUP($A67,'BASE EQUIPO'!$A:$D,2)) -> VOLQUETA 8M3 | D67: 1 | E67: =IF($A67=0,"",VLOOKUP($A67,'BASE EQUIPO'!$A:$D,4)) -> 28 | F67: =IF($A67=0,"",ROUND(D67*E67,2)) -> 28 | G67: 1 | H67: =IF($A67=0,"",ROUND(G67*F67,2)) -> 28
B68: =IF($A68=0,"",VLOOKUP($A68,'BASE EQUIPO'!$A:$D,2)) | E68: =IF($A68=0,"",VLOOKUP($A68,'BASE EQUIPO'!$A:$D,4)) | F68: =IF($A68=0,"",ROUND(D68*E68,2)) | H68: =IF($A68=0,"",ROUND(G68*F68,2))
B69: =IF($A69=0,"",VLOOKUP($A69,'BASE EQUIPO'!$A:$D,2)) | E69: =IF($A69=0,"",VLOOKUP($A69,'BASE EQUIPO'!$A:$D,4)) | F69: =IF($A69=0,"",ROUND(D69*E69,2)) | H69: =IF($A69=0,"",ROUND(G69*F69,2))
B70: =IF($A70=0,"",VLOOKUP($A70,'BASE EQUIPO'!$A:$D,2)) | E70: =IF($A70=0,"",VLOOKUP($A70,'BASE EQUIPO'!$A:$D,4)) | F70: =IF($A70=0,"",ROUND(D70*E70,2)) | H70: =IF($A70=0,"",ROUND(G70*F70,2))
B71: =IF($A71=0,"",VLOOKUP($A71,'BASE EQUIPO'!$A:$D,2)) | E71: =IF($A71=0,"",VLOOKUP($A71,'BASE EQUIPO'!$A:$D,4)) | F71: =IF($A71=0,"",ROUND(D71*E71,2)) | H71: =IF($A71=0,"",ROUND(G71*F71,2))
B72: SUBTOTAL M | H72: =ROUND(SUM(H65:H71),2) -> 28.4
B73: MANO DE OBRA
B74: DESCRIPCION (CATEG) | D74: CANTIDAD A | E74: JORNAL/HR B | F74: COSTO HORA C= A*B | G74: RENDIMIENTO | H74: COSTO D=C*R
A75: 20001 | B75: =IF($A75=0,"",VLOOKUP($A75,'BASE M-OBRA'!$A:$D,2)) -> MAESTRO | D75: 1 | E75: =IF($A75=0,"",VLOOKUP($A75,'BASE M-OBRA'!$A:$D,4)) -> 3.02 | F75: =IF($A75=0,"",ROUND(D75*E75,2)) -> 3.02 | G75: =IF($A75=0,"",ROUND(H75/F75,2)) -> 0.74 | H75: =IF($A75=0,"",ROUND(SUM(H76:H81)*'BASE M-OBRA'!$D$23,2)) -> 2.23
A76: 20002 | B76: =IF($A76=0,"",VLOOKUP($A76,'BASE M-OBRA'!$A:$D,2)) -> PEON | D76: 4 | E76: =IF($A76=0,"",VLOOKUP($A76,'BASE M-OBRA'!$A:$D,4)) -> 2.79 | F76: =IF($A76=0,"",ROUND(D76*E76,2)) -> 11.16 | G76: 1 | H76: =IF($A76=0,"",ROUND(G76*F76,2)) -> 11.16
B77: =IF($A77=0,"",VLOOKUP($A77,'BASE M-OBRA'!$A:$D,2)) | E77: =IF($A77=0,"",VLOOKUP($A77,'BASE M-OBRA'!$A:$D,4)) | F77: =IF($A77=0,"",ROUND(D77*E77,2)) | H77: =IF($A77=0,"",ROUND(G77*F77,2))
B78: =IF($A78=0,"",VLOOKUP($A78,'BASE M-OBRA'!$A:$D,2)) | E78: =IF($A78=0,"",VLOOKUP($A78,'BASE M-OBRA'!$A:$D,4)) | F78: =IF($A78=0,"",ROUND(D78*E78,2)) | H78: =IF($A78=0,"",ROUND(G78*F78,2))
B79: =IF($A79=0,"",VLOOKUP($A79,'BASE M-OBRA'!$A:$D,2)) | E79: =IF($A79=0,"",VLOOKUP($A79,'BASE M-OBRA'!$A:$D,4)) | F79: =IF($A79=0,"",ROUND(D79*E79,2)) | H79: =IF($A79=0,"",ROUND(G79*F79,2))
B80: =IF($A80=0,"",VLOOKUP($A80,'BASE M-OBRA'!$A:$D,2)) | E80: =IF($A80=0,"",VLOOKUP($A80,'BASE M-OBRA'!$A:$D,4)) | F80: =IF($A80=0,"",ROUND(D80*E80,2)) | H80: =IF($A80=0,"",ROUND(G80*F80,2))
B81: =IF($A81=0,"",VLOOKUP($A81,'BASE M-OBRA'!$A:$D,2)) | E81: =IF($A81=0,"",VLOOKUP($A81,'BASE M-OBRA'!$A:$D,4)) | F81: =IF($A81=0,"",ROUND(D81*E81,2)) | H81: =IF($A81=0,"",ROUND(G81*F81,2))
B82: SUBTOTAL N | H82: =ROUND(SUM(H74:H81),2) -> 13.39
B83: MATERIALES
B84: DESCRIPCION | E84: UNIDAD | F84: CANTIDAD A | G84: UNITARIO B | H84: COSTO C=A*B
B85: =IF($A85=0,"",VLOOKUP($A85,'BASE MATERIAL'!$A:$D,2)) | E85: =IF($A85=0,"",VLOOKUP($A85,'BASE MATERIAL'!$A:$D,3)) | G85: =IF($A85=0,"",VLOOKUP($A85,'BASE MATERIAL'!$A:$D,4)) | H85: =IF($A85=0,"",ROUND(F85*G85,2))
B86: =IF($A86=0,"",VLOOKUP($A86,'BASE MATERIAL'!$A:$D,2)) | E86: =IF($A86=0,"",VLOOKUP($A86,'BASE MATERIAL'!$A:$D,3)) | G86: =IF($A86=0,"",VLOOKUP($A86,'BASE MATERIAL'!$A:$D,4)) | H86: =IF($A86=0,"",ROUND(F86*G86,2))
B87: =IF($A87=0,"",VLOOKUP($A87,'BASE MATERIAL'!$A:$D,2)) | E87: =IF($A87=0,"",VLOOKUP($A87,'BASE MATERIAL'!$A:$D,3)) | G87: =IF($A87=0,"",VLOOKUP($A87,'BASE MATERIAL'!$A:$D,4)) | H87: =IF($A87=0,"",ROUND(F87*G87,2))
B88: =IF($A88=0,"",VLOOKUP($A88,'BASE MATERIAL'!$A:$D,2)) | E88: =IF($A88=0,"",VLOOKUP($A88,'BASE MATERIAL'!$A:$D,3)) | G88: =IF($A88=0,"",VLOOKUP($A88,'BASE MATERIAL'!$A:$D,4)) | H88: =IF($A88=0,"",ROUND(F88*G88,2))
B89: =IF($A89=0,"",VLOOKUP($A89,'BASE MATERIAL'!$A:$D,2)) | E89: =IF($A89=0,"",VLOOKUP($A89,'BASE MATERIAL'!$A:$D,3)) | G89: =IF($A89=0,"",VLOOKUP($A89,'BASE MATERIAL'!$A:$D,4)) | H89: =IF($A89=0,"",ROUND(F89*G89,2))
B90: =IF($A90=0,"",VLOOKUP($A90,'BASE MATERIAL'!$A:$D,2)) | E90: =IF($A90=0,"",VLOOKUP($A90,'BASE MATERIAL'!$A:$D,3)) | G90: =IF($A90=0,"",VLOOKUP($A90,'BASE MATERIAL'!$A:$D,4)) | H90: =IF($A90=0,"",ROUND(F90*G90,2))
B91: =IF($A91=0,"",VLOOKUP($A91,'BASE MATERIAL'!$A:$D,2)) | E91: =IF($A91=0,"",VLOOKUP($A91,'BASE MATERIAL'!$A:$D,3)) | G91: =IF($A91=0,"",VLOOKUP($A91,'BASE MATERIAL'!$A:$D,4)) | H91: =IF($A91=0,"",ROUND(F91*G91,2))
B92: =IF($A92=0,"",VLOOKUP($A92,'BASE MATERIAL'!$A:$D,2)) | E92: =IF($A92=0,"",VLOOKUP($A92,'BASE MATERIAL'!$A:$D,3)) | G92: =IF($A92=0,"",VLOOKUP($A92,'BASE MATERIAL'!$A:$D,4)) | H92: =IF($A92=0,"",ROUND(F92*G92,2))
B93: =IF($A93=0,"",VLOOKUP($A93,'BASE MATERIAL'!$A:$D,2)) | E93: =IF($A93=0,"",VLOOKUP($A93,'BASE MATERIAL'!$A:$D,3)) | G93: =IF($A93=0,"",VLOOKUP($A93,'BASE MATERIAL'!$A:$D,4)) | H93: =IF($A93=0,"",ROUND(F93*G93,2))
B94: =IF($A94=0,"",VLOOKUP($A94,'BASE MATERIAL'!$A:$D,2)) | E94: =IF($A94=0,"",VLOOKUP($A94,'BASE MATERIAL'!$A:$D,3)) | G94: =IF($A94=0,"",VLOOKUP($A94,'BASE MATERIAL'!$A:$D,4)) | H94: =IF($A94=0,"",ROUND(F94*G94,2))
B95: =IF($A95=0,"",VLOOKUP($A95,'BASE MATERIAL'!$A:$D,2)) | E95: =IF($A95=0,"",VLOOKUP($A95,'BASE MATERIAL'!$A:$D,3)) | G95: =IF($A95=0,"",VLOOKUP($A95,'BASE MATERIAL'!$A:$D,4)) | H95: =IF($A95=0,"",ROUND(F95*G95,2))
B96: =IF($A96=0,"",VLOOKUP($A96,'BASE MATERIAL'!$A:$D,2)) | E96: =IF($A96=0,"",VLOOKUP($A96,'BASE MATERIAL'!$A:$D,3)) | G96: =IF($A96=0,"",VLOOKUP($A96,'BASE MATERIAL'!$A:$D,4)) | H96: =IF($A96=0,"",ROUND(F96*G96,2))
... B99: =IF($A99=0,"",VLOOKUP($A99,'BASE MATERIAL'!$A:$D,2)) | E99: =IF($A99=0,"",VLOOKUP($A99,'BASE MATERIAL'!$A:$D,3)) | G99: =IF($A99=0,"",VLOOKUP($A99,'BASE MATERIAL'!$A:$D,4)) | H99: =IF($A99=0,"",ROUND(F99*G99,2))
B100: =IF($A100=0,"",VLOOKUP($A100,'BASE MATERIAL'!$A:$D,2)) | E100: =IF($A100=0,"",VLOOKUP($A100,'BASE MATERIAL'!$A:$D,3)) | G100: =IF($A100=0,"",VLOOKUP($A100,'BASE MATERIAL'!$A:$D,4)) | H100: =IF($A100=0,"",ROUND(E100*F100,2))
B101: SUBTOTAL O | H101: =ROUND(SUM(H84:H100),2) -> 0
B102: TRANSPORTE
B103: DESCRIPCION | E103: UNIDAD | F103: CANTIDAD A | G103: TARIFA B | H103: COSTO C=A*B
B104: =IF($A104=0,"",VLOOKUP($A104,'BASE EQUIPO'!$A:$D,2)) | E104: =IF($A104=0,"",VLOOKUP($A104,'BASE EQUIPO'!$A:$D,3)) | G104: =IF($A104=0,"",VLOOKUP($A104,'BASE EQUIPO'!$A:$D,4)*H101) | H104: =IF($A104=0,"",ROUND(F104*G104,2))
B105: =IF($A105=0,"",VLOOKUP($A105,'BASE EQUIPO'!$A:$D,2)) | E105: =IF($A105=0,"",VLOOKUP($A105,'BASE EQUIPO'!$A:$D,3)) | G105: =IF($A105=0,"",VLOOKUP($A105,'BASE EQUIPO'!$A:$D,4)*H102) | H105: =IF($A105=0,"",ROUND(F105*G105,2))
B106: =IF($A106=0,"",VLOOKUP($A106,'BASE EQUIPO'!$A:$D,2)) | E106: =IF($A106=0,"",VLOOKUP($A106,'BASE EQUIPO'!$A:$D,3)) | G106: =IF($A106=0,"",VLOOKUP($A106,'BASE EQUIPO'!$A:$D,4)*H103) | H106: =IF($A106=0,"",ROUND(F106*G106,2))
...

Sheet 1.3
B1: NOMBRE DEL PROPONENTE: | D1: ='1.1'!$D$1 -> ESPOL | H1: FORM. #3 | L1: =A5 -> 1 | M1: =C6 -> Limpieza del terreno | N1: =H5 -> m2 | O1: =H56 -> 0.56
B2: OBRA: | C2: ='1.1'!$C$2 -> 0 | G2: HOJA | I2: de
C3: ='1.1'!$C$3 -> 0
B4: ANALISIS DE PRECIOS UNITARIOS
A5: 1 | B5: RUBRO | C5: 1.3.1 | G5: UNIDAD: | H5: m2
B6: DETALLE | C6: Limpieza del terreno
B8: EQUIPOS
B9: DESCRIPCION | D9: CANTIDAD A | E9: TARIFA B | F9: COSTO HORA C= A*B | G9: RENDIMIENTO | H9: COSTO D=C*R
A10: 19015 | B10: =IF($A10=0,"",VLOOKUP($A10,'BASE EQUIPO'!$A:$D,2)) -> HERRAMIENTA MENOR | D10: 1 | E10: =IF($A10=0,"",VLOOKUP($A10,'BASE EQUIPO'!$A:$D,4)*H26) -> 0.0162 | F10: =IF($A10=0,"",ROUND(D10*E10,2)) -> 0.02 | G10: 1 | H10: =IF($A10=0,"",ROUND(G10*F10,2)) -> 0.02
B11: =IF($A11=0,"",VLOOKUP($A11,'BASE EQUIPO'!$A:$D,2)) | E11: =IF($A11=0,"",VLOOKUP($A11,'BASE EQUIPO'!$A:$D,4)) | F11: =IF($A11=0,"",ROUND(D11*E11,2)) | H11: =IF($A11=0,"",ROUND(G11*F11,2))
B12: =IF($A12=0,"",VLOOKUP($A12,'BASE EQUIPO'!$A:$D,2)) | E12: =IF($A12=0,"",VLOOKUP($A12,'BASE EQUIPO'!$A:$D,4)) | F12: =IF($A12=0,"",ROUND(D12*E12,2)) | H12: =IF($A12=0,"",ROUND(G12*F12,2))
B13: =IF($A13=0,"",VLOOKUP($A13,'BASE EQUIPO'!$A:$D,2)) | F13: =IF($A13=0,"",ROUND(D13*E13,2)) | H13: =IF($A13=0,"",ROUND(G13*F13,2))
B14: =IF($A14=0,"",VLOOKUP($A14,'BASE EQUIPO'!$A:$D,2)) | E14: =IF($A14=0,"",VLOOKUP($A14,'BASE EQUIPO'!$A:$D,4)) | F14: =IF($A14=0,"",ROUND(D14*E14,2)) | H14: =IF($A14=0,"",ROUND(G14*F14,2))
B15: =IF($A15=0,"",VLOOKUP($A15,'BASE EQUIPO'!$A:$D,2)) | E15: =IF($A15=0,"",VLOOKUP($A15,'BASE EQUIPO'!$A:$D,4)) | F15: =IF($A15=0,"",ROUND(D15*E15,2)) | H15: =IF($A15=0,"",ROUND(G15*F15,2))
B16: SUBTOTAL M | H16: =ROUND(SUM(H9:H15),2) -> 0.02 | K16: =2834.75*0.3 -> 850.425
B17: MANO DE OBRA | K17: =+K16*4.5 -> 3826.9125
B18: DESCRIPCION (CATEG) | D18: CANTIDAD A | E18: JORNAL/HR B | F18: COSTO HORA C= A*B | G18: RENDIMIENTO | H18: COSTO D=C*R
A19: 20001 | B19: =IF($A19=0,"",VLOOKUP($A19,'BASE M-OBRA'!$A:$D,2)) -> MAESTRO | D19: 1 | E19: =IF($A19=0,"",VLOOKUP($A19,'BASE M-OBRA'!$A:$D,4)) -> 3.02 | F19: =IF($A19=0,"",ROUND(D19*E19,2)) -> 3.02 | G19: =IF($A19=0,"",ROUND(H19/F19,2)) -> 0.03 | H19: =IF($A19=0,"",ROUND(SUM(H20:H25)*'BASE M-OBRA'!$D$23,2)) -> 0.09
A20: 20002 | B20: =IF($A20=0,"",VLOOKUP($A20,'BASE M-OBRA'!$A:$D,2)) -> PEON | D20: 4 | E20: =IF($A20=0,"",VLOOKUP($A20,'BASE M-OBRA'!$A:$D,4)) -> 2.79 | F20: =IF($A20=0,"",ROUND(D20*E20,2)) -> 11.16 | G20: 0.04 | H20: =IF($A20=0,"",ROUND(G20*F20,2)) -> 0.45
B21: =IF($A21=0,"",VLOOKUP($A21,'BASE M-OBRA'!$A:$D,2)) | E21: =IF($A21=0,"",VLOOKUP($A21,'BASE M-OBRA'!$A:$D,4)) | F21: =IF($A21=0,"",ROUND(D21*E21,2)) | H21: =IF($A21=0,"",ROUND(G21*F21,2))
B22: =IF($A22=0,"",VLOOKUP($A22,'BASE M-OBRA'!$A:$D,2)) | E22: =IF($A22=0,"",VLOOKUP($A22,'BASE M-OBRA'!$A:$D,4)) | F22: =IF($A22=0,"",ROUND(D22*E22,2)) | H22: =IF($A22=0,"",ROUND(G22*F22,2))
B23: =IF($A23=0,"",VLOOKUP($A23,'BASE M-OBRA'!$A:$D,2)) | E23: =IF($A23=0,"",VLOOKUP($A23,'BASE M-OBRA'!$A:$D,4)) | F23: =IF($A23=0,"",ROUND(D23*E23,2)) | H23: =IF($A23=0,"",ROUND(G23*F23,2))
B24: =IF($A24=0,"",VLOOKUP($A24,'BASE M-OBRA'!$A:$D,2)) | E24: =IF($A24=0,"",VLOOKUP($A24,'BASE M-OBRA'!$A:$D,4)) | F24: =IF($A24=0,"",ROUND(D24*E24,2)) | H24: =IF($A24=0,"",ROUND(G24*F24,2))
B25: =IF($A25=0,"",VLOOKUP($A25,'BASE M-OBRA'!$A:$D,2)) | E25: =IF($A25=0,"",VLOOKUP($A25,'BASE M-OBRA'!$A:$D,4)) | F25: =IF($A25=0,"",ROUND(D25*E25,2)) | H25: =IF($A25=0,"",ROUND(G25*F25,2))
B26: SUBTOTAL N | H26: =ROUND(SUM(H18:H25),2) -> 0.54
B27: MATERIALES
B28: DESCRIPCION | E28: UNIDAD | F28: CANTIDAD A | G28: UNITARIO B | H28: COSTO C=A*B
B29: =IF($A29=0,"",VLOOKUP($A29,'BASE MATERIAL'!$A:$D,2)) | E29: =IF($A29=0,"",VLOOKUP($A29,'BASE MATERIAL'!$A:$D,3)) | G29: =IF($A29=0,"",VLOOKUP($A29,'BASE MATERIAL'!$A:$D,4)) | H29: =IF($A29=0,"",ROUND(F29*G29,2))
B30: =IF($A30=0,"",VLOOKUP($A30,'BASE MATERIAL'!$A:$D,2)) | E30: =IF($A30=0,"",VLOOKUP($A30,'BASE MATERIAL'!$A:$D,3)) | G30: =IF($A30=0,"",VLOOKUP($A30,'BASE MATERIAL'!$A:$D,4)) | H30: =IF($A30=0,"",ROUND(F30*G30,2))
B31: =IF($A31=0,"",VLOOKUP($A31,'BASE MATERIAL'!$A:$D,2)) | E31: =IF($A31=0,"",VLOOKUP($A31,'BASE MATERIAL'!$A:$D,3)) | G31: =IF($A31=0,"",VLOOKUP($A31,'BASE MATERIAL'!$A:$D,4)) | H31: =IF($A31=0,"",ROUND(F31*G31,2))
B32: =IF($A32=0,"",VLOOKUP($A32,'BASE MATERIAL'!$A:$D,2)) | E32: =IF($A32=0,"",VLOOKUP($A32,'BASE MATERIAL'!$A:$D,3)) | G32: =IF($A32=0,"",VLOOKUP($A32,'BASE MATERIAL'!$A:$D,4)) | H32: =IF($A32=0,"",ROUND(F32*G32,2))
B33: =IF($A33=0,"",VLOOKUP($A33,'BASE MATERIAL'!$A:$D,2)) | E33: =IF($A33=0,"",VLOOKUP($A33,'BASE MATERIAL'!$A:$D,3)) | G33: =IF($A33=0,"",VLOOKUP($A33,'BASE MATERIAL'!$A:$D,4)) | H33: =IF($A33=0,"",ROUND(F33*G33,2))
B34: =IF($A34=0,"",VLOOKUP($A34,'BASE MATERIAL'!$A:$D,2)) | E34: =IF($A34=0,"",VLOOKUP($A34,'BASE MATERIAL'!$A:$D,3)) | G34: =IF($A34=0,"",VLOOKUP($A34,'BASE MATERIAL'!$A:$D,4)) | H34: =IF($A34=0,"",ROUND(F34*G34,2))
B35: =IF($A35=0,"",VLOOKUP($A35,'BASE MATERIAL'!$A:$D,2)) | E35: =IF($A35=0,"",VLOOKUP($A35,'BASE MATERIAL'!$A:$D,3)) | G35: =IF($A35=0,"",VLOOKUP($A35,'BASE MATERIAL'!$A:$D,4)) | H35: =IF($A35=0,"",ROUND(F35*G35,2))
B36: =IF($A36=0,"",VLOOKUP($A36,'BASE MATERIAL'!$A:$D,2)) | E36: =IF($A36=0,"",VLOOKUP($A36,'BASE MATERIAL'!$A:$D,3)) | G36: =IF($A36=0,"",VLOOKUP($A36,'BASE MATERIAL'!$A:$D,4)) | H36: =IF($A36=0,"",ROUND(F36*G36,2))
B37: =IF($A37=0,"",VLOOKUP($A37,'BASE MATERIAL'!$A:$D,2)) | E37: =IF($A37=0,"",VLOOKUP($A37,'BASE MATERIAL'!$A:$D,3)) | G37: =IF($A37=0,"",VLOOKUP($A37,'BASE MATERIAL'!$A:$D,4)) | H37: =IF($A37=0,"",ROUND(F37*G37,2))
B38: =IF($A38=0,"",VLOOKUP($A38,'BASE MATERIAL'!$A:$D,2)) | E38: =IF($A38=0,"",VLOOKUP($A38,'BASE MATERIAL'!$A:$D,3)) | G38: =IF($A38=0,"",VLOOKUP($A38,'BASE MATERIAL'!$A:$D,4)) | H38: =IF($A38=0,"",ROUND(F38*G38,2))
B39: =IF($A39=0,"",VLOOKUP($A39,'BASE MATERIAL'!$A:$D,2)) | E39: =IF($A39=0,"",VLOOKUP($A39,'BASE MATERIAL'!$A:$D,3)) | G39: =IF($A39=0,"",VLOOKUP($A39,'BASE MATERIAL'!$A:$D,4)) | H39: =IF($A39=0,"",ROUND(F39*G39,2))
B40: =IF($A40=0,"",VLOOKUP($A40,'BASE MATERIAL'!$A:$D,2)) | E40: =IF($A40=0,"",VLOOKUP($A40,'BASE MATERIAL'!$A:$D,3)) | G40: =IF($A40=0,"",VLOOKUP($A40,'BASE MATERIAL'!$A:$D,4)) | H40: =IF($A40=0,"",ROUND(F40*G40,2))
... B43: =IF($A43=0,"",VLOOKUP($A43,'BASE MATERIAL'!$A:$D,2)) | E43: =IF($A43=0,"",VLOOKUP($A43,'BASE MATERIAL'!$A:$D,3)) | G43: =IF($A43=0,"",VLOOKUP($A43,'BASE MATERIAL'!$A:$D,4)) | H43: =IF($A43=0,"",ROUND(F43*G43,2))
B44: =IF($A44=0,"",VLOOKUP($A44,'BASE MATERIAL'!$A:$D,2)) | E44: =IF($A44=0,"",VLOOKUP($A44,'BASE MATERIAL'!$A:$D,3)) | G44: =IF($A44=0,"",VLOOKUP($A44,'BASE MATERIAL'!$A:$D,4)) | H44: =IF($A44=0,"",ROUND(E44*F44,2))
B45: SUBTOTAL O | H45: =ROUND(SUM(H28:H44),2) -> 0
B46: TRANSPORTE
B47: DESCRIPCION | E47: UNIDAD | F47: CANTIDAD A | G47: TARIFA B | H47: COSTO C=A*B
B48: =IF($A48=0,"",VLOOKUP($A48,'BASE EQUIPO'!$A:$D,2)) | E48: =IF($A48=0,"",VLOOKUP($A48,'BASE EQUIPO'!$A:$D,3)) | G48: =IF($A48=0,"",VLOOKUP($A48,'BASE EQUIPO'!$A:$D,4)*H45) | H48: =IF($A48=0,"",ROUND(F48*G48,2))
B49: =IF($A49=0,"",VLOOKUP($A49,'BASE EQUIPO'!$A:$D,2)) | E49: =IF($A49=0,"",VLOOKUP($A49,'BASE EQUIPO'!$A:$D,3)) | G49: =IF($A49=0,"",VLOOKUP($A49,'BASE EQUIPO'!$A:$D,4)*H46) | H49: =IF($A49=0,"",ROUND(F49*G49,2))
B50: =IF($A50=0,"",VLOOKUP($A50,'BASE EQUIPO'!$A:$D,2)) | E50: =IF($A50=0,"",VLOOKUP($A50,'BASE EQUIPO'!$A:$D,3)) | G50: =IF($A50=0,"",VLOOKUP($A50,'BASE EQUIPO'!$A:$D,4)*H47) | H50: =IF($A50=0,"",ROUND(F50*G50,2))
B51: SUBTOTAL P | H51: =ROUND(SUM(H47:H50),2) -> 0
D52: TOTAL COSTO DIRECTO (M+N+O+P) | H52: =ROUND(SUM(H51,H45,H26,H16),2) -> 0.56
A53: 40002 | D53: INDIRECTOS Y UTILIDADES % | G53: =IF($A53=0,"",VLOOKUP($A53,'BASE MATERIAL'!$M:$P,4)) -> 0 | H53: =IF($A53=0,"",ROUND(G53*H52,2)) -> 0
A54: 40003 | D54: OTROS INDIRECTOS % | G54: =IF($A54=0,"",VLOOKUP($A54,'BASE MATERIAL'!$M:$P,4)) -> 0 | H54: =IF($A54=0,"",ROUND(G54*H52,2)) -> 0
D55: COSTO TOTAL DEL RUBRO | H55: =ROUND(SUM(H52:H54),2) -> 0.56
D56: VALOR OFERTADO | H56: =ROUND(H55,2) -> 0.56 | K56: 0.5
B57: NOMBRE DEL PROPONENTE: | D57: ='1.1'!$D$1 -> ESPOL | H57: FORM. #3 | L57: =A61 -> 1 | M57: =C62 -> Replanteo de la terraza | N57: =H61 -> M2 | O57: =H112 -> 0.35
B58: OBRA: | C58: ='1.1'!$C$2 -> 0 | G58: HOJA | I58: de
C59: ='1.1'!$C$3 -> 0
B60: ANALISIS DE PRECIOS UNITARIOS
A61: 1 | B61: RUBRO | C61: 1.3.2 | G61: UNIDAD: | H61: M2
B62: DETALLE | C62: Replanteo de la terraza
B64: EQUIPOS
B65: DESCRIPCION | D65: CANTIDAD A | E65: TARIFA B | F65: COSTO HORA C= A*B | G65: RENDIMIENTO | H65: COSTO D=C*R
A66: 19015 | B66: =IF($A66=0,"",VLOOKUP($A66,'BASE EQUIPO'!$A:$D,2)) -> HERRAMIENTA MENOR | D66: 1 | E66: =IF($A66=0,"",VLOOKUP($A66,'BASE EQUIPO'!$A:$D,4)*H82) -> 0.0054 | F66: =IF($A66=0,"",ROUND(D66*E66,2)) -> 0.01 | G66: 1 | H66: =IF($A66=0,"",ROUND(G66*F66,2)) -> 0.01
A67: 19007 | B67: =IF($A67=0,"",VLOOKUP($A67,'BASE EQUIPO'!$A:$D,2)) -> TEODOLITO | D67: 1 | E67: =IF($A67=0,"",VLOOKUP($A67,'BASE EQUIPO'!$A:$D,4)) -> 10 | F67: =IF($A67=0,"",ROUND(D67*E67,2)) -> 10 | G67: 0.01 | H67: =IF($A67=0,"",ROUND(G67*F67,2)) -> 0.1
B68: =IF($A68=0,"",VLOOKUP($A68,'BASE EQUIPO'!$A:$D,2)) | E68: =IF($A68=0,"",VLOOKUP($A68,'BASE EQUIPO'!$A:$D,4)) | F68: =IF($A68=0,"",ROUND(D68*E68,2)) | H68: =IF($A68=0,"",ROUND(G68*F68,2))
B69: =IF($A69=0,"",VLOOKUP($A69,'BASE EQUIPO'!$A:$D,2)) | E69: =IF($A69=0,"",VLOOKUP($A69,'BASE EQUIPO'!$A:$D,4)) | F69: =IF($A69=0,"",ROUND(D69*E69,2)) | H69: =IF($A69=0,"",ROUND(G69*F69,2))
B70: =IF($A70=0,"",VLOOKUP($A70,'BASE EQUIPO'!$A:$D,2)) | E70: =IF($A70=0,"",VLOOKUP($A70,'BASE EQUIPO'!$A:$D,4)) | F70: =IF($A70=0,"",ROUND(D70*E70,2)) | H70: =IF($A70=0,"",ROUND(G70*F70,2))
B71: =IF($A71=0,"",VLOOKUP($A71,'BASE EQUIPO'!$A:$D,2)) | E71: =IF($A71=0,"",VLOOKUP($A71,'BASE EQUIPO'!$A:$D,4)) | F71: =IF($A71=0,"",ROUND(D71*E71,2)) | H71: =IF($A71=0,"",ROUND(G71*F71,2))
B72: SUBTOTAL M | H72: =ROUND(SUM(H65:H71),2) -> 0.11
B73: MANO DE OBRA
B74: DESCRIPCION (CATEG) | D74: CANTIDAD A | E74: JORNAL/HR B | F74: COSTO HORA C= A*B | G74: RENDIMIENTO | H74: COSTO D=C*R
A75: 20007 | B75: =IF($A75=0,"",VLOOKUP($A75,'BASE M-OBRA'!$A:$D,2)) -> TOPOGRAFO | D75: 1 | E75: =IF($A75=0,"",VLOOKUP($A75,'BASE M-OBRA'!$A:$D,4)) -> 3.02 | F75: =IF($A75=0,"",ROUND(D75*E75,2)) -> 3.02 | G75: =IF($A75=0,"",ROUND(H75/F75,2)) -> 0.01 | H75: =IF($A75=0,"",ROUND(SUM(H76:H81)*'BASE M-OBRA'!$D$23,2)) -> 0.03
A76: 20010 | B76: =IF($A76=0,"",VLOOKUP($A76,'BASE M-OBRA'!$A:$D,2)) -> CADENERO | D76: 2 | E76: =IF($A76=0,"",VLOOKUP($A76,'BASE M-OBRA'!$A:$D,4)) -> 2.82 | F76: =IF($A76=0,"",ROUND(D76*E76,2)) -> 5.64 | G76: 0.018 | H76: =IF($A76=0,"",ROUND(G76*F76,2)) -> 0.1
A77: 20002 | B77: =IF($A77=0,"",VLOOKUP($A77,'BASE M-OBRA'!$A:$D,2)) -> PEON | D77: 1 | E77: =IF($A77=0,"",VLOOKUP($A77,'BASE M-OBRA'!$A:$D,4)) -> 2.79 | F77: =IF($A77=0,"",ROUND(D77*E77,2)) -> 2.79 | G77: =+G76 -> 0.018 | H77: =IF($A77=0,"",ROUND(G77*F77,2)) -> 0.05
B78: =IF($A78=0,"",VLOOKUP($A78,'BASE M-OBRA'!$A:$D,2)) | E78: =IF($A78=0,"",VLOOKUP($A78,'BASE M-OBRA'!$A:$D,4)) | F78: =IF($A78=0,"",ROUND(D78*E78,2)) | H78: =IF($A78=0,"",ROUND(G78*F78,2))
B79: =IF($A79=0,"",VLOOKUP($A79,'BASE M-OBRA'!$A:$D,2)) | E79: =IF($A79=0,"",VLOOKUP($A79,'BASE M-OBRA'!$A:$D,4)) | F79: =IF($A79=0,"",ROUND(D79*E79,2)) | H79: =IF($A79=0,"",ROUND(G79*F79,2))
B80: =IF($A80=0,"",VLOOKUP($A80,'BASE M-OBRA'!$A:$D,2)) | E80: =IF($A80=0,"",VLOOKUP($A80,'BASE M-OBRA'!$A:$D,4)) | F80: =IF($A80=0,"",ROUND(D80*E80,2)) | H80: =IF($A80=0,"",ROUND(G80*F80,2))
B81: =IF($A81=0,"",VLOOKUP($A81,'BASE M-OBRA'!$A:$D,2)) | E81: =IF($A81=0,"",VLOOKUP($A81,'BASE M-OBRA'!$A:$D,4)) | F81: =IF($A81=0,"",ROUND(D81*E81,2)) | H81: =IF($A81=0,"",ROUND(G81*F81,2))
B82: SUBTOTAL N | H82: =ROUND(SUM(H74:H81),2) -> 0.18
B83: MATERIALES
B84: DESCRIPCION | E84: UNIDAD | F84: CANTIDAD A | G84: UNITARIO B | H84: COSTO C=A*B
A85: 11009 | B85: =IF($A85=0,"",VLOOKUP($A85,'BASE MATERIAL'!$A:$D,2)) -> CUARTON | E85: =IF($A85=0,"",VLOOKUP($A85,'BASE MATERIAL'!$A:$D,3)) -> U | F85: 0.01 | G85: =IF($A85=0,"",VLOOKUP($A85,'BASE MATERIAL'!$A:$D,4)) -> 2.42 | H85: =IF($A85=0,"",ROUND(F85*G85,2)) -> 0.02
A86: 11004 | B86: =IF($A86=0,"",VLOOKUP($A86,'BASE MATERIAL'!$A:$D,2)) -> PIOLA | E86: =IF($A86=0,"",VLOOKUP($A86,'BASE MATERIAL'!$A:$D,3)) -> ML | F86: 1 | G86: =IF($A86=0,"",VLOOKUP($A86,'BASE MATERIAL'!$A:$D,4)) -> 0.02 | H86: =IF($A86=0,"",ROUND(F86*G86,2)) -> 0.02
A87: 4004 | B87: =IF($A87=0,"",VLOOKUP($A87,'BASE MATERIAL'!$A:$D,2)) -> CAL | E87: =IF($A87=0,"",VLOOKUP($A87,'BASE MATERIAL'!$A:$D,3)) -> KG | F87: 0.2 | G87: =IF($A87=0,"",VLOOKUP($A87,'BASE MATERIAL'!$A:$D,4)) -> 0.1 | H87: =IF($A87=0,"",ROUND(F87*G87,2)) -> 0.02
B88: =IF($A88=0,"",VLOOKUP($A88,'BASE MATERIAL'!$A:$D,2)) | E88: =IF($A88=0,"",VLOOKUP($A88,'BASE MATERIAL'!$A:$D,3)) | G88: =IF($A88=0,"",VLOOKUP($A88,'BASE MATERIAL'!$A:$D,4)) | H88: =IF($A88=0,"",ROUND(F88*G88,2))
B89: =IF($A89=0,"",VLOOKUP($A89,'BASE MATERIAL'!$A:$D,2)) | E89: =IF($A89=0,"",VLOOKUP($A89,'BASE MATERIAL'!$A:$D,3)) | G89: =IF($A89=0,"",VLOOKUP($A89,'BASE MATERIAL'!$A:$D,4)) | H89: =IF($A89=0,"",ROUND(F89*G89,2))
B90: =IF($A90=0,"",VLOOKUP($A90,'BASE MATERIAL'!$A:$D,2)) | E90: =IF($A90=0,"",VLOOKUP($A90,'BASE MATERIAL'!$A:$D,3)) | G90: =IF($A90=0,"",VLOOKUP($A90,'BASE MATERIAL'!$A:$D,4)) | H90: =IF($A90=0,"",ROUND(F90*G90,2))
B91: =IF($A91=0,"",VLOOKUP($A91,'BASE MATERIAL'!$A:$D,2)) | E91: =IF($A91=0,"",VLOOKUP($A91,'BASE MATERIAL'!$A:$D,3)) | G91: =IF($A91=0,"",VLOOKUP($A91,'BASE MATERIAL'!$A:$D,4)) | H91: =IF($A91=0,"",ROUND(F91*G91,2))
B92: =IF($A92=0,"",VLOOKUP($A92,'BASE MATERIAL'!$A:$D,2)) | E92: =IF($A92=0,"",VLOOKUP($A92,'BASE MATERIAL'!$A:$D,3)) | G92: =IF($A92=0,"",VLOOKUP($A92,'BASE MATERIAL'!$A:$D,4)) | H92: =IF($A92=0,"",ROUND(F92*G92,2))
B93: =IF($A93=0,"",VLOOKUP($A93,'BASE MATERIAL'!$A:$D,2)) | E93: =IF($A93=0,"",VLOOKUP($A93,'BASE MATERIAL'!$A:$D,3)) | G93: =IF($A93=0,"",VLOOKUP($A93,'BASE MATERIAL'!$A:$D,4)) | H93: =IF($A93=0,"",ROUND(F93*G93,2))
B94: =IF($A94=0,"",VLOOKUP($A94,'BASE MATERIAL'!$A:$D,2)) | E94: =IF($A94=0,"",VLOOKUP($A94,'BASE MATERIAL'!$A:$D,3)) | G94: =IF($A94=0,"",VLOOKUP($A94,'BASE MATERIAL'!$A:$D,4)) | H94: =IF($A94=0,"",ROUND(F94*G94,2))
B95: =IF($A95=0,"",VLOOKUP($A95,'BASE MATERIAL'!$A:$D,2)) | E95: =IF($A95=0,"",VLOOKUP($A95,'BASE MATERIAL'!$A:$D,3)) | G95: =IF($A95=0,"",VLOOKUP($A95,'BASE MATERIAL'!$A:$D,4)) | H95: =IF($A95=0,"",ROUND(F95*G95,2))
B96: =IF($A96=0,"",VLOOKUP($A96,'BASE MATERIAL'!$A:$D,2)) | E96: =IF($A96=0,"",VLOOKUP($A96,'BASE MATERIAL'!$A:$D,3)) | G96: =IF($A96=0,"",VLOOKUP($A96,'BASE MATERIAL'!$A:$D,4)) | H96: =IF($A96=0,"",ROUND(F96*G96,2))
B97: =IF($A97=0,"",VLOOKUP($A97,'BASE MATERIAL'!$A:$D,2)) | E97: =IF($A97=0,"",VLOOKUP($A97,'BASE MATERIAL'!$A:$D,3)) | G97: =IF($A97=0,"",VLOOKUP($A97,'BASE MATERIAL'!$A:$D,4)) | H97: =IF($A97=0,"",ROUND(F97*G97,2))
B98: =IF($A98=0,"",VLOOKUP($A98,'BASE MATERIAL'!$A:$D,2)) | E98: =IF($A98=0,"",VLOOKUP($A98,'BASE MATERIAL'!$A:$D,3)) | G98: =IF($A98=0,"",VLOOKUP($A98,'BASE MATERIAL'!$A:$D,4)) | H98: =IF($A98=0,"",ROUND(F98*G98,2))
B99: =IF($A99=0,"",VLOOKUP($A99,'BASE MATERIAL'!$A:$D,2)) | E99: =IF($A99=0,"",VLOOKUP($A99,'BASE MATERIAL'!$A:$D,3)) | G99: =IF($A99=0,"",VLOOKUP($A99,'BASE MATERIAL'!$A:$D,4)) | H99: =IF($A99=0,"",ROUND(F99*G99,2))
B100: =IF($A100=0,"",VLOOKUP($A100,'BASE MATERIAL'!$A:$D,2)) | E100: =IF($A100=0,"",VLOOKUP($A100,'BASE MATERIAL'!$A:$D,3)) | G100: =IF($A100=0,"",VLOOKUP($A100,'BASE MATERIAL'!$A:$D,4)) | H100: =IF($A100=0,"",ROUND(E100*F100,2))
B101: SUBTOTAL O | H101: =ROUND(SUM(H84:H100),2) -> 0.06
B102: TRANSPORTE
B103: DESCRIPCION | E103: UNIDAD | F103: CANTIDAD A | G103: TARIFA B | H103: COSTO C=A*B
A104: 19019 | B104: =IF($A104=0,"",VLOOKUP($A104,'BASE EQUIPO'!$A:$D,2)) -> TRANSPORTE DE MATERIAL | E104: =IF($A104=0,"",VLOOKUP($A104,'BASE EQUIPO'!$A:$D,3)) -> GLOBAL | F104: 1 | G104: =IF($A104=0,"",VLOOKUP($A104,'BASE EQUIPO'!$A:$D,4)*H101) -> 0.0018 | H104: =IF($A104=0,"",ROUND(F104*G104,2)) -> 0
...

Sheet 1.4
B1: NOMBRE DEL PROPONENTE: | D1: ='1.1'!$D$1 -> ESPOL | H1: FORM. #3 | L1: =A5 -> 4 | M1: =C6 -> Corte de terraza (terreno rocoso) | N1: =H5 -> m3 | O1: =H56 -> 12.2
B2: OBRA: | C2: ='1.1'!$C$2 -> 0 | G2: HOJA | I2: de
C3: ='1.1'!$C$3 -> 0
B4: ANALISIS DE PRECIOS UNITARIOS
A5: 4 | B5: RUBRO | C5: 1.4.1.1 | G5: UNIDAD: | H5: m3
B6: DETALLE | C6: Corte de terraza (terreno rocoso)
B8: EQUIPOS
B9: DESCRIPCION | D9: CANTIDAD A | E9: TARIFA B | F9: COSTO HORA C= A*B | G9: RENDIMIENTO | H9: COSTO D=C*R
A10: 19015 | B10: =IF($A10=0,"",VLOOKUP($A10,'BASE EQUIPO'!$A:$D,2)) -> HERRAMIENTA MENOR | D10: 1 | E10: =IF($A10=0,"",VLOOKUP($A10,'BASE EQUIPO'!$A:$D,4)*H26)+0.06 -> 0.1509 | F10: =IF($A10=0,"",ROUND(D10*E10,2)) -> 0.15 | G10: 1 | H10: =IF($A10=0,"",ROUND(G10*F10,2)) -> 0.15
A11: 1 | B11: Martillo de aire (inc. Compresor) | D11: 2 | E11: 11 | F11: =IF($A11=0,"",ROUND(D11*E11,2)) -> 22 | G11: 0.11 | H11: =IF($A11=0,"",ROUND(G11*F11,2)) -> 2.42
A12: 19002 | B12: Retroexcavadora | D12: 2 | E12: 30 | F12: =IF($A12=0,"",ROUND(D12*E12,2)) -> 60 | G12: 0.11 | H12: =IF($A12=0,"",ROUND(G12*F12,2)) -> 6.6
B13: =IF($A13=0,"",VLOOKUP($A13,'BASE EQUIPO'!$A:$D,2)) | E13: =IF($A13=0,"",VLOOKUP($A13,'BASE EQUIPO'!$A:$D,4)) | F13: =IF($A13=0,"",ROUND(D13*E13,2)) | H13: =IF($A13=0,"",ROUND(G13*F13,2))
B14: =IF($A14=0,"",VLOOKUP($A14,'BASE EQUIPO'!$A:$D,2)) | E14: =IF($A14=0,"",VLOOKUP($A14,'BASE EQUIPO'!$A:$D,4)) | F14: =IF($A14=0,"",ROUND(D14*E14,2)) | H14: =IF($A14=0,"",ROUND(G14*F14,2))
B15: =IF($A15=0,"",VLOOKUP($A15,'BASE EQUIPO'!$A:$D,2)) | E15: =IF($A15=0,"",VLOOKUP($A15,'BASE EQUIPO'!$A:$D,4)) | F15: =IF($A15=0,"",ROUND(D15*E15,2)) | H15: =IF($A15=0,"",ROUND(G15*F15,2))
B16: SUBTOTAL M | H16: =ROUND(SUM(H9:H15),2) -> 9.17
B17: MANO DE OBRA
B18: DESCRIPCION (CATEG) | D18: CANTIDAD A | E18: JORNAL/HR B | F18: COSTO HORA C= A*B | G18: RENDIMIENTO | H18: COSTO D=C*R
A20: 20002 | B20: =IF($A20=0,"",VLOOKUP($A20,'BASE M-OBRA'!$A:$D,2)) -> PEON | D20: 6 | E20: =IF($A20=0,"",VLOOKUP($A20,'BASE M-OBRA'!$A:$D,4)) -> 2.79 | F20: =IF($A20=0,"",ROUND(D20*E20,2)) -> 16.74 | G20: 0.105 | H20: =IF($A20=0,"",ROUND(G20*F20,2)) -> 1.76
A21: 20012 | B21: =IF($A21=0,"",VLOOKUP($A21,'BASE M-OBRA'!$A:$D,2)) -> OP.EQUIPO PESADO | D21: 4 | E21: =IF($A21=0,"",VLOOKUP($A21,'BASE M-OBRA'!$A:$D,4)) -> 3.02 | F21: =IF($A21=0,"",ROUND(D21*E21,2)) -> 12.08 | G21: =+G20 -> 0.105 | H21: =IF($A21=0,"",ROUND(G21*F21,2)) -> 1.27
B22: =IF($A22=0,"",VLOOKUP($A22,'BASE M-OBRA'!$A:$D,2)) | E22: =IF($A22=0,"",VLOOKUP($A22,'BASE M-OBRA'!$A:$D,4)) | F22: =IF($A22=0,"",ROUND(D22*E22,2)) | H22: =IF($A22=0,"",ROUND(G22*F22,2))
B23: =IF($A23=0,"",VLOOKUP($A23,'BASE M-OBRA'!$A:$D,2)) | E23: =IF($A23=0,"",VLOOKUP($A23,'BASE M-OBRA'!$A:$D,4)) | F23: =IF($A23=0,"",ROUND(D23*E23,2)) | H23: =IF($A23=0,"",ROUND(G23*F23,2))
B24: =IF($A24=0,"",VLOOKUP($A24,'BASE M-OBRA'!$A:$D,2)) | E24: =IF($A24=0,"",VLOOKUP($A24,'BASE M-OBRA'!$A:$D,4)) | F24: =IF($A24=0,"",ROUND(D24*E24,2)) | H24: =IF($A24=0,"",ROUND(G24*F24,2))
B25: =IF($A25=0,"",VLOOKUP($A25,'BASE M-OBRA'!$A:$D,2)) | E25: =IF($A25=0,"",VLOOKUP($A25,'BASE M-OBRA'!$A:$D,4)) | F25: =IF($A25=0,"",ROUND(D25*E25,2)) | H25: =IF($A25=0,"",ROUND(G25*F25,2))
B26: SUBTOTAL N | H26: =ROUND(SUM(H18:H25),2) -> 3.03
B27: MATERIALES
B28: DESCRIPCION | E28: UNIDAD | F28: CANTIDAD A | G28: UNITARIO B | H28: COSTO C=A*B
B29: =IF($A29=0,"",VLOOKUP($A29,'BASE MATERIAL'!$A:$D,2)) | E29: =IF($A29=0,"",VLOOKUP($A29,'BASE MATERIAL'!$A:$D,3)) | G29: =IF($A29=0,"",VLOOKUP($A29,'BASE MATERIAL'!$A:$D,4)) | H29: =IF($A29=0,"",ROUND(F29*G29,2))
B30: =IF($A30=0,"",VLOOKUP($A30,'BASE MATERIAL'!$A:$D,2)) | E30: =IF($A30=0,"",VLOOKUP($A30,'BASE MATERIAL'!$A:$D,3)) | G30: =IF($A30=0,"",VLOOKUP($A30,'BASE MATERIAL'!$A:$D,4)) | H30: =IF($A30=0,"",ROUND(F30*G30,2))
B31: =IF($A31=0,"",VLOOKUP($A31,'BASE MATERIAL'!$A:$D,2)) | E31: =IF($A31=0,"",VLOOKUP($A31,'BASE MATERIAL'!$A:$D,3)) | G31: =IF($A31=0,"",VLOOKUP($A31,'BASE MATERIAL'!$A:$D,4)) | H31: =IF($A31=0,"",ROUND(F31*G31,2))
B32: =IF($A32=0,"",VLOOKUP($A32,'BASE MATERIAL'!$A:$D,2)) | E32: =IF($A32=0,"",VLOOKUP($A32,'BASE MATERIAL'!$A:$D,3)) | G32: =IF($A32=0,"",VLOOKUP($A32,'BASE MATERIAL'!$A:$D,4)) | H32: =IF($A32=0,"",ROUND(F32*G32,2))
B33: =IF($A33=0,"",VLOOKUP($A33,'BASE MATERIAL'!$A:$D,2)) | E33: =IF($A33=0,"",VLOOKUP($A33,'BASE MATERIAL'!$A:$D,3)) | G33: =IF($A33=0,"",VLOOKUP($A33,'BASE MATERIAL'!$A:$D,4)) | H33: =IF($A33=0,"",ROUND(F33*G33,2))
B34: =IF($A34=0,"",VLOOKUP($A34,'BASE MATERIAL'!$A:$D,2)) | E34: =IF($A34=0,"",VLOOKUP($A34,'BASE MATERIAL'!$A:$D,3)) | G34: =IF($A34=0,"",VLOOKUP($A34,'BASE MATERIAL'!$A:$D,4)) | H34: =IF($A34=0,"",ROUND(F34*G34,2))
B35: =IF($A35=0,"",VLOOKUP($A35,'BASE MATERIAL'!$A:$D,2)) | E35: =IF($A35=0,"",VLOOKUP($A35,'BASE MATERIAL'!$A:$D,3)) | G35: =IF($A35=0,"",VLOOKUP($A35,'BASE MATERIAL'!$A:$D,4)) | H35: =IF($A35=0,"",ROUND(F35*G35,2))
B36: =IF($A36=0,"",VLOOKUP($A36,'BASE MATERIAL'!$A:$D,2)) | E36: =IF($A36=0,"",VLOOKUP($A36,'BASE MATERIAL'!$A:$D,3)) | G36: =IF($A36=0,"",VLOOKUP($A36,'BASE MATERIAL'!$A:$D,4)) | H36: =IF($A36=0,"",ROUND(F36*G36,2))
B37: =IF($A37=0,"",VLOOKUP($A37,'BASE MATERIAL'!$A:$D,2)) | E37: =IF($A37=0,"",VLOOKUP($A37,'BASE MATERIAL'!$A:$D,3)) | G37: =IF($A37=0,"",VLOOKUP($A37,'BASE MATERIAL'!$A:$D,4)) | H37: =IF($A37=0,"",ROUND(F37*G37,2))
B38: =IF($A38=0,"",VLOOKUP($A38,'BASE MATERIAL'!$A:$D,2)) | E38: =IF($A38=0,"",VLOOKUP($A38,'BASE MATERIAL'!$A:$D,3)) | G38: =IF($A38=0,"",VLOOKUP($A38,'BASE MATERIAL'!$A:$D,4)) | H38: =IF($A38=0,"",ROUND(F38*G38,2))
B39: =IF($A39=0,"",VLOOKUP($A39,'BASE MATERIAL'!$A:$D,2)) | E39: =IF($A39=0,"",VLOOKUP($A39,'BASE MATERIAL'!$A:$D,3)) | G39: =IF($A39=0,"",VLOOKUP($A39,'BASE MATERIAL'!$A:$D,4)) | H39: =IF($A39=0,"",ROUND(F39*G39,2))
B40: =IF($A40=0,"",VLOOKUP($A40,'BASE MATERIAL'!$A:$D,2)) | E40: =IF($A40=0,"",VLOOKUP($A40,'BASE MATERIAL'!$A:$D,3)) | G40: =IF($A40=0,"",VLOOKUP($A40,'BASE MATERIAL'!$A:$D,4)) | H40: =IF($A40=0,"",ROUND(F40*G40,2))
... B43: =IF($A43=0,"",VLOOKUP($A43,'BASE MATERIAL'!$A:$D,2)) | E43: =IF($A43=0,"",VLOOKUP($A43,'BASE MATERIAL'!$A:$D,3)) | G43: =IF($A43=0,"",VLOOKUP($A43,'BASE MATERIAL'!$A:$D,4)) | H43: =IF($A43=0,"",ROUND(F43*G43,2))
B44: =IF($A44=0,"",VLOOKUP($A44,'BASE MATERIAL'!$A:$D,2)) | E44: =IF($A44=0,"",VLOOKUP($A44,'BASE MATERIAL'!$A:$D,3)) | G44: =IF($A44=0,"",VLOOKUP($A44,'BASE MATERIAL'!$A:$D,4)) | H44: =IF($A44=0,"",ROUND(E44*F44,2))
B45: SUBTOTAL O | H45: =ROUND(SUM(H28:H44),2) -> 0
B46: TRANSPORTE
B47: DESCRIPCION | E47: UNIDAD | F47: CANTIDAD A | G47: TARIFA B | H47: COSTO C=A*B
H48: =IF($A48=0,"",ROUND(F48*G48,2))
B49: =IF($A49=0,"",VLOOKUP($A49,'BASE EQUIPO'!$A:$D,2)) | E49: =IF($A49=0,"",VLOOKUP($A49,'BASE EQUIPO'!$A:$D,3)) | G49: =IF($A49=0,"",VLOOKUP($A49,'BASE EQUIPO'!$A:$D,4)*H46) | H49: =IF($A49=0,"",ROUND(F49*G49,2))
B50: =IF($A50=0,"",VLOOKUP($A50,'BASE EQUIPO'!$A:$D,2)) | E50: =IF($A50=0,"",VLOOKUP($A50,'BASE EQUIPO'!$A:$D,3)) | G50: =IF($A50=0,"",VLOOKUP($A50,'BASE EQUIPO'!$A:$D,4)*H47) | H50: =IF($A50=0,"",ROUND(F50*G50,2))
B51: SUBTOTAL P | H51: =ROUND(SUM(H47:H50),2) -> 0
D52: TOTAL COSTO DIRECTO (M+N+O+P) | H52: =ROUND(SUM(H51,H45,H26,H16),2) -> 12.2
A53: 40002 | D53: INDIRECTOS Y UTILIDADES % | G53: =IF($A53=0,"",VLOOKUP($A53,'BASE MATERIAL'!$M:$P,4)) -> 0 | H53: =IF($A53=0,"",ROUND(G53*H52,2)) -> 0
A54: 40003 | D54: OTROS INDIRECTOS % | G54: =IF($A54=0,"",VLOOKUP($A54,'BASE MATERIAL'!$M:$P,4)) -> 0 | H54: =IF($A54=0,"",ROUND(G54*H52,2)) -> 0
D55: COSTO TOTAL DEL RUBRO | H55: =ROUND(SUM(H52:H54),2) -> 12.2
D56: VALOR OFERTADO | H56: =ROUND(H55,2) -> 12.2 | K56: 11.38
B57: NOMBRE DEL PROPONENTE: | D57: =$D$1 -> ESPOL | H57: FORM. #3 | L57: =A61 -> 6 | M57: =C62 -> Relleno y compactacion en terraza (material de sitio) | N57: =H61 -> m3 | O57: =H112 -> 6.82
B58: OBRA: | C58: ='1.1'!$C$2 -> 0 | G58: HOJA | I58: de
C59: ='1.1'!$C$3 -> 0
B60: ANALISIS DE PRECIOS UNITARIOS
A61: 6 | B61: RUBRO | C61: 1.4.1,2 | G61: UNIDAD: | H61: m3
B62: DETALLE | C62: Relleno y compactacion en terraza (material de sitio)
B64: EQUIPOS
B65: DESCRIPCION | D65: CANTIDAD A | E65: TARIFA B | F65: COSTO HORA C= A*B | G65: RENDIMIENTO | H65: COSTO D=C*R
A66: 19015 | B66: =IF($A66=0,"",VLOOKUP($A66,'BASE EQUIPO'!$A:$D,2)) -> HERRAMIENTA MENOR | D66: 1 | E66: =IF($A66=0,"",VLOOKUP($A66,'BASE EQUIPO'!$A:$D,4)*H82)-0.02 -> 0.1327 | F66: =IF($A66=0,"",ROUND(D66*E66,2)) -> 0.13 | G66: 1 | H66: =IF($A66=0,"",ROUND(G66*F66,2)) -> 0.13
A67: 19029 | B67: =IF($A67=0,"",VLOOKUP($A67,'BASE EQUIPO'!$A:$D,2)) -> COMPACTADOR PESADO (RODILLO MANUAL) | D67: 2 | E67: =IF($A67=0,"",VLOOKUP($A67,'BASE EQUIPO'!$A:$D,4)) -> 3.5 | F67: =IF($A67=0,"",ROUND(D67*E67,2)) -> 7 | G67: 0.185 | H67: =IF($A67=0,"",ROUND(G67*F67,2)) -> 1.3
B68: =IF($A68=0,"",VLOOKUP($A68,'BASE EQUIPO'!$A:$D,2)) | E68: =IF($A68=0,"",VLOOKUP($A68,'BASE EQUIPO'!$A:$D,4)) | F68: =IF($A68=0,"",ROUND(D68*E68,2)) | H68: =IF($A68=0,"",ROUND(G68*F68,2))
B69: =IF($A69=0,"",VLOOKUP($A69,'BASE EQUIPO'!$A:$D,2)) | E69: =IF($A69=0,"",VLOOKUP($A69,'BASE EQUIPO'!$A:$D,4)) | F69: =IF($A69=0,"",ROUND(D69*E69,2)) | H69: =IF($A69=0,"",ROUND(G69*F69,2))
B70: =IF($A70=0,"",VLOOKUP($A70,'BASE EQUIPO'!$A:$D,2)) | E70: =IF($A70=0,"",VLOOKUP($A70,'BASE EQUIPO'!$A:$D,4)) | F70: =IF($A70=0,"",ROUND(D70*E70,2)) | H70: =IF($A70=0,"",ROUND(G70*F70,2))
B71: =IF($A71=0,"",VLOOKUP($A71,'BASE EQUIPO'!$A:$D,2)) | E71: =IF($A71=0,"",VLOOKUP($A71,'BASE EQUIPO'!$A:$D,4)) | F71: =IF($A71=0,"",ROUND(D71*E71,2)) | H71: =IF($A71=0,"",ROUND(G71*F71,2))
B72: SUBTOTAL M | H72: =ROUND(SUM(H65:H71),2) -> 1.43
B73: MANO DE OBRA
B74: DESCRIPCION (CATEG) | D74: CANTIDAD A | E74: JORNAL/HR B | F74: COSTO HORA C= A*B | G74: RENDIMIENTO | H74: COSTO D=C*R
A75: 20001 | B75: =IF($A75=0,"",VLOOKUP($A75,'BASE M-OBRA'!$A:$D,2)) -> MAESTRO | D75: 1 | E75: =IF($A75=0,"",VLOOKUP($A75,'BASE M-OBRA'!$A:$D,4)) -> 3.02 | F75: =IF($A75=0,"",ROUND(D75*E75,2)) -> 3.02 | G75: =IF($A75=0,"",ROUND(H75/F75,2)) -> 0.28 | H75: =IF($A75=0,"",ROUND(SUM(H76:H81)*'BASE M-OBRA'!$D$23,2)) -> 0.85
A76: 20002 | B76: =IF($A76=0,"",VLOOKUP($A76,'BASE M-OBRA'!$A:$D,2)) -> PEON | D76: 4 | E76: =IF($A76=0,"",VLOOKUP($A76,'BASE M-OBRA'!$A:$D,4)) -> 2.79 | F76: =IF($A76=0,"",ROUND(D76*E76,2)) -> 11.16 | G76: 0.38 | H76: =IF($A76=0,"",ROUND(G76*F76,2)) -> 4.24
B77: =IF($A77=0,"",VLOOKUP($A77,'BASE M-OBRA'!$A:$D,2)) | E77: =IF($A77=0,"",VLOOKUP($A77,'BASE M-OBRA'!$A:$D,4)) | F77: =IF($A77=0,"",ROUND(D77*E77,2)) | H77: =IF($A77=0,"",ROUND(G77*F77,2))
B78: =IF($A78=0,"",VLOOKUP($A78,'BASE M-OBRA'!$A:$D,2)) | E78: =IF($A78=0,"",VLOOKUP($A78,'BASE M-OBRA'!$A:$D,4)) | F78: =IF($A78=0,"",ROUND(D78*E78,2)) | H78: =IF($A78=0,"",ROUND(G78*F78,2))
B79: =IF($A79=0,"",VLOOKUP($A79,'BASE M-OBRA'!$A:$D,2)) | E79: =IF($A79=0,"",VLOOKUP($A79,'BASE M-OBRA'!$A:$D,4)) | F79: =IF($A79=0,"",ROUND(D79*E79,2)) | H79: =IF($A79=0,"",ROUND(G79*F79,2))
B80: =IF($A80=0,"",VLOOKUP($A80,'BASE M-OBRA'!$A:$D,2)) | E80: =IF($A80=0,"",VLOOKUP($A80,'BASE M-OBRA'!$A:$D,4)) | F80: =IF($A80=0,"",ROUND(D80*E80,2)) | H80: =IF($A80=0,"",ROUND(G80*F80,2))
B81: =IF($A81=0,"",VLOOKUP($A81,'BASE M-OBRA'!$A:$D,2)) | E81: =IF($A81=0,"",VLOOKUP($A81,'BASE M-OBRA'!$A:$D,4)) | F81: =IF($A81=0,"",ROUND(D81*E81,2)) | H81: =IF($A81=0,"",ROUND(G81*F81,2))
B82: SUBTOTAL N | H82: =ROUND(SUM(H74:H81),2) -> 5.09
B83: MATERIALES
B84: DESCRIPCION | E84: UNIDAD | F84: CANTIDAD A | G84: UNITARIO B | H84: COSTO C=A*B
B85: =IF($A85=0,"",VLOOKUP($A85,'BASE MATERIAL'!$A:$D,2)) | E85: =IF($A85=0,"",VLOOKUP($A85,'BASE MATERIAL'!$A:$D,3)) | G85: =IF($A85=0,"",VLOOKUP($A85,'BASE MATERIAL'!$A:$D,4)) | H85: =IF($A85=0,"",ROUND(F85*G85,2))
A86: 5005 | B86: =IF($A86=0,"",VLOOKUP($A86,'BASE MATERIAL'!$A:$D,2)) -> AGUA | E86: =IF($A86=0,"",VLOOKUP($A86,'BASE MATERIAL'!$A:$D,3)) -> LT | F86: 150 | G86: =IF($A86=0,"",VLOOKUP($A86,'BASE MATERIAL'!$A:$D,4)) -> 0.002 | H86: =IF($A86=0,"",ROUND(F86*G86,2)) -> 0.3
B87: =IF($A87=0,"",VLOOKUP($A87,'BASE MATERIAL'!$A:$D,2)) | E87: =IF($A87=0,"",VLOOKUP($A87,'BASE MATERIAL'!$A:$D,3)) | G87: =IF($A87=0,"",VLOOKUP($A87,'BASE MATERIAL'!$A:$D,4)) | H87: =IF($A87=0,"",ROUND(F87*G87,2))
B88: =IF($A88=0,"",VLOOKUP($A88,'BASE MATERIAL'!$A:$D,2)) | E88: =IF($A88=0,"",VLOOKUP($A88,'BASE MATERIAL'!$A:$D,3)) | G88: =IF($A88=0,"",VLOOKUP($A88,'BASE MATERIAL'!$A:$D,4)) | H88: =IF($A88=0,"",ROUND(F88*G88,2))
B89: =IF($A89=0,"",VLOOKUP($A89,'BASE MATERIAL'!$A:$D,2)) | E89: =IF($A89=0,"",VLOOKUP($A89,'BASE MATERIAL'!$A:$D,3)) | G89: =IF($A89=0,"",VLOOKUP($A89,'BASE MATERIAL'!$A:$D,4)) | H89: =IF($A89=0,"",ROUND(F89*G89,2))
B90: =IF($A90=0,"",VLOOKUP($A90,'BASE MATERIAL'!$A:$D,2)) | E90: =IF($A90=0,"",VLOOKUP($A90,'BASE MATERIAL'!$A:$D,3)) | G90: =IF($A90=0,"",VLOOKUP($A90,'BASE MATERIAL'!$A:$D,4)) | H90: =IF($A90=0,"",ROUND(F90*G90,2))
B91: =IF($A91=0,"",VLOOKUP($A91,'BASE MATERIAL'!$A:$D,2)) | E91: =IF($A91=0,"",VLOOKUP($A91,'BASE MATERIAL'!$A:$D,3)) | G91: =IF($A91=0,"",VLOOKUP($A91,'BASE MATERIAL'!$A:$D,4)) | H91: =IF($A91=0,"",ROUND(F91*G91,2))
B92: =IF($A92=0,"",VLOOKUP($A92,'BASE MATERIAL'!$A:$D,2)) | E92: =IF($A92=0,"",VLOOKUP($A92,'BASE MATERIAL'!$A:$D,3)) | G92: =IF($A92=0,"",VLOOKUP($A92,'BASE MATERIAL'!$A:$D,4)) | H92: =IF($A92=0,"",ROUND(F92*G92,2))
B93: =IF($A93=0,"",VLOOKUP($A93,'BASE MATERIAL'!$A:$D,2)) | E93: =IF($A93=0,"",VLOOKUP($A93,'BASE MATERIAL'!$A:$D,3)) | G93: =IF($A93=0,"",VLOOKUP($A93,'BASE MATERIAL'!$A:$D,4)) | H93: =IF($A93=0,"",ROUND(F93*G93,2))
B94: =IF($A94=0,"",VLOOKUP($A94,'BASE MATERIAL'!$A:$D,2)) | E94: =IF($A94=0,"",VLOOKUP($A94,'BASE MATERIAL'!$A:$D,3)) | G94: =IF($A94=0,"",VLOOKUP($A94,'BASE MATERIAL'!$A:$D,4)) | H94: =IF($A94=0,"",ROUND(F94*G94,2))
B95: =IF($A95=0,"",VLOOKUP($A95,'BASE MATERIAL'!$A:$D,2)) | E95: =IF($A95=0,"",VLOOKUP($A95,'BASE MATERIAL'!$A:$D,3)) | G95: =IF($A95=0,"",VLOOKUP($A95,'BASE MATERIAL'!$A:$D,4)) | H95: =IF($A95=0,"",ROUND(F95*G95,2))
B96: =IF($A96=0,"",VLOOKUP($A96,'BASE MATERIAL'!$A:$D,2)) | E96: =IF($A96=0,"",VLOOKUP($A96,'BASE MATERIAL'!$A:$D,3)) | G96: =IF($A96=0,"",VLOOKUP($A96,'BASE MATERIAL'!$A:$D,4)) | H96: =IF($A96=0,"",ROUND(F96*G96,2))
B97: =IF($A97=0,"",VLOOKUP($A97,'BASE MATERIAL'!$A:$D,2)) | E97: =IF($A97=0,"",VLOOKUP($A97,'BASE MATERIAL'!$A:$D,3)) | G97: =IF($A97=0,"",VLOOKUP($A97,'BASE MATERIAL'!$A:$D,4)) | H97: =IF($A97=0,"",ROUND(F97*G97,2))
B98: =IF($A98=0,"",VLOOKUP($A98,'BASE MATERIAL'!$A:$D,2)) | E98: =IF($A98=0,"",VLOOKUP($A98,'BASE MATERIAL'!$A:$D,3)) | G98: =IF($A98=0,"",VLOOKUP($A98,'BASE MATERIAL'!$A:$D,4)) | H98: =IF($A98=0,"",ROUND(F98*G98,2))
B99: =IF($A99=0,"",VLOOKUP($A99,'BASE MATERIAL'!$A:$D,2)) | E99: =IF($A99=0,"",VLOOKUP($A99,'BASE MATERIAL'!$A:$D,3)) | G99: =IF($A99=0,"",VLOOKUP($A99,'BASE MATERIAL'!$A:$D,4)) | H99: =IF($A99=0,"",ROUND(F99*G99,2))
B100: =IF($A100=0,"",VLOOKUP($A100,'BASE MATERIAL'!$A:$D,2)) | E100: =IF($A100=0,"",VLOOKUP($A100,'BASE MATERIAL'!$A:$D,3)) | G100: =IF($A100=0,"",VLOOKUP($A100,'BASE MATERIAL'!$A:$D,4)) | H100: =IF($A100=0,"",ROUND(E100*F100,2))
B101: SUBTOTAL O | H101: =ROUND(SUM(H84:H100),2) -> 0.3
B102: TRANSPORTE
B103: DESCRIPCION | E103: UNIDAD | F103: CANTIDAD A | G103: TARIFA B | H103: COSTO C=A*B
B104: =IF($A104=0,"",VLOOKUP($A104,'BASE EQUIPO'!$A:$D,2)) | E104: =IF($A104=0,"",VLOOKUP($A104,'BASE EQUIPO'!$A:$D,3)) | G104: =IF($A104=0,"",VLOOKUP($A104,'BASE EQUIPO'!$A:$D,4)*H101) | H104: =IF($A104=0,"",ROUND(F104*G104,2))
B105: =IF($A105=0,"",VLOOKUP($A105,'BASE EQUIPO'!$A:$D,2)) | E105: =IF($A105=0,"",VLOOKUP($A105,'BASE EQUIPO'!$A:$D,3)) | G105: =IF($A105=0,"",VLOOKUP($A105,'BASE EQUIPO'!$A:$D,4)*H102) | H105: =IF($A105=0,"",ROUND(F105*G105,2))
...

Sheet 1.5
B1: NOMBRE DEL PROPONENTE: | D1: ='1.1'!$D$1 -> ESPOL | H1: FORM. #3 | L1: =A5 -> 1 | M1: =C6 -> Replantillo hormigon simple | N1: =H5 -> m3 | O1: =H56 -> 113.61
B2: OBRA: | C2: ='1.1'!$C$2 -> 0 | G2: HOJA | I2: de
C3: ='1.1'!$C$3 -> 0
B4: ANALISIS DE PRECIOS UNITARIOS
A5: 1 | B5: RUBRO | C5: 1.5.1 | G5: UNIDAD: | H5: m3
B6: DETALLE | C6: Replantillo hormigon simple
B8: EQUIPOS
B9: DESCRIPCION | D9: CANTIDAD A | E9: TARIFA B | F9: COSTO HORA C= A*B | G9: RENDIMIENTO | H9: COSTO D=C*R
A10: 19015 | B10: =IF($A10=0,"",VLOOKUP($A10,'BASE EQUIPO'!$A:$D,2)) -> HERRAMIENTA MENOR | D10: 1 | E10: =IF($A10=0,"",VLOOKUP($A10,'BASE EQUIPO'!$A:$D,4)*H26) -> 1.2522 | F10: =IF($A10=0,"",ROUND(D10*E10,2)) -> 1.25 | G10: 1 | H10: =IF($A10=0,"",ROUND(G10*F10,2)) -> 1.25
A11: 19003 | B11: =IF($A11=0,"",VLOOKUP($A11,'BASE EQUIPO'!$A:$D,2)) -> CONCRETERA | D11: 1 | E11: =IF($A11=0,"",VLOOKUP($A11,'BASE EQUIPO'!$A:$D,4)) -> 3.5 | F11: =IF($A11=0,"",ROUND(D11*E11,2)) -> 3.5 | G11: =+G20*0.5 -> 0.775 | H11: =IF($A11=0,"",ROUND(G11*F11,2)) -> 2.71
B12: =IF($A12=0,"",VLOOKUP($A12,'BASE EQUIPO'!$A:$D,2)) | E12: =IF($A12=0,"",VLOOKUP($A12,'BASE EQUIPO'!$A:$D,4)) | F12: =IF($A12=0,"",ROUND(D12*E12,2)) | H12: =IF($A12=0,"",ROUND(G12*F12,2))
B13: =IF($A13=0,"",VLOOKUP($A13,'BASE EQUIPO'!$A:$D,2)) | E13: =IF($A13=0,"",VLOOKUP($A13,'BASE EQUIPO'!$A:$D,4)) | F13: =IF($A13=0,"",ROUND(D13*E13,2)) | H13: =IF($A13=0,"",ROUND(G13*F13,2))
B14: =IF($A14=0,"",VLOOKUP($A14,'BASE EQUIPO'!$A:$D,2)) | E14: =IF($A14=0,"",VLOOKUP($A14,'BASE EQUIPO'!$A:$D,4)) | F14: =IF($A14=0,"",ROUND(D14*E14,2)) | H14: =IF($A14=0,"",ROUND(G14*F14,2))
B15: =IF($A15=0,"",VLOOKUP($A15,'BASE EQUIPO'!$A:$D,2)) | E15: =IF($A15=0,"",VLOOKUP($A15,'BASE EQUIPO'!$A:$D,4)) | F15: =IF($A15=0,"",ROUND(D15*E15,2)) | H15: =IF($A15=0,"",ROUND(G15*F15,2))
B16: SUBTOTAL M | H16: =ROUND(SUM(H9:H15),2) -> 3.96
B17: MANO DE OBRA
B18: DESCRIPCION (CATEG) | D18: CANTIDAD A | E18: JORNAL/HR B | F18: COSTO HORA C= A*B | G18: RENDIMIENTO | H18: COSTO D=C*R
A19: 20001 | B19: =IF($A19=0,"",VLOOKUP($A19,'BASE M-OBRA'!$A:$D,2)) -> MAESTRO | D19: 1 | E19: =IF($A19=0,"",VLOOKUP($A19,'BASE M-OBRA'!$A:$D,4)) -> 3.02 | F19: =IF($A19=0,"",ROUND(D19*E19,2)) -> 3.02 | G19: =IF($A19=0,"",ROUND(H19/F19,2)) -> 2.3 | H19: =IF($A19=0,"",ROUND(SUM(H20:H25)*'BASE M-OBRA'!$D$23,2)) -> 6.96
A20: 20002 | B20: =IF($A20=0,"",VLOOKUP($A20,'BASE M-OBRA'!$A:$D,2)) -> PEON | D20: 4 | E20: =IF($A20=0,"",VLOOKUP($A20,'BASE M-OBRA'!$A:$D,4)) -> 2.79 | F20: =IF($A20=0,"",ROUND(D20*E20,2)) -> 11.16 | G20: 1.55 | H20: =IF($A20=0,"",ROUND(G20*F20,2)) -> 17.3
A21: 20003 | B21: =IF($A21=0,"",VLOOKUP($A21,'BASE M-OBRA'!$A:$D,2)) -> ALBAÑIL | D21: 2 | E21: =IF($A21=0,"",VLOOKUP($A21,'BASE M-OBRA'!$A:$D,4)) -> 2.82 | F21: =IF($A21=0,"",ROUND(D21*E21,2)) -> 5.64 | G21: =+G20 -> 1.55 | H21: =IF($A21=0,"",ROUND(G21*F21,2)) -> 8.74
A22: 20004 | B22: =IF($A22=0,"",VLOOKUP($A22,'BASE M-OBRA'!$A:$D,2)) -> CARPINTERO | D22: 2 | E22: =IF($A22=0,"",VLOOKUP($A22,'BASE M-OBRA'!$A:$D,4)) -> 2.82 | F22: =IF($A22=0,"",ROUND(D22*E22,2)) -> 5.64 | G22: =+G21 -> 1.55 | H22: =IF($A22=0,"",ROUND(G22*F22,2)) -> 8.74
B23: =IF($A23=0,"",VLOOKUP($A23,'BASE M-OBRA'!$A:$D,2)) | E23: =IF($A23=0,"",VLOOKUP($A23,'BASE M-OBRA'!$A:$D,4)) | F23: =IF($A23=0,"",ROUND(D23*E23,2)) | H23: =IF($A23=0,"",ROUND(G23*F23,2))
B24: =IF($A24=0,"",VLOOKUP($A24,'BASE M-OBRA'!$A:$D,2)) | E24: =IF($A24=0,"",VLOOKUP($A24,'BASE M-OBRA'!$A:$D,4)) | F24: =IF($A24=0,"",ROUND(D24*E24,2)) | H24: =IF($A24=0,"",ROUND(G24*F24,2))
B25: =IF($A25=0,"",VLOOKUP($A25,'BASE M-OBRA'!$A:$D,2)) | E25: =IF($A25=0,"",VLOOKUP($A25,'BASE M-OBRA'!$A:$D,4)) | F25: =IF($A25=0,"",ROUND(D25*E25,2)) | H25: =IF($A25=0,"",ROUND(G25*F25,2))
B26: SUBTOTAL N | H26: =ROUND(SUM(H18:H25),2) -> 41.74
B27: MATERIALES
B28: DESCRIPCION | E28: UNIDAD | F28: CANTIDAD A | G28: UNITARIO B | H28: COSTO C=A*B
A29: 11010 | B29: =IF($A29=0,"",VLOOKUP($A29,'BASE MATERIAL'!$A:$D,2)) -> TIRA | E29: =IF($A29=0,"",VLOOKUP($A29,'BASE MATERIAL'!$A:$D,3)) -> U | F29: 2.25 | G29: =IF($A29=0,"",VLOOKUP($A29,'BASE MATERIAL'!$A:$D,4)) -> 1.5 | H29: =IF($A29=0,"",ROUND(F29*G29,2)) -> 3.38
A30: 11007 | B30: =IF($A30=0,"",VLOOKUP($A30,'BASE MATERIAL'!$A:$D,2)) -> CLAVO 2 1/2" | E30: =IF($A30=0,"",VLOOKUP($A30,'BASE MATERIAL'!$A:$D,3)) -> KG | F30: 0.75 | G30: =IF($A30=0,"",VLOOKUP($A30,'BASE MATERIAL'!$A:$D,4)) -> 2.652 | H30: =IF($A30=0,"",ROUND(F30*G30,2)) -> 1.99
A31: 4001 | B31: =IF($A31=0,"",VLOOKUP($A31,'BASE MATERIAL'!$A:$D,2)) -> CEMENTO | E31: =IF($A31=0,"",VLOOKUP($A31,'BASE MATERIAL'!$A:$D,3)) -> SACO | F31: 6 | G31: =IF($A31=0,"",VLOOKUP($A31,'BASE MATERIAL'!$A:$D,4)) -> 7.09 | H31: =IF($A31=0,"",ROUND(F31*G31,2)) -> 42.54
A32: 5004 | B32: =IF($A32=0,"",VLOOKUP($A32,'BASE MATERIAL'!$A:$D,2)) -> ARENA | E32: =IF($A32=0,"",VLOOKUP($A32,'BASE MATERIAL'!$A:$D,3)) -> M3 | F32: =ROUND(F31*0.032*3,2) -> 0.58 | G32: =IF($A32=0,"",VLOOKUP($A32,'BASE MATERIAL'!$A:$D,4)) -> 12.27625 | H32: =IF($A32=0,"",ROUND(F32*G32,2)) -> 7.12
A33: 5002 | B33: =IF($A33=0,"",VLOOKUP($A33,'BASE MATERIAL'!$A:$D,2)) -> PIEDRA 3-4 | E33: =IF($A33=0,"",VLOOKUP($A33,'BASE MATERIAL'!$A:$D,3)) -> M3 | F33: =ROUND(F31*0.032*4,2) -> 0.77 | G33: =IF($A33=0,"",VLOOKUP($A33,'BASE MATERIAL'!$A:$D,4)) -> 13.75 | H33: =IF($A33=0,"",ROUND(F33*G33,2)) -> 10.59
A34: 5005 | B34: =IF($A34=0,"",VLOOKUP($A34,'BASE MATERIAL'!$A:$D,2)) -> AGUA | E34: =IF($A34=0,"",VLOOKUP($A34,'BASE MATERIAL'!$A:$D,3)) -> LT | F34: =26*F31 -> 156 | G34: =IF($A34=0,"",VLOOKUP($A34,'BASE MATERIAL'!$A:$D,4)) -> 0.002 | H34: =IF($A34=0,"",ROUND(F34*G34,2)) -> 0.31
B35: =IF($A35=0,"",VLOOKUP($A35,'BASE MATERIAL'!$A:$D,2)) | E35: =IF($A35=0,"",VLOOKUP($A35,'BASE MATERIAL'!$A:$D,3)) | G35: =IF($A35=0,"",VLOOKUP($A35,'BASE MATERIAL'!$A:$D,4)) | H35: =IF($A35=0,"",ROUND(F35*G35,2))
B36: =IF($A36=0,"",VLOOKUP($A36,'BASE MATERIAL'!$A:$D,2)) | E36: =IF($A36=0,"",VLOOKUP($A36,'BASE MATERIAL'!$A:$D,3)) | G36: =IF($A36=0,"",VLOOKUP($A36,'BASE MATERIAL'!$A:$D,4)) | H36: =IF($A36=0,"",ROUND(F36*G36,2))
B37: =IF($A37=0,"",VLOOKUP($A37,'BASE MATERIAL'!$A:$D,2)) | E37: =IF($A37=0,"",VLOOKUP($A37,'BASE MATERIAL'!$A:$D,3)) | G37: =IF($A37=0,"",VLOOKUP($A37,'BASE MATERIAL'!$A:$D,4)) | H37: =IF($A37=0,"",ROUND(F37*G37,2))
B38: =IF($A38=0,"",VLOOKUP($A38,'BASE MATERIAL'!$A:$D,2)) | E38: =IF($A38=0,"",VLOOKUP($A38,'BASE MATERIAL'!$A:$D,3)) | G38: =IF($A38=0,"",VLOOKUP($A38,'BASE MATERIAL'!$A:$D,4)) | H38: =IF($A38=0,"",ROUND(F38*G38,2))
B39: =IF($A39=0,"",VLOOKUP($A39,'BASE MATERIAL'!$A:$D,2)) | E39: =IF($A39=0,"",VLOOKUP($A39,'BASE MATERIAL'!$A:$D,3)) | G39: =IF($A39=0,"",VLOOKUP($A39,'BASE MATERIAL'!$A:$D,4)) | H39: =IF($A39=0,"",ROUND(F39*G39,2))
B40: =IF($A40=0,"",VLOOKUP($A40,'BASE MATERIAL'!$A:$D,2)) | E40: =IF($A40=0,"",VLOOKUP($A40,'BASE MATERIAL'!$A:$D,3)) | G40: =IF($A40=0,"",VLOOKUP($A40,'BASE MATERIAL'!$A:$D,4)) | H40: =IF($A40=0,"",ROUND(F40*G40,2))
B41: =IF($A41=0,"",VLOOKUP($A41,'BASE MATERIAL'!$A:$D,2)) | E41: =IF($A41=0,"",VLOOKUP($A41,'BASE MATERIAL'!$A:$D,3)) | G41: =IF($A41=0,"",VLOOKUP($A41,'BASE MATERIAL'!$A:$D,4)) | H41: =IF($A41=0,"",ROUND(F41*G41,2))
B42: =IF($A42=0,"",VLOOKUP($A42,'BASE MATERIAL'!$A:$D,2)) | E42: =IF($A42=0,"",VLOOKUP($A42,'BASE MATERIAL'!$A:$D,3)) | G42: =IF($A42=0,"",VLOOKUP($A42,'BASE MATERIAL'!$A:$D,4)) | H42: =IF($A42=0,"",ROUND(F42*G42,2))
B43: =IF($A43=0,"",VLOOKUP($A43,'BASE MATERIAL'!$A:$D,2)) | E43: =IF($A43=0,"",VLOOKUP($A43,'BASE MATERIAL'!$A:$D,3)) | G43: =IF($A43=0,"",VLOOKUP($A43,'BASE MATERIAL'!$A:$D,4)) | H43: =IF($A43=0,"",ROUND(F43*G43,2))
B44: =IF($A44=0,"",VLOOKUP($A44,'BASE MATERIAL'!$A:$D,2)) | E44: =IF($A44=0,"",VLOOKUP($A44,'BASE MATERIAL'!$A:$D,3)) | G44: =IF($A44=0,"",VLOOKUP($A44,'BASE MATERIAL'!$A:$D,4)) | H44: =IF($A44=0,"",ROUND(E44*F44,2))
B45: SUBTOTAL O | H45: =ROUND(SUM(H28:H44),2) -> 65.93
B46: TRANSPORTE
B47: DESCRIPCION | E47: UNIDAD | F47: CANTIDAD A | G47: TARIFA B | H47: COSTO C=A*B
A48: 19019 | B48: =IF($A48=0,"",VLOOKUP($A48,'BASE EQUIPO'!$A:$D,2)) -> TRANSPORTE DE MATERIAL | E48: =IF($A48=0,"",VLOOKUP($A48,'BASE EQUIPO'!$A:$D,3)) -> GLOBAL | F48: 1 | G48: =IF($A48=0,"",VLOOKUP($A48,'BASE EQUIPO'!$A:$D,4)*H45) -> 1.9779 | H48: =IF($A48=0,"",ROUND(F48*G48,2)) -> 1.98
B49: =IF($A49=0,"",VLOOKUP($A49,'BASE EQUIPO'!$A:$D,2)) | E49: =IF($A49=0,"",VLOOKUP($A49,'BASE EQUIPO'!$A:$D,3)) | G49: =IF($A49=0,"",VLOOKUP($A49,'BASE EQUIPO'!$A:$D,4)*H46) | H49: =IF($A49=0,"",ROUND(F49*G49,2))
B50: =IF($A50=0,"",VLOOKUP($A50,'BASE EQUIPO'!$A:$D,2)) | E50: =IF($A50=0,"",VLOOKUP($A50,'BASE EQUIPO'!$A:$D,3)) | G50: =IF($A50=0,"",VLOOKUP($A50,'BASE EQUIPO'!$A:$D,4)*H47) | H50: =IF($A50=0,"",ROUND(F50*G50,2))
B51: SUBTOTAL P | H51: =ROUND(SUM(H47:H50),2) -> 1.98
D52: TOTAL COSTO DIRECTO (M+N+O+P) | H52: =ROUND(SUM(H51,H45,H26,H16),2) -> 113.61
A53: 40002 | D53: INDIRECTOS Y UTILIDADES % | G53: =IF($A53=0,"",VLOOKUP($A53,'BASE MATERIAL'!$M:$P,4)) -> 0 | H53: =IF($A53=0,"",ROUND(G53*H52,2)) -> 0
A54: 40003 | D54: OTROS INDIRECTOS % | G54: =IF($A54=0,"",VLOOKUP($A54,'BASE MATERIAL'!$M:$P,4)) -> 0 | H54: =IF($A54=0,"",ROUND(G54*H52,2)) -> 0
D55: COSTO TOTAL DEL RUBRO | H55: =ROUND(SUM(H52:H54),2) -> 113.61
D56: VALOR OFERTADO | H56: =ROUND(H55,2) -> 113.61
B57: NOMBRE DEL PROPONENTE: | D57: =$D$1 -> ESPOL | H57: FORM. #3 | L57: =A61 -> 2 | M57: =C62 -> Muros de h. ciclopeo en estructuras | N57: =H61 -> m3 | O57: =H112 -> 141.35
B58: OBRA: | C58: ='1.1'!$C$2 -> 0 | G58: HOJA | I58: de
C59: ='1.1'!$C$3 -> 0
B60: ANALISIS DE PRECIOS UNITARIOS
A61: 2 | B61: RUBRO | C61: 1.5.2 | G61: UNIDAD: | H61: m3
B62: DETALLE | C62: Muros de h. ciclopeo en estructuras
B64: EQUIPOS
B65: DESCRIPCION | D65: CANTIDAD A | E65: TARIFA B | F65: COSTO HORA C= A*B | G65: RENDIMIENTO | H65: COSTO D=C*R
A66: 19015 | B66: =IF($A66=0,"",VLOOKUP($A66,'BASE EQUIPO'!$A:$D,2)) -> HERRAMIENTA MENOR | D66: 1 | E66: =IF($A66=0,"",VLOOKUP($A66,'BASE EQUIPO'!$A:$D,4)*H82)-0.06 -> 1.5576 | F66: =IF($A66=0,"",ROUND(D66*E66,2)) -> 1.56 | G66: 1 | H66: =IF($A66=0,"",ROUND(G66*F66,2)) -> 1.56
A67: 19003 | B67: =IF($A67=0,"",VLOOKUP($A67,'BASE EQUIPO'!$A:$D,2)) -> CONCRETERA | D67: 1 | E67: =IF($A67=0,"",VLOOKUP($A67,'BASE EQUIPO'!$A:$D,4)) -> 3.5 | F67: =IF($A67=0,"",ROUND(D67*E67,2)) -> 3.5 | G67: =+G76*0.25 -> 0.2 | H67: =IF($A67=0,"",ROUND(G67*F67,2)) -> 0.7
B68: =IF($A68=0,"",VLOOKUP($A68,'BASE EQUIPO'!$A:$D,2)) | E68: =IF($A68=0,"",VLOOKUP($A68,'BASE EQUIPO'!$A:$D,4)) | F68: =IF($A68=0,"",ROUND(D68*E68,2)) | H68: =IF($A68=0,"",ROUND(G68*F68,2))
B69: =IF($A69=0,"",VLOOKUP($A69,'BASE EQUIPO'!$A:$D,2)) | E69: =IF($A69=0,"",VLOOKUP($A69,'BASE EQUIPO'!$A:$D,4)) | F69: =IF($A69=0,"",ROUND(D69*E69,2)) | H69: =IF($A69=0,"",ROUND(G69*F69,2))
B70: =IF($A70=0,"",VLOOKUP($A70,'BASE EQUIPO'!$A:$D,2)) | E70: =IF($A70=0,"",VLOOKUP($A70,'BASE EQUIPO'!$A:$D,4)) | F70: =IF($A70=0,"",ROUND(D70*E70,2)) | H70: =IF($A70=0,"",ROUND(G70*F70,2))
B71: =IF($A71=0,"",VLOOKUP($A71,'BASE EQUIPO'!$A:$D,2)) | E71: =IF($A71=0,"",VLOOKUP($A71,'BASE EQUIPO'!$A:$D,4)) | F71: =IF($A71=0,"",ROUND(D71*E71,2)) | H71: =IF($A71=0,"",ROUND(G71*F71,2))
B72: SUBTOTAL M | H72: =ROUND(SUM(H65:H71),2) -> 2.26
B73: MANO DE OBRA
B74: DESCRIPCION (CATEG) | D74: CANTIDAD A | E74: JORNAL/HR B | F74: COSTO HORA C= A*B | G74: RENDIMIENTO | H74: COSTO D=C*R
A75: 20001 | B75: =IF($A75=0,"",VLOOKUP($A75,'BASE M-OBRA'!$A:$D,2)) -> MAESTRO | D75: 1 | E75: =IF($A75=0,"",VLOOKUP($A75,'BASE M-OBRA'!$A:$D,4)) -> 3.02 | F75: =IF($A75=0,"",ROUND(D75*E75,2)) -> 3.02 | G75: =IF($A75=0,"",ROUND(H75/F75,2)) -> 2.98 | H75: =IF($A75=0,"",ROUND(SUM(H76:H81)*'BASE M-OBRA'!$D$23,2)) -> 8.99
A76: 20002 | B76: =IF($A76=0,"",VLOOKUP($A76,'BASE M-OBRA'!$A:$D,2)) -> PEON | D76: 8 | E76: =IF($A76=0,"",VLOOKUP($A76,'BASE M-OBRA'!$A:$D,4)) -> 2.79 | F76: =IF($A76=0,"",ROUND(D76*E76,2)) -> 22.32 | G76: 0.8 | H76: =IF($A76=0,"",ROUND(G76*F76,2)) -> 17.86
A77: 20003 | B77: =IF($A77=0,"",VLOOKUP($A77,'BASE M-OBRA'!$A:$D,2)) -> ALBAÑIL | D77: 2 | E77: =IF($A77=0,"",VLOOKUP($A77,'BASE M-OBRA'!$A:$D,4)) -> 2.82 | F77: =IF($A77=0,"",ROUND(D77*E77,2)) -> 5.64 | G77: =+G76 -> 0.8 | H77: =IF($A77=0,"",ROUND(G77*F77,2)) -> 4.51
A78: 20004 | B78: =IF($A78=0,"",VLOOKUP($A78,'BASE M-OBRA'!$A:$D,2)) -> CARPINTERO | D78: 2 | E78: =IF($A78=0,"",VLOOKUP($A78,'BASE M-OBRA'!$A:$D,4)) -> 2.82 | F78: =IF($A78=0,"",ROUND(D78*E78,2)) -> 5.64 | G78: 4 | H78: =IF($A78=0,"",ROUND(G78*F78,2)) -> 22.56
B79: =IF($A79=0,"",VLOOKUP($A79,'BASE M-OBRA'!$A:$D,2)) | E79: =IF($A79=0,"",VLOOKUP($A79,'BASE M-OBRA'!$A:$D,4)) | F79: =IF($A79=0,"",ROUND(D79*E79,2)) | H79: =IF($A79=0,"",ROUND(G79*F79,2))
B80: =IF($A80=0,"",VLOOKUP($A80,'BASE M-OBRA'!$A:$D,2)) | E80: =IF($A80=0,"",VLOOKUP($A80,'BASE M-OBRA'!$A:$D,4)) | F80: =IF($A80=0,"",ROUND(D80*E80,2)) | H80: =IF($A80=0,"",ROUND(G80*F80,2))
B81: =IF($A81=0,"",VLOOKUP($A81,'BASE M-OBRA'!$A:$D,2)) | E81: =IF($A81=0,"",VLOOKUP($A81,'BASE M-OBRA'!$A:$D,4)) | F81: =IF($A81=0,"",ROUND(D81*E81,2)) | H81: =IF($A81=0,"",ROUND(G81*F81,2))
B82: SUBTOTAL N | H82: =ROUND(SUM(H74:H81),2) -> 53.92
B83: MATERIALES
B84: DESCRIPCION | E84: UNIDAD | F84: CANTIDAD A | G84: UNITARIO B | H84: COSTO C=A*B
A85: 11008 | B85: =IF($A85=0,"",VLOOKUP($A85,'BASE MATERIAL'!$A:$D,2)) -> TABLA | E85: =IF($A85=0,"",VLOOKUP($A85,'BASE MATERIAL'!$A:$D,3)) -> U | F85: =ROUND(10*5/(4*3),2) -> 4.17 | G85: =IF($A85=0,"",VLOOKUP($A85,'BASE MATERIAL'!$A:$D,4)) -> 3.5 | H85: =IF($A85=0,"",ROUND(F85*G85,2)) -> 14.6
A86: 11009 | B86: =IF($A86=0,"",VLOOKUP($A86,'BASE MATERIAL'!$A:$D,2)) -> CUARTON | E86: =IF($A86=0,"",VLOOKUP($A86,'BASE MATERIAL'!$A:$D,3)) -> U | F86: =ROUND(10*8/(4*3),2) -> 6.67 | G86: =IF($A86=0,"",VLOOKUP($A86,'BASE MATERIAL'!$A:$D,4)) -> 2.42 | H86: =IF($A86=0,"",ROUND(F86*G86,2)) -> 16.14
A87: 11010 | B87: =IF($A87=0,"",VLOOKUP($A87,'BASE MATERIAL'!$A:$D,2)) -> TIRA | E87: =IF($A87=0,"",VLOOKUP($A87,'BASE MATERIAL'!$A:$D,3)) -> U | F87: =ROUND(10*4/(4*3),2) -> 3.33 | G87: =IF($A87=0,"",VLOOKUP($A87,'BASE MATERIAL'!$A:$D,4)) -> 1.5 | H87: =IF($A87=0,"",ROUND(F87*G87,2)) -> 5
A88: 11007 | B88: =IF($A88=0,"",VLOOKUP($A88,'BASE MATERIAL'!$A:$D,2)) -> CLAVO 2 1/2" | E88: =IF($A88=0,"",VLOOKUP($A88,'BASE MATERIAL'!$A:$D,3)) -> KG | F88: =ROUND(10*56/(178*1.5),2) -> 2.1 | G88: =IF($A88=0,"",VLOOKUP($A88,'BASE MATERIAL'!$A:$D,4)) -> 2.652 | H88: =IF($A88=0,"",ROUND(F88*G88,2)) -> 5.57
A89: 4001 | B89: =IF($A89=0,"",VLOOKUP($A89,'BASE MATERIAL'!$A:$D,2)) -> CEMENTO | E89: =IF($A89=0,"",VLOOKUP($A89,'BASE MATERIAL'!$A:$D,3)) -> SACO | F89: =ROUND(6*0.6,2) -> 3.6 | G89: =IF($A89=0,"",VLOOKUP($A89,'BASE MATERIAL'!$A:$D,4)) -> 7.09 | H89: =IF($A89=0,"",ROUND(F89*G89,2)) -> 25.52
A90: 5004 | B90: =IF($A90=0,"",VLOOKUP($A90,'BASE MATERIAL'!$A:$D,2)) -> ARENA | E90: =IF($A90=0,"",VLOOKUP($A90,'BASE MATERIAL'!$A:$D,3)) -> M3 | F90: =ROUND(F89*0.4*0.4*0.2*3,2) -> 0.35 | G90: =IF($A90=0,"",VLOOKUP($A90,'BASE MATERIAL'!$A:$D,4)) -> 12.27625 | H90: =IF($A90=0,"",ROUND(F90*G90,2)) -> 4.3
A91: 5002 | B91: =IF($A91=0,"",VLOOKUP($A91,'BASE MATERIAL'!$A:$D,2)) -> PIEDRA 3-4 | E91: =IF($A91=0,"",VLOOKUP($A91,'BASE MATERIAL'!$A:$D,3)) -> M3 | F91: =ROUND(F89*0.4*0.4*0.2*4,2) -> 0.46 | G91: =IF($A91=0,"",VLOOKUP($A91,'BASE MATERIAL'!$A:$D,4)) -> 13.75 | H91: =IF($A91=0,"",ROUND(F91*G91,2)) -> 6.33
A92: 5005 | B92: =IF($A92=0,"",VLOOKUP($A92,'BASE MATERIAL'!$A:$D,2)) -> AGUA | E92: =IF($A92=0,"",VLOOKUP($A92,'BASE MATERIAL'!$A:$D,3)) -> LT | F92: =26*F89 -> 93.6 | G92: =IF($A92=0,"",VLOOKUP($A92,'BASE MATERIAL'!$A:$D,4)) -> 0.002 | H92: =IF($A92=0,"",ROUND(F92*G92,2)) -> 0.19
A93: 5003 | B93: =IF($A93=0,"",VLOOKUP($A93,'BASE MATERIAL'!$A:$D,2)) -> PIEDRA BASE | E93: =IF($A93=0,"",VLOOKUP($A93,'BASE MATERIAL'!$A:$D,3)) -> M3 | F93: 0.4 | G93: =IF($A93=0,"",VLOOKUP($A93,'BASE MATERIAL'!$A:$D,4)) -> 12.6 | H93: =IF($A93=0,"",ROUND(F93*G93,2)) -> 5.04
B94: =IF($A94=0,"",VLOOKUP($A94,'BASE MATERIAL'!$A:$D,2)) | E94: =IF($A94=0,"",VLOOKUP($A94,'BASE MATERIAL'!$A:$D,3)) | G94: =IF($A94=0,"",VLOOKUP($A94,'BASE MATERIAL'!$A:$D,4)) | H94: =IF($A94=0,"",ROUND(F94*G94,2))
B95: =IF($A95=0,"",VLOOKUP($A95,'BASE MATERIAL'!$A:$D,2)) | E95: =IF($A95=0,"",VLOOKUP($A95,'BASE MATERIAL'!$A:$D,3)) | G95: =IF($A95=0,"",VLOOKUP($A95,'BASE MATERIAL'!$A:$D,4)) | H95: =IF($A95=0,"",ROUND(F95*G95,2))
B96: =IF($A96=0,"",VLOOKUP($A96,'BASE MATERIAL'!$A:$D,2)) | E96: =IF($A96=0,"",VLOOKUP($A96,'BASE MATERIAL'!$A:$D,3)) | G96: =IF($A96=0,"",VLOOKUP($A96,'BASE MATERIAL'!$A:$D,4)) | H96: =IF($A96=0,"",ROUND(F96*G96,2))
B97: =IF($A97=0,"",VLOOKUP($A97,'BASE MATERIAL'!$A:$D,2)) | E97: =IF($A97=0,"",VLOOKUP($A97,'BASE MATERIAL'!$A:$D,3)) | G97: =IF($A97=0,"",VLOOKUP($A97,'BASE MATERIAL'!$A:$D,4)) | H97: =IF($A97=0,"",ROUND(F97*G97,2))
B98: =IF($A98=0,"",VLOOKUP($A98,'BASE MATERIAL'!$A:$D,2)) | E98: =IF($A98=0,"",VLOOKUP($A98,'BASE MATERIAL'!$A:$D,3)) | G98: =IF($A98=0,"",VLOOKUP($A98,'BASE MATERIAL'!$A:$D,4)) | H98: =IF($A98=0,"",ROUND(F98*G98,2))
B99: =IF($A99=0,"",VLOOKUP($A99,'BASE MATERIAL'!$A:$D,2)) | E99: =IF($A99=0,"",VLOOKUP($A99,'BASE MATERIAL'!$A:$D,3)) | G99: =IF($A99=0,"",VLOOKUP($A99,'BASE MATERIAL'!$A:$D,4)) | H99: =IF($A99=0,"",ROUND(F99*G99,2))
B100: =IF($A100=0,"",VLOOKUP($A100,'BASE MATERIAL'!$A:$D,2)) | E100: =IF($A100=0,"",VLOOKUP($A100,'BASE MATERIAL'!$A:$D,3)) | G100: =IF($A100=0,"",VLOOKUP($A100,'BASE MATERIAL'!$A:$D,4)) | H100: =IF($A100=0,"",ROUND(E100*F100,2))
B101: SUBTOTAL O | H101: =ROUND(SUM(H84:H100),2) -> 82.69
B102: TRANSPORTE
...

Sheet 1.6b
B1: NOMBRE DEL PROPONENTE: | D1: ='1.1'!$D$1 -> ESPOL | H1: FORM. #3 | L1: =#REF! -> #REF! | M1: =#REF! -> #REF! | N1: =#REF! -> #REF! | O1: =#REF! -> #REF!
B2: OBRA: | C2: ='1.1'!$C$2 -> 0 | G2: HOJA | I2: de
C3: ='1.1'!$C$3 -> 0
B4: ANALISIS DE PRECIOS UNITARIOS
A5: 2 | B5: RUBRO | C5: 1.6.1 | G5: UNIDAD: | H5: m3
B6: DETALLE | C6: Zapatas de cimentacion
B8: EQUIPOS
B9: DESCRIPCION | D9: CANTIDAD A | E9: TARIFA B | F9: COSTO HORA C= A*B | G9: RENDIMIENTO | H9: COSTO D=C*R
A10: 19015 | B10: =IF($A10=0,"",VLOOKUP($A10,'BASE EQUIPO'!$A:$D,2)) -> HERRAMIENTA MENOR | D10: 1 | E10: =IF($A10=0,"",VLOOKUP($A10,'BASE EQUIPO'!$A:$D,4)*H26) -> 2.6841 | F10: =IF($A10=0,"",ROUND(D10*E10,2)) -> 2.68 | G10: 1 | H10: =IF($A10=0,"",ROUND(G10*F10,2)) -> 2.68
A11: 19003 | B11: =IF($A11=0,"",VLOOKUP($A11,'BASE EQUIPO'!$A:$D,2)) -> CONCRETERA | D11: 1 | E11: =IF($A11=0,"",VLOOKUP($A11,'BASE EQUIPO'!$A:$D,4)) -> 3.5 | F11: =IF($A11=0,"",ROUND(D11*E11,2)) -> 3.5 | G11: =+G20*0.5 -> 0.35 | H11: =IF($A11=0,"",ROUND(G11*F11,2)) -> 1.23
A12: 19008 | B12: =IF($A12=0,"",VLOOKUP($A12,'BASE EQUIPO'!$A:$D,2)) -> VIBRADOR | D12: 1 | E12: =IF($A12=0,"",VLOOKUP($A12,'BASE EQUIPO'!$A:$D,4)) -> 2.5 | F12: =IF($A12=0,"",ROUND(D12*E12,2)) -> 2.5 | G12: =+G20*0.5 -> 0.35 | H12: =IF($A12=0,"",ROUND(G12*F12,2)) -> 0.88
B13: =IF($A13=0,"",VLOOKUP($A13,'BASE EQUIPO'!$A:$D,2)) | E13: =IF($A13=0,"",VLOOKUP($A13,'BASE EQUIPO'!$A:$D,4)) | F13: =IF($A13=0,"",ROUND(D13*E13,2)) | H13: =IF($A13=0,"",ROUND(G13*F13,2))
B14: =IF($A14=0,"",VLOOKUP($A14,'BASE EQUIPO'!$A:$D,2)) | E14: =IF($A14=0,"",VLOOKUP($A14,'BASE EQUIPO'!$A:$D,4)) | F14: =IF($A14=0,"",ROUND(D14*E14,2)) | H14: =IF($A14=0,"",ROUND(G14*F14,2))
B15: =IF($A15=0,"",VLOOKUP($A15,'BASE EQUIPO'!$A:$D,2)) | E15: =IF($A15=0,"",VLOOKUP($A15,'BASE EQUIPO'!$A:$D,4)) | F15: =IF($A15=0,"",ROUND(D15*E15,2)) | H15: =IF($A15=0,"",ROUND(G15*F15,2))
B16: SUBTOTAL M | H16: =ROUND(SUM(H9:H15),2) -> 4.79
B17: MANO DE OBRA
B18: DESCRIPCION (CATEG) | D18: CANTIDAD A | E18: JORNAL/HR B | F18: COSTO HORA C= A*B | G18: RENDIMIENTO | H18: COSTO D=C*R
A19: 20001 | B19: =IF($A19=0,"",VLOOKUP($A19,'BASE M-OBRA'!$A:$D,2)) -> MAESTRO | D19: 1 | E19: =IF($A19=0,"",VLOOKUP($A19,'BASE M-OBRA'!$A:$D,4)) -> 3.02 | F19: =IF($A19=0,"",ROUND(D19*E19,2)) -> 3.02 | G19: =IF($A19=0,"",ROUND(H19/F19,2)) -> 4.94 | H19: =IF($A19=0,"",ROUND(SUM(H20:H25)*'BASE M-OBRA'!$D$23,2)) -> 14.91
A20: 20002 | B20: =IF($A20=0,"",VLOOKUP($A20,'BASE M-OBRA'!$A:$D,2)) -> PEON | D20: 8 | E20: =IF($A20=0,"",VLOOKUP($A20,'BASE M-OBRA'!$A:$D,4)) -> 2.79 | F20: =IF($A20=0,"",ROUND(D20*E20,2)) -> 22.32 | G20: 0.7 | H20: =IF($A20=0,"",ROUND(G20*F20,2)) -> 15.62 | K20: =(8.94*0+22.37)/1.2 -> 18.641667 | L20: =H20+H21 -> 19.57
A21: 20003 | B21: =IF($A21=0,"",VLOOKUP($A21,'BASE M-OBRA'!$A:$D,2)) -> ALBAÑIL | D21: 2 | E21: =IF($A21=0,"",VLOOKUP($A21,'BASE M-OBRA'!$A:$D,4)) -> 2.82 | F21: =IF($A21=0,"",ROUND(D21*E21,2)) -> 5.64 | G21: =+G20 -> 0.7 | H21: =IF($A21=0,"",ROUND(G21*F21,2)) -> 3.95
A22: 20004 | B22: =IF($A22=0,"",VLOOKUP($A22,'BASE M-OBRA'!$A:$D,2)) -> CARPINTERO | D22: 2 | E22: =IF($A22=0,"",VLOOKUP($A22,'BASE M-OBRA'!$A:$D,4)) -> 2.82 | F22: =IF($A22=0,"",ROUND(D22*E22,2)) -> 5.64 | G22: 6 | H22: =IF($A22=0,"",ROUND(G22*F22,2)) -> 33.84 | K22: =(1.58*0+5.66)*K29/1.2 -> 33.016667
A23: 20005 | B23: =IF($A23=0,"",VLOOKUP($A23,'BASE M-OBRA'!$A:$D,2)) -> FIERRERO | D23: 2 | E23: =IF($A23=0,"",VLOOKUP($A23,'BASE M-OBRA'!$A:$D,4)) -> 2.82 | F23: =IF($A23=0,"",ROUND(D23*E23,2)) -> 5.64 | G23: 3.75 | H23: =IF($A23=0,"",ROUND(G23*F23,2)) -> 21.15 | K23: =+F38*0.3/1.2 -> 21.25
B24: =IF($A24=0,"",VLOOKUP($A24,'BASE M-OBRA'!$A:$D,2)) | E24: =IF($A24=0,"",VLOOKUP($A24,'BASE M-OBRA'!$A:$D,4)) | F24: =IF($A24=0,"",ROUND(D24*E24,2)) | H24: =IF($A24=0,"",ROUND(G24*F24,2))
B25: =IF($A25=0,"",VLOOKUP($A25,'BASE M-OBRA'!$A:$D,2)) | E25: =IF($A25=0,"",VLOOKUP($A25,'BASE M-OBRA'!$A:$D,4)) | F25: =IF($A25=0,"",ROUND(D25*E25,2)) | H25: =IF($A25=0,"",ROUND(G25*F25,2))
B26: SUBTOTAL N | H26: =ROUND(SUM(H18:H25),2) -> 89.47 | K26: =SUM(K19:K25) -> 72.908333
B27: MATERIALES
B28: DESCRIPCION | E28: UNIDAD | F28: CANTIDAD A | G28: UNITARIO B | H28: COSTO C=A*B
A29: 11008 | B29: =IF($A29=0,"",VLOOKUP($A29,'BASE MATERIAL'!$A:$D,2)) -> TABLA | E29: =IF($A29=0,"",VLOOKUP($A29,'BASE MATERIAL'!$A:$D,3)) -> U | F29: =ROUND(7*5/(4*3),2) -> 2.92 | G29: =IF($A29=0,"",VLOOKUP($A29,'BASE MATERIAL'!$A:$D,4)) -> 3.5 | H29: =IF($A29=0,"",ROUND(F29*G29,2)) -> 10.22 | K29: 7
A30: 11009 | B30: =IF($A30=0,"",VLOOKUP($A30,'BASE MATERIAL'!$A:$D,2)) -> CUARTON | E30: =IF($A30=0,"",VLOOKUP($A30,'BASE MATERIAL'!$A:$D,3)) -> U | F30: =ROUND(7*8/(4*3),2) -> 4.67 | G30: =IF($A30=0,"",VLOOKUP($A30,'BASE MATERIAL'!$A:$D,4)) -> 2.42 | H30: =IF($A30=0,"",ROUND(F30*G30,2)) -> 11.3
A31: 11007 | B31: =IF($A31=0,"",VLOOKUP($A31,'BASE MATERIAL'!$A:$D,2)) -> CLAVO 2 1/2" | E31: =IF($A31=0,"",VLOOKUP($A31,'BASE MATERIAL'!$A:$D,3)) -> KG | F31: =ROUND(7*56/(178*1.5),2) -> 1.47 | G31: =IF($A31=0,"",VLOOKUP($A31,'BASE MATERIAL'!$A:$D,4)) -> 2.652 | H31: =IF($A31=0,"",ROUND(F31*G31,2)) -> 3.9
A32: 11010 | B32: =IF($A32=0,"",VLOOKUP($A32,'BASE MATERIAL'!$A:$D,2)) -> TIRA | E32: =IF($A32=0,"",VLOOKUP($A32,'BASE MATERIAL'!$A:$D,3)) -> U | F32: =ROUND(7*4/(4*3),2) -> 2.33 | G32: =IF($A32=0,"",VLOOKUP($A32,'BASE MATERIAL'!$A:$D,4)) -> 1.5 | H32: =IF($A32=0,"",ROUND(F32*G32,2)) -> 3.5
A33: 4001 | B33: =IF($A33=0,"",VLOOKUP($A33,'BASE MATERIAL'!$A:$D,2)) -> CEMENTO | E33: =IF($A33=0,"",VLOOKUP($A33,'BASE MATERIAL'!$A:$D,3)) -> SACO | F33: =7*1.03 -> 7.21 | G33: =IF($A33=0,"",VLOOKUP($A33,'BASE MATERIAL'!$A:$D,4)) -> 7.09 | H33: =IF($A33=0,"",ROUND(F33*G33,2)) -> 51.12
A34: 5004 | B34: =IF($A34=0,"",VLOOKUP($A34,'BASE MATERIAL'!$A:$D,2)) -> ARENA | E34: =IF($A34=0,"",VLOOKUP($A34,'BASE MATERIAL'!$A:$D,3)) -> M3 | F34: =ROUND(F33*0.032*2,2) -> 0.46 | G34: =IF($A34=0,"",VLOOKUP($A34,'BASE MATERIAL'!$A:$D,4)) -> 12.27625 | H34: =IF($A34=0,"",ROUND(F34*G34,2)) -> 5.65
A35: 5002 | B35: =IF($A35=0,"",VLOOKUP($A35,'BASE MATERIAL'!$A:$D,2)) -> PIEDRA 3-4 | E35: =IF($A35=0,"",VLOOKUP($A35,'BASE MATERIAL'!$A:$D,3)) -> M3 | F35: =ROUND(F33*0.032*3,2) -> 0.69 | G35: =IF($A35=0,"",VLOOKUP($A35,'BASE MATERIAL'!$A:$D,4)) -> 13.75 | H35: =IF($A35=0,"",ROUND(F35*G35,2)) -> 9.49
A36: 5005 | B36: =IF($A36=0,"",VLOOKUP($A36,'BASE MATERIAL'!$A:$D,2)) -> AGUA | E36: =IF($A36=0,"",VLOOKUP($A36,'BASE MATERIAL'!$A:$D,3)) -> LT | F36: =26*F33 -> 187.46 | G36: =IF($A36=0,"",VLOOKUP($A36,'BASE MATERIAL'!$A:$D,4)) -> 0.002 | H36: =IF($A36=0,"",ROUND(F36*G36,2)) -> 0.37
B37: =IF($A37=0,"",VLOOKUP($A37,'BASE MATERIAL'!$A:$D,2)) | E37: =IF($A37=0,"",VLOOKUP($A37,'BASE MATERIAL'!$A:$D,3)) | G37: =IF($A37=0,"",VLOOKUP($A37,'BASE MATERIAL'!$A:$D,4)) | H37: =IF($A37=0,"",ROUND(F37*G37,2))
A38: 1001 | B38: =IF($A38=0,"",VLOOKUP($A38,'BASE MATERIAL'!$A:$D,2)) -> HIERRO | E38: =IF($A38=0,"",VLOOKUP($A38,'BASE MATERIAL'!$A:$D,3)) -> KG | F38: 85 | G38: =IF($A38=0,"",VLOOKUP($A38,'BASE MATERIAL'!$A:$D,4)) -> 1.17 | H38: =IF($A38=0,"",ROUND(F38*G38,2)) -> 99.45
A39: 11002 | B39: =IF($A39=0,"",VLOOKUP($A39,'BASE MATERIAL'!$A:$D,2)) -> ALAMBRE #18 RECOCIDO | E39: =IF($A39=0,"",VLOOKUP($A39,'BASE MATERIAL'!$A:$D,3)) -> KG | F39: =+F38*0.03 -> 2.55 | G39: =IF($A39=0,"",VLOOKUP($A39,'BASE MATERIAL'!$A:$D,4)) -> 1.87 | H39: =IF($A39=0,"",ROUND(F39*G39,2)) -> 4.77
B40: =IF($A40=0,"",VLOOKUP($A40,'BASE MATERIAL'!$A:$D,2)) | E40: =IF($A40=0,"",VLOOKUP($A40,'BASE MATERIAL'!$A:$D,3)) | G40: =IF($A40=0,"",VLOOKUP($A40,'BASE MATERIAL'!$A:$D,4)) | H40: =IF($A40=0,"",ROUND(F40*G40,2))
B41: =IF($A41=0,"",VLOOKUP($A41,'BASE MATERIAL'!$A:$D,2)) | E41: =IF($A41=0,"",VLOOKUP($A41,'BASE MATERIAL'!$A:$D,3)) | G41: =IF($A41=0,"",VLOOKUP($A41,'BASE MATERIAL'!$A:$D,4)) | H41: =IF($A41=0,"",ROUND(F41*G41,2))
B42: =IF($A42=0,"",VLOOKUP($A42,'BASE MATERIAL'!$A:$D,2)) | E42: =IF($A42=0,"",VLOOKUP($A42,'BASE MATERIAL'!$A:$D,3)) | G42: =IF($A42=0,"",VLOOKUP($A42,'BASE MATERIAL'!$A:$D,4)) | H42: =IF($A42=0,"",ROUND(F42*G42,2))
B43: =IF($A43=0,"",VLOOKUP($A43,'BASE MATERIAL'!$A:$D,2)) | E43: =IF($A43=0,"",VLOOKUP($A43,'BASE MATERIAL'!$A:$D,3)) | G43: =IF($A43=0,"",VLOOKUP($A43,'BASE MATERIAL'!$A:$D,4)) | H43: =IF($A43=0,"",ROUND(F43*G43,2))
B44: =IF($A44=0,"",VLOOKUP($A44,'BASE MATERIAL'!$A:$D,2)) | E44: =IF($A44=0,"",VLOOKUP($A44,'BASE MATERIAL'!$A:$D,3)) | G44: =IF($A44=0,"",VLOOKUP($A44,'BASE MATERIAL'!$A:$D,4)) | H44: =IF($A44=0,"",ROUND(E44*F44,2))
B45: SUBTOTAL O | H45: =ROUND(SUM(H28:H44),2) -> 199.77
B46: TRANSPORTE
B47: DESCRIPCION | E47: UNIDAD | F47: CANTIDAD A | G47: TARIFA B | H47: COSTO C=A*B
A48: 19019 | B48: =IF($A48=0,"",VLOOKUP($A48,'BASE EQUIPO'!$A:$D,2)) -> TRANSPORTE DE MATERIAL | E48: =IF($A48=0,"",VLOOKUP($A48,'BASE EQUIPO'!$A:$D,3)) -> GLOBAL | F48: 1 | G48: =IF($A48=0,"",VLOOKUP($A48,'BASE EQUIPO'!$A:$D,4)*H45)+0.23 -> 6.2231 | H48: =IF($A48=0,"",ROUND(F48*G48,2)) -> 6.22
B49: =IF($A49=0,"",VLOOKUP($A49,'BASE EQUIPO'!$A:$D,2)) | E49: =IF($A49=0,"",VLOOKUP($A49,'BASE EQUIPO'!$A:$D,3)) | G49: =IF($A49=0,"",VLOOKUP($A49,'BASE EQUIPO'!$A:$D,4)*H46) | H49: =IF($A49=0,"",ROUND(F49*G49,2))
B50: =IF($A50=0,"",VLOOKUP($A50,'BASE EQUIPO'!$A:$D,2)) | E50: =IF($A50=0,"",VLOOKUP($A50,'BASE EQUIPO'!$A:$D,3)) | G50: =IF($A50=0,"",VLOOKUP($A50,'BASE EQUIPO'!$A:$D,4)*H47) | H50: =IF($A50=0,"",ROUND(F50*G50,2))
B51: SUBTOTAL P | H51: =ROUND(SUM(H47:H50),2) -> 6.22
D52: TOTAL COSTO DIRECTO (M+N+O+P) | H52: =ROUND(SUM(H51,H45,H26,H16),2) -> 300.25
A53: 40002 | D53: INDIRECTOS Y UTILIDADES % | G53: =IF($A53=0,"",VLOOKUP($A53,'BASE MATERIAL'!$M:$P,4)) -> 0 | H53: =IF($A53=0,"",ROUND(G53*H52,2)) -> 0
A54: 40003 | D54: OTROS INDIRECTOS % | G54: =IF($A54=0,"",VLOOKUP($A54,'BASE MATERIAL'!$M:$P,4)) -> 0 | H54: =IF($A54=0,"",ROUND(G54*H52,2)) -> 0
D55: COSTO TOTAL DEL RUBRO | H55: =ROUND(SUM(H52:H54),2) -> 300.25
D56: VALOR OFERTADO | H56: =ROUND(H55,2) -> 300.25
B57: NOMBRE DEL PROPONENTE: | D57: =$D$1 -> ESPOL | H57: FORM. #3 | L57: =A61 -> 3 | M57: =C62 -> Zapata y Vigas de cimentacion | N57: =H61 -> m3 | O57: =H112 -> 375.27
B58: OBRA: | C58: ='1.1'!$C$2 -> 0 | G58: HOJA | I58: de
C59: ='1.1'!$C$3 -> 0
B60: ANALISIS DE PRECIOS UNITARIOS
A61: 3 | B61: RUBRO | C61: 1.6.2 | G61: UNIDAD: | H61: m3
B62: DETALLE | C62: Zapata y Vigas de cimentacion
B64: EQUIPOS
B65: DESCRIPCION | D65: CANTIDAD A | E65: TARIFA B | F65: COSTO HORA C= A*B | G65: RENDIMIENTO | H65: COSTO D=C*R
A66: 19015 | B66: =IF($A66=0,"",VLOOKUP($A66,'BASE EQUIPO'!$A:$D,2)) -> HERRAMIENTA MENOR | D66: 1 | E66: =IF($A66=0,"",VLOOKUP($A66,'BASE EQUIPO'!$A:$D,4)*H82) -> 2.9694 | F66: =IF($A66=0,"",ROUND(D66*E66,2)) -> 2.97 | G66: 1 | H66: =IF($A66=0,"",ROUND(G66*F66,2)) -> 2.97
A67: 19003 | B67: =IF($A67=0,"",VLOOKUP($A67,'BASE EQUIPO'!$A:$D,2)) -> CONCRETERA | D67: 1 | E67: =IF($A67=0,"",VLOOKUP($A67,'BASE EQUIPO'!$A:$D,4)) -> 3.5 | F67: =IF($A67=0,"",ROUND(D67*E67,2)) -> 3.5 | G67: =+G76*0.5 -> 0.325 | H67: =IF($A67=0,"",ROUND(G67*F67,2)) -> 1.14
A68: 19008 | B68: =IF($A68=0,"",VLOOKUP($A68,'BASE EQUIPO'!$A:$D,2)) -> VIBRADOR | D68: 1 | E68: =IF($A68=0,"",VLOOKUP($A68,'BASE EQUIPO'!$A:$D,4)) -> 2.5 | F68: =IF($A68=0,"",ROUND(D68*E68,2)) -> 2.5 | G68: =+G76*0.5 -> 0.325 | H68: =IF($A68=0,"",ROUND(G68*F68,2)) -> 0.81
B69: =IF($A69=0,"",VLOOKUP($A69,'BASE EQUIPO'!$A:$D,2)) | E69: =IF($A69=0,"",VLOOKUP($A69,'BASE EQUIPO'!$A:$D,4)) | F69: =IF($A69=0,"",ROUND(D69*E69,2)) | H69: =IF($A69=0,"",ROUND(G69*F69,2))
B70: =IF($A70=0,"",VLOOKUP($A70,'BASE EQUIPO'!$A:$D,2)) | E70: =IF($A70=0,"",VLOOKUP($A70,'BASE EQUIPO'!$A:$D,4)) | F70: =IF($A70=0,"",ROUND(D70*E70,2)) | H70: =IF($A70=0,"",ROUND(G70*F70,2))
B71: =IF($A71=0,"",VLOOKUP($A71,'BASE EQUIPO'!$A:$D,2)) | E71: =IF($A71=0,"",VLOOKUP($A71,'BASE EQUIPO'!$A:$D,4)) | F71: =IF($A71=0,"",ROUND(D71*E71,2)) | H71: =IF($A71=0,"",ROUND(G71*F71,2))
B72: SUBTOTAL M | H72: =ROUND(SUM(H65:H71),2) -> 4.92
B73: MANO DE OBRA
B74: DESCRIPCION (CATEG) | D74: CANTIDAD A | E74: JORNAL/HR B | F74: COSTO HORA C= A*B | G74: RENDIMIENTO | H74: COSTO D=C*R
A75: 20001 | B75: =IF($A75=0,"",VLOOKUP($A75,'BASE M-OBRA'!$A:$D,2)) -> MAESTRO | D75: 1 | E75: =IF($A75=0,"",VLOOKUP($A75,'BASE M-OBRA'!$A:$D,4)) -> 3.02 | F75: =IF($A75=0,"",ROUND(D75*E75,2)) -> 3.02 | G75: =IF($A75=0,"",ROUND(H75/F75,2)) -> 5.46 | H75: =IF($A75=0,"",ROUND(SUM(H76:H81)*'BASE M-OBRA'!$D$23,2)) -> 16.5
A76: 20002 | B76: =IF($A76=0,"",VLOOKUP($A76,'BASE M-OBRA'!$A:$D,2)) -> PEON | D76: 8 | E76: =IF($A76=0,"",VLOOKUP($A76,'BASE M-OBRA'!$A:$D,4)) -> 2.79 | F76: =IF($A76=0,"",ROUND(D76*E76,2)) -> 22.32 | G76: 0.65 | H76: =IF($A76=0,"",ROUND(G76*F76,2)) -> 14.51 | K76: =(8.94*0+22.37)/1.2 -> 18.641667 | L76: =H76+H77 -> 18.18
A77: 20003 | B77: =IF($A77=0,"",VLOOKUP($A77,'BASE M-OBRA'!$A:$D,2)) -> ALBAÑIL | D77: 2 | E77: =IF($A77=0,"",VLOOKUP($A77,'BASE M-OBRA'!$A:$D,4)) -> 2.82 | F77: =IF($A77=0,"",ROUND(D77*E77,2)) -> 5.64 | G77: =+G76 -> 0.65 | H77: =IF($A77=0,"",ROUND(G77*F77,2)) -> 3.67
A78: 20004 | B78: =IF($A78=0,"",VLOOKUP($A78,'BASE M-OBRA'!$A:$D,2)) -> CARPINTERO | D78: 2 | E78: =IF($A78=0,"",VLOOKUP($A78,'BASE M-OBRA'!$A:$D,4)) -> 2.82 | F78: =IF($A78=0,"",ROUND(D78*E78,2)) -> 5.64 | G78: 6 | H78: =IF($A78=0,"",ROUND(G78*F78,2)) -> 33.84 | K78: =(1.58*0+5.66)*K85/1.2 -> 47.166667
A79: 20005 | B79: =IF($A79=0,"",VLOOKUP($A79,'BASE M-OBRA'!$A:$D,2)) -> FIERRERO | D79: 2 | E79: =IF($A79=0,"",VLOOKUP($A79,'BASE M-OBRA'!$A:$D,4)) -> 2.82 | F79: =IF($A79=0,"",ROUND(D79*E79,2)) -> 5.64 | G79: 5.4 | H79: =IF($A79=0,"",ROUND(G79*F79,2)) -> 30.46 | K79: =+F94*0.3/1.2 -> 29.75
B80: =IF($A80=0,"",VLOOKUP($A80,'BASE M-OBRA'!$A:$D,2)) | E80: =IF($A80=0,"",VLOOKUP($A80,'BASE M-OBRA'!$A:$D,4)) | F80: =IF($A80=0,"",ROUND(D80*E80,2)) | H80: =IF($A80=0,"",ROUND(G80*F80,2))
B81: =IF($A81=0,"",VLOOKUP($A81,'BASE M-OBRA'!$A:$D,2)) | E81: =IF($A81=0,"",VLOOKUP($A81,'BASE M-OBRA'!$A:$D,4)) | F81: =IF($A81=0,"",ROUND(D81*E81,2)) | H81: =IF($A81=0,"",ROUND(G81*F81,2))
B82: SUBTOTAL N | H82: =ROUND(SUM(H74:H81),2) -> 98.98
B83: MATERIALES
B84: DESCRIPCION | E84: UNIDAD | F84: CANTIDAD A | G84: UNITARIO B | H84: COSTO C=A*B
A85: 11008 | B85: =IF($A85=0,"",VLOOKUP($A85,'BASE MATERIAL'!$A:$D,2)) -> TABLA | E85: =IF($A85=0,"",VLOOKUP($A85,'BASE MATERIAL'!$A:$D,3)) -> U | F85: =ROUND(10*5/(4*3),2) -> 4.17 | G85: =IF($A85=0,"",VLOOKUP($A85,'BASE MATERIAL'!$A:$D,4)) -> 3.5 | H85: =IF($A85=0,"",ROUND(F85*G85,2)) -> 14.6 | K85: =0.25*2/(0.25*0.2) -> 10
A86: 11009 | B86: =IF($A86=0,"",VLOOKUP($A86,'BASE MATERIAL'!$A:$D,2)) -> CUARTON | E86: =IF($A86=0,"",VLOOKUP($A86,'BASE MATERIAL'!$A:$D,3)) -> U | F86: =ROUND(10*8/(4*3),2) -> 6.67 | G86: =IF($A86=0,"",VLOOKUP($A86,'BASE MATERIAL'!$A:$D,4)) -> 2.42 | H86: =IF($A86=0,"",ROUND(F86*G86,2)) -> 16.14
A87: 11007 | B87: =IF($A87=0,"",VLOOKUP($A87,'BASE MATERIAL'!$A:$D,2)) -> CLAVO 2 1/2" | E87: =IF($A87=0,"",VLOOKUP($A87,'BASE MATERIAL'!$A:$D,3)) -> KG | F87: =ROUND(10*56/(178*1.5),2) -> 2.1 | G87: =IF($A87=0,"",VLOOKUP($A87,'BASE MATERIAL'!$A:$D,4)) -> 2.652 | H87: =IF($A87=0,"",ROUND(F87*G87,2)) -> 5.57
A88: 11010 | B88: =IF($A88=0,"",VLOOKUP($A88,'BASE MATERIAL'!$A:$D,2)) -> TIRA | E88: =IF($A88=0,"",VLOOKUP($A88,'BASE MATERIAL'!$A:$D,3)) -> U | F88: =ROUND(10*4/(4*3),2) -> 3.33 | G88: =IF($A88=0,"",VLOOKUP($A88,'BASE MATERIAL'!$A:$D,4)) -> 1.5 | H88: =IF($A88=0,"",ROUND(F88*G88,2)) -> 5
A89: 4001 | B89: =IF($A89=0,"",VLOOKUP($A89,'BASE MATERIAL'!$A:$D,2)) -> CEMENTO | E89: =IF($A89=0,"",VLOOKUP($A89,'BASE MATERIAL'!$A:$D,3)) -> SACO | F89: =8*1.03 -> 8.24 | G89: =IF($A89=0,"",VLOOKUP($A89,'BASE MATERIAL'!$A:$D,4)) -> 7.09 | H89: =IF($A89=0,"",ROUND(F89*G89,2)) -> 58.42
A90: 5004 | B90: =IF($A90=0,"",VLOOKUP($A90,'BASE MATERIAL'!$A:$D,2)) -> ARENA | E90: =IF($A90=0,"",VLOOKUP($A90,'BASE MATERIAL'!$A:$D,3)) -> M3 | F90: =ROUND(F89*0.032*2,2) -> 0.53 | G90: =IF($A90=0,"",VLOOKUP($A90,'BASE MATERIAL'!$A:$D,4)) -> 12.27625 | H90: =IF($A90=0,"",ROUND(F90*G90,2)) -> 6.51
A91: 5002 | B91: =IF($A91=0,"",VLOOKUP($A91,'BASE MATERIAL'!$A:$D,2)) -> PIEDRA 3-4 | E91: =IF($A91=0,"",VLOOKUP($A91,'BASE MATERIAL'!$A:$D,3)) -> M3 | F91: =ROUND(F89*0.032*3,2) -> 0.79 | G91: =IF($A91=0,"",VLOOKUP($A91,'BASE MATERIAL'!$A:$D,4)) -> 13.75 | H91: =IF($A91=0,"",ROUND(F91*G91,2)) -> 10.86
A92: 5005 | B92: =IF($A92=0,"",VLOOKUP($A92,'BASE MATERIAL'!$A:$D,2)) -> AGUA | E92: =IF($A92=0,"",VLOOKUP($A92,'BASE MATERIAL'!$A:$D,3)) -> LT | F92: =26*F89 -> 214.24 | G92: =IF($A92=0,"",VLOOKUP($A92,'BASE MATERIAL'!$A:$D,4)) -> 0.002 | H92: =IF($A92=0,"",ROUND(F92*G92,2)) -> 0.43
B93: =IF($A93=0,"",VLOOKUP($A93,'BASE MATERIAL'!$A:$D,2)) | E93: =IF($A93=0,"",VLOOKUP($A93,'BASE MATERIAL'!$A:$D,3)) | G93: =IF($A93=0,"",VLOOKUP($A93,'BASE MATERIAL'!$A:$D,4)) | H93: =IF($A93=0,"",ROUND(F93*G93,2))
A94: 1001 | B94: =IF($A94=0,"",VLOOKUP($A94,'BASE MATERIAL'!$A:$D,2)) -> HIERRO | E94: =IF($A94=0,"",VLOOKUP($A94,'BASE MATERIAL'!$A:$D,3)) -> KG | F94: 119 | G94: =IF($A94=0,"",VLOOKUP($A94,'BASE MATERIAL'!$A:$D,4)) -> 1.17 | H94: =IF($A94=0,"",ROUND(F94*G94,2)) -> 139.23
A95: 11002 | B95: =IF($A95=0,"",VLOOKUP($A95,'BASE MATERIAL'!$A:$D,2)) -> ALAMBRE #18 RECOCIDO | E95: =IF($A95=0,"",VLOOKUP($A95,'BASE MATERIAL'!$A:$D,3)) -> KG | F95: =+F94*0.03 -> 3.57 | G95: =IF($A95=0,"",VLOOKUP($A95,'BASE MATERIAL'!$A:$D,4)) -> 1.87 | H95: =IF($A95=0,"",ROUND(F95*G95,2)) -> 6.68
B96: =IF($A96=0,"",VLOOKUP($A96,'BASE MATERIAL'!$A:$D,2)) | E96: =IF($A96=0,"",VLOOKUP($A96,'BASE MATERIAL'!$A:$D,3)) | G96: =IF($A96=0,"",VLOOKUP($A96,'BASE MATERIAL'!$A:$D,4)) | H96: =IF($A96=0,"",ROUND(F96*G96,2))
B97: =IF($A97=0,"",VLOOKUP($A97,'BASE MATERIAL'!$A:$D,2)) | E97: =IF($A97=0,"",VLOOKUP($A97,'BASE MATERIAL'!$A:$D,3)) | G97: =IF($A97=0,"",VLOOKUP($A97,'BASE MATERIAL'!$A:$D,4)) | H97: =IF($A97=0,"",ROUND(F97*G97,2))
B98: =IF($A98=0,"",VLOOKUP($A98,'BASE MATERIAL'!$A:$D,2)) | E98: =IF($A98=0,"",VLOOKUP($A98,'BASE MATERIAL'!$A:$D,3)) | G98: =IF($A98=0,"",VLOOKUP($A98,'BASE MATERIAL'!$A:$D,4)) | H98: =IF($A98=0,"",ROUND(F98*G98,2))
B99: =IF($A99=0,"",VLOOKUP($A99,'BASE MATERIAL'!$A:$D,2)) | E99: =IF($A99=0,"",VLOOKUP($A99,'BASE MATERIAL'!$A:$D,3)) | G99: =IF($A99=0,"",VLOOKUP($A99,'BASE MATERIAL'!$A:$D,4)) | H99: =IF($A99=0,"",ROUND(F99*G99,2))
B100: =IF($A100=0,"",VLOOKUP($A100,'BASE MATERIAL'!$A:$D,2)) | E100: =IF($A100=0,"",VLOOKUP($A100,'BASE MATERIAL'!$A:$D,3)) | G100: =IF($A100=0,"",VLOOKUP($A100,'BASE MATERIAL'!$A:$D,4)) | H100: =IF($A100=0,"",ROUND(E100*F100,2))
B101: SUBTOTAL O | H101: =ROUND(SUM(H84:H100),2) -> 263.44
B102: TRANSPORTE
...

Sheet 1.6
B1: NOMBRE DEL PROPONENTE: | D1: ='1.1'!$D$1 -> ESPOL | H1: FORM. #3 | L1: =#REF! -> #REF! | M1: =#REF! -> #REF! | N1: =#REF! -> #REF! | O1: =#REF! -> #REF!
B2: OBRA: | C2: ='1.1'!$C$2 -> 0 | G2: HOJA | I2: de
C3: ='1.1'!$C$3 -> 0
B4: ANALISIS DE PRECIOS UNITARIOS
A5: 2 | B5: RUBRO | C5: 1.6.1 | G5: UNIDAD: | H5: m3
B6: DETALLE | C6: Zapatas de cimentacion
B8: EQUIPOS
B9: DESCRIPCION | D9: CANTIDAD A | E9: TARIFA B | F9: COSTO HORA C= A*B | G9: RENDIMIENTO | H9: COSTO D=C*R
A10: 19015 | B10: =IF($A10=0,"",VLOOKUP($A10,'BASE EQUIPO'!$A:$D,2)) -> HERRAMIENTA MENOR | D10: 1 | E10: =IF($A10=0,"",VLOOKUP($A10,'BASE EQUIPO'!$A:$D,4)*H26) -> 1.8186 | F10: =IF($A10=0,"",ROUND(D10*E10,2)) -> 1.82 | G10: 1 | H10: =IF($A10=0,"",ROUND(G10*F10,2)) -> 1.82
B11: =IF($A11=0,"",VLOOKUP($A11,'BASE EQUIPO'!$A:$D,2)) | D11: 1 | E11: =IF($A11=0,"",VLOOKUP($A11,'BASE EQUIPO'!$A:$D,4)) | F11: =IF($A11=0,"",ROUND(D11*E11,2)) | H11: =IF($A11=0,"",ROUND(G11*F11,2))
A12: 19008 | B12: =IF($A12=0,"",VLOOKUP($A12,'BASE EQUIPO'!$A:$D,2)) -> VIBRADOR | D12: 1 | E12: =IF($A12=0,"",VLOOKUP($A12,'BASE EQUIPO'!$A:$D,4)) -> 2.5 | F12: =IF($A12=0,"",ROUND(D12*E12,2)) -> 2.5 | G12: =+G20 -> 1 | H12: =IF($A12=0,"",ROUND(G12*F12,2)) -> 2.5
B13: =IF($A13=0,"",VLOOKUP($A13,'BASE EQUIPO'!$A:$D,2)) | E13: =IF($A13=0,"",VLOOKUP($A13,'BASE EQUIPO'!$A:$D,4)) | F13: =IF($A13=0,"",ROUND(D13*E13,2)) | H13: =IF($A13=0,"",ROUND(G13*F13,2))
B14: =IF($A14=0,"",VLOOKUP($A14,'BASE EQUIPO'!$A:$D,2)) | E14: =IF($A14=0,"",VLOOKUP($A14,'BASE EQUIPO'!$A:$D,4)) | F14: =IF($A14=0,"",ROUND(D14*E14,2)) | H14: =IF($A14=0,"",ROUND(G14*F14,2))
B15: =IF($A15=0,"",VLOOKUP($A15,'BASE EQUIPO'!$A:$D,2)) | E15: =IF($A15=0,"",VLOOKUP($A15,'BASE EQUIPO'!$A:$D,4)) | F15: =IF($A15=0,"",ROUND(D15*E15,2)) | H15: =IF($A15=0,"",ROUND(G15*F15,2))
B16: SUBTOTAL M | H16: =ROUND(SUM(H9:H15),2) -> 4.32
B17: MANO DE OBRA
B18: DESCRIPCION (CATEG) | D18: CANTIDAD A | E18: JORNAL/HR B | F18: COSTO HORA C= A*B | G18: RENDIMIENTO | H18: COSTO D=C*R
A19: 20001 | B19: =IF($A19=0,"",VLOOKUP($A19,'BASE M-OBRA'!$A:$D,2)) -> MAESTRO | D19: 1 | E19: =IF($A19=0,"",VLOOKUP($A19,'BASE M-OBRA'!$A:$D,4)) -> 3.02 | F19: =IF($A19=0,"",ROUND(D19*E19,2)) -> 3.02 | G19: =IF($A19=0,"",ROUND(H19/F19,2)) -> 3.34 | H19: =IF($A19=0,"",ROUND(SUM(H20:H25)*'BASE M-OBRA'!$D$23,2)) -> 10.1
A20: 20002 | B20: =IF($A20=0,"",VLOOKUP($A20,'BASE M-OBRA'!$A:$D,2)) -> PEON | D20: 8 | E20: =IF($A20=0,"",VLOOKUP($A20,'BASE M-OBRA'!$A:$D,4)) -> 2.79 | F20: =IF($A20=0,"",ROUND(D20*E20,2)) -> 22.32 | G20: 1 | H20: =IF($A20=0,"",ROUND(G20*F20,2)) -> 22.32 | K20: 20
A21: 20003 | B21: =IF($A21=0,"",VLOOKUP($A21,'BASE M-OBRA'!$A:$D,2)) -> ALBAÑIL | D21: 2 | E21: =IF($A21=0,"",VLOOKUP($A21,'BASE M-OBRA'!$A:$D,4)) -> 2.82 | F21: =IF($A21=0,"",ROUND(D21*E21,2)) -> 5.64 | G21: =+G20 -> 1 | H21: =IF($A21=0,"",ROUND(G21*F21,2)) -> 5.64
A22: 20004 | B22: =IF($A22=0,"",VLOOKUP($A22,'BASE M-OBRA'!$A:$D,2)) -> CARPINTERO | D22: 2 | E22: =IF($A22=0,"",VLOOKUP($A22,'BASE M-OBRA'!$A:$D,4)) -> 2.82 | F22: =IF($A22=0,"",ROUND(D22*E22,2)) -> 5.64 | G22: 4 | H22: =IF($A22=0,"",ROUND(G22*F22,2)) -> 22.56 | K22: =10*2.9 -> 29
B23: =IF($A23=0,"",VLOOKUP($A23,'BASE M-OBRA'!$A:$D,2)) | E23: =IF($A23=0,"",VLOOKUP($A23,'BASE M-OBRA'!$A:$D,4)) | F23: =IF($A23=0,"",ROUND(D23*E23,2)) | H23: =IF($A23=0,"",ROUND(G23*F23,2))
B24: =IF($A24=0,"",VLOOKUP($A24,'BASE M-OBRA'!$A:$D,2)) | E24: =IF($A24=0,"",VLOOKUP($A24,'BASE M-OBRA'!$A:$D,4)) | F24: =IF($A24=0,"",ROUND(D24*E24,2)) | H24: =IF($A24=0,"",ROUND(G24*F24,2))
B25: =IF($A25=0,"",VLOOKUP($A25,'BASE M-OBRA'!$A:$D,2)) | E25: =IF($A25=0,"",VLOOKUP($A25,'BASE M-OBRA'!$A:$D,4)) | F25: =IF($A25=0,"",ROUND(D25*E25,2)) | H25: =IF($A25=0,"",ROUND(G25*F25,2))
B26: SUBTOTAL N | H26: =ROUND(SUM(H18:H25),2) -> 60.62
B27: MATERIALES
B28: DESCRIPCION | E28: UNIDAD | F28: CANTIDAD A | G28: UNITARIO B | H28: COSTO C=A*B
A29: 11008 | B29: =IF($A29=0,"",VLOOKUP($A29,'BASE MATERIAL'!$A:$D,2)) -> TABLA | E29: =IF($A29=0,"",VLOOKUP($A29,'BASE MATERIAL'!$A:$D,3)) -> U | F29: =ROUND(10*5/(4*3),2) -> 4.17 | G29: =IF($A29=0,"",VLOOKUP($A29,'BASE MATERIAL'!$A:$D,4)) -> 3.5 | H29: =IF($A29=0,"",ROUND(F29*G29,2)) -> 14.6
A30: 11009 | B30: =IF($A30=0,"",VLOOKUP($A30,'BASE MATERIAL'!$A:$D,2)) -> CUARTON | E30: =IF($A30=0,"",VLOOKUP($A30,'BASE MATERIAL'!$A:$D,3)) -> U | F30: =ROUND(10*8/(4*3),2) -> 6.67 | G30: =IF($A30=0,"",VLOOKUP($A30,'BASE MATERIAL'!$A:$D,4)) -> 2.42 | H30: =IF($A30=0,"",ROUND(F30*G30,2)) -> 16.14
A31: 11007 | B31: =IF($A31=0,"",VLOOKUP($A31,'BASE MATERIAL'!$A:$D,2)) -> CLAVO 2 1/2" | E31: =IF($A31=0,"",VLOOKUP($A31,'BASE MATERIAL'!$A:$D,3)) -> KG | F31: =ROUND(10*56/(178*1.5),2) -> 2.1 | G31: =IF($A31=0,"",VLOOKUP($A31,'BASE MATERIAL'!$A:$D,4)) -> 2.652 | H31: =IF($A31=0,"",ROUND(F31*G31,2)) -> 5.57
A32: 11010 | B32: =IF($A32=0,"",VLOOKUP($A32,'BASE MATERIAL'!$A:$D,2)) -> TIRA | E32: =IF($A32=0,"",VLOOKUP($A32,'BASE MATERIAL'!$A:$D,3)) -> U | F32: =ROUND(10*4/(4*3),2) -> 3.33 | G32: =IF($A32=0,"",VLOOKUP($A32,'BASE MATERIAL'!$A:$D,4)) -> 1.5 | H32: =IF($A32=0,"",ROUND(F32*G32,2)) -> 5
B33: =IF($A33=0,"",VLOOKUP($A33,'BASE MATERIAL'!$A:$D,2)) | E33: =IF($A33=0,"",VLOOKUP($A33,'BASE MATERIAL'!$A:$D,3)) | G33: =IF($A33=0,"",VLOOKUP($A33,'BASE MATERIAL'!$A:$D,4)) | H33: =IF($A33=0,"",ROUND(F33*G33,2))
A34: 11009 | B34: Hormg. Premezclado bombeable f'c=280 Kg/cm2 | E34: m3 | F34: 1.02 | G34: =106.7*1.12 -> 119.504 | H34: =IF($A34=0,"",ROUND(F34*G34,2)) -> 121.89
B35: =IF($A35=0,"",VLOOKUP($A35,'BASE MATERIAL'!$A:$D,2)) | E35: =IF($A35=0,"",VLOOKUP($A35,'BASE MATERIAL'!$A:$D,3)) | G35: =IF($A35=0,"",VLOOKUP($A35,'BASE MATERIAL'!$A:$D,4)) | H35: =IF($A35=0,"",ROUND(F35*G35,2))
B36: =IF($A36=0,"",VLOOKUP($A36,'BASE MATERIAL'!$A:$D,2)) | E36: =IF($A36=0,"",VLOOKUP($A36,'BASE MATERIAL'!$A:$D,3)) | G36: =IF($A36=0,"",VLOOKUP($A36,'BASE MATERIAL'!$A:$D,4)) | H36: =IF($A36=0,"",ROUND(F36*G36,2))
B37: =IF($A37=0,"",VLOOKUP($A37,'BASE MATERIAL'!$A:$D,2)) | E37: =IF($A37=0,"",VLOOKUP($A37,'BASE MATERIAL'!$A:$D,3)) | G37: =IF($A37=0,"",VLOOKUP($A37,'BASE MATERIAL'!$A:$D,4)) | H37: =IF($A37=0,"",ROUND(F37*G37,2))
B38: =IF($A38=0,"",VLOOKUP($A38,'BASE MATERIAL'!$A:$D,2)) | E38: =IF($A38=0,"",VLOOKUP($A38,'BASE MATERIAL'!$A:$D,3)) | G38: =IF($A38=0,"",VLOOKUP($A38,'BASE MATERIAL'!$A:$D,4)) | H38: =IF($A38=0,"",ROUND(F38*G38,2))
B39: =IF($A39=0,"",VLOOKUP($A39,'BASE MATERIAL'!$A:$D,2)) | E39: =IF($A39=0,"",VLOOKUP($A39,'BASE MATERIAL'!$A:$D,3)) | G39: =IF($A39=0,"",VLOOKUP($A39,'BASE MATERIAL'!$A:$D,4)) | H39: =IF($A39=0,"",ROUND(F39*G39,2))
B40: =IF($A40=0,"",VLOOKUP($A40,'BASE MATERIAL'!$A:$D,2)) | E40: =IF($A40=0,"",VLOOKUP($A40,'BASE MATERIAL'!$A:$D,3)) | G40: =IF($A40=0,"",VLOOKUP($A40,'BASE MATERIAL'!$A:$D,4)) | H40: =IF($A40=0,"",ROUND(F40*G40,2))
B41: =IF($A41=0,"",VLOOKUP($A41,'BASE MATERIAL'!$A:$D,2)) | E41: =IF($A41=0,"",VLOOKUP($A41,'BASE MATERIAL'!$A:$D,3)) | G41: =IF($A41=0,"",VLOOKUP($A41,'BASE MATERIAL'!$A:$D,4)) | H41: =IF($A41=0,"",ROUND(F41*G41,2))
B42: =IF($A42=0,"",VLOOKUP($A42,'BASE MATERIAL'!$A:$D,2)) | E42: =IF($A42=0,"",VLOOKUP($A42,'BASE MATERIAL'!$A:$D,3)) | G42: =IF($A42=0,"",VLOOKUP($A42,'BASE MATERIAL'!$A:$D,4)) | H42: =IF($A42=0,"",ROUND(F42*G42,2))
B43: =IF($A43=0,"",VLOOKUP($A43,'BASE MATERIAL'!$A:$D,2)) | E43: =IF($A43=0,"",VLOOKUP($A43,'BASE MATERIAL'!$A:$D,3)) | G43: =IF($A43=0,"",VLOOKUP($A43,'BASE MATERIAL'!$A:$D,4)) | H43: =IF($A43=0,"",ROUND(F43*G43,2))
B44: =IF($A44=0,"",VLOOKUP($A44,'BASE MATERIAL'!$A:$D,2)) | E44: =IF($A44=0,"",VLOOKUP($A44,'BASE MATERIAL'!$A:$D,3)) | G44: =IF($A44=0,"",VLOOKUP($A44,'BASE MATERIAL'!$A:$D,4)) | H44: =IF($A44=0,"",ROUND(E44*F44,2))
B45: SUBTOTAL O | H45: =ROUND(SUM(H28:H44),2) -> 163.2
B46: TRANSPORTE
B47: DESCRIPCION | E47: UNIDAD | F47: CANTIDAD A | G47: TARIFA B | H47: COSTO C=A*B
A48: 19019 | B48: =IF($A48=0,"",VLOOKUP($A48,'BASE EQUIPO'!$A:$D,2)) -> TRANSPORTE DE MATERIAL | E48: =IF($A48=0,"",VLOOKUP($A48,'BASE EQUIPO'!$A:$D,3)) -> GLOBAL | F48: 1 | G48: =IF($A48=0,"",VLOOKUP($A48,'BASE EQUIPO'!$A:$D,4)*H45)+0.23 -> 5.126 | H48: =IF($A48=0,"",ROUND(F48*G48,2)) -> 5.13
B49: =IF($A49=0,"",VLOOKUP($A49,'BASE EQUIPO'!$A:$D,2)) | E49: =IF($A49=0,"",VLOOKUP($A49,'BASE EQUIPO'!$A:$D,3)) | G49: =IF($A49=0,"",VLOOKUP($A49,'BASE EQUIPO'!$A:$D,4)*H46) | H49: =IF($A49=0,"",ROUND(F49*G49,2))
B50: =IF($A50=0,"",VLOOKUP($A50,'BASE EQUIPO'!$A:$D,2)) | E50: =IF($A50=0,"",VLOOKUP($A50,'BASE EQUIPO'!$A:$D,3)) | G50: =IF($A50=0,"",VLOOKUP($A50,'BASE EQUIPO'!$A:$D,4)*H47) | H50: =IF($A50=0,"",ROUND(F50*G50,2))
B51: SUBTOTAL P | H51: =ROUND(SUM(H47:H50),2) -> 5.13
D52: TOTAL COSTO DIRECTO (M+N+O+P) | H52: =ROUND(SUM(H51,H45,H26,H16),2) -> 233.27
A53: 40002 | D53: INDIRECTOS Y UTILIDADES % | G53: =IF($A53=0,"",VLOOKUP($A53,'BASE MATERIAL'!$M:$P,4)) -> 0 | H53: =IF($A53=0,"",ROUND(G53*H52,2)) -> 0
A54: 40003 | D54: OTROS INDIRECTOS % | G54: =IF($A54=0,"",VLOOKUP($A54,'BASE MATERIAL'!$M:$P,4)) -> 0 | H54: =IF($A54=0,"",ROUND(G54*H52,2)) -> 0
D55: COSTO TOTAL DEL RUBRO | H55: =ROUND(SUM(H52:H54),2) -> 233.27
D56: VALOR OFERTADO | H56: =ROUND(H55,2) -> 233.27
B57: NOMBRE DEL PROPONENTE: | D57: =$D$1 -> ESPOL | H57: FORM. #3 | L57: =A61 -> 3 | M57: =C62 -> Vigas de cimentacion | N57: =H61 -> m3 | O57: =H112 -> 273.12
B58: OBRA: | C58: ='1.1'!$C$2 -> 0 | G58: HOJA | I58: de
C59: ='1.1'!$C$3 -> 0
B60: ANALISIS DE PRECIOS UNITARIOS
A61: 3 | B61: RUBRO | C61: 1.6.2 | G61: UNIDAD: | H61: m3
B62: DETALLE | C62: Vigas de cimentacion
B64: EQUIPOS
B65: DESCRIPCION | D65: CANTIDAD A | E65: TARIFA B | F65: COSTO HORA C= A*B | G65: RENDIMIENTO | H65: COSTO D=C*R
A66: 19015 | B66: =IF($A66=0,"",VLOOKUP($A66,'BASE EQUIPO'!$A:$D,2)) -> HERRAMIENTA MENOR | D66: 1 | E66: =IF($A66=0,"",VLOOKUP($A66,'BASE EQUIPO'!$A:$D,4)*H82) -> 2.7312 | F66: =IF($A66=0,"",ROUND(D66*E66,2)) -> 2.73 | G66: 1 | H66: =IF($A66=0,"",ROUND(G66*F66,2)) -> 2.73
B67: =IF($A67=0,"",VLOOKUP($A67,'BASE EQUIPO'!$A:$D,2)) | E67: =IF($A67=0,"",VLOOKUP($A67,'BASE EQUIPO'!$A:$D,4)) | F67: =IF($A67=0,"",ROUND(D67*E67,2)) | H67: =IF($A67=0,"",ROUND(G67*F67,2))
A68: 19008 | B68: =IF($A68=0,"",VLOOKUP($A68,'BASE EQUIPO'!$A:$D,2)) -> VIBRADOR | D68: 1 | E68: =IF($A68=0,"",VLOOKUP($A68,'BASE EQUIPO'!$A:$D,4)) -> 2.5 | F68: =IF($A68=0,"",ROUND(D68*E68,2)) -> 2.5 | G68: =+G76 -> 1.1 | H68: =IF($A68=0,"",ROUND(G68*F68,2)) -> 2.75
B69: =IF($A69=0,"",VLOOKUP($A69,'BASE EQUIPO'!$A:$D,2)) | E69: =IF($A69=0,"",VLOOKUP($A69,'BASE EQUIPO'!$A:$D,4)) | F69: =IF($A69=0,"",ROUND(D69*E69,2)) | H69: =IF($A69=0,"",ROUND(G69*F69,2))
B70: =IF($A70=0,"",VLOOKUP($A70,'BASE EQUIPO'!$A:$D,2)) | E70: =IF($A70=0,"",VLOOKUP($A70,'BASE EQUIPO'!$A:$D,4)) | F70: =IF($A70=0,"",ROUND(D70*E70,2)) | H70: =IF($A70=0,"",ROUND(G70*F70,2))
B71: =IF($A71=0,"",VLOOKUP($A71,'BASE EQUIPO'!$A:$D,2)) | E71: =IF($A71=0,"",VLOOKUP($A71,'BASE EQUIPO'!$A:$D,4)) | F71: =IF($A71=0,"",ROUND(D71*E71,2)) | H71: =IF($A71=0,"",ROUND(G71*F71,2))
B72: SUBTOTAL M | H72: =ROUND(SUM(H65:H71),2) -> 5.48
B73: MANO DE OBRA
B74: DESCRIPCION (CATEG) | D74: CANTIDAD A | E74: JORNAL/HR B | F74: COSTO HORA C= A*B | G74: RENDIMIENTO | H74: COSTO D=C*R
A75: 20001 | B75: =IF($A75=0,"",VLOOKUP($A75,'BASE M-OBRA'!$A:$D,2)) -> MAESTRO | D75: 1 | E75: =IF($A75=0,"",VLOOKUP($A75,'BASE M-OBRA'!$A:$D,4)) -> 3.02 | F75: =IF($A75=0,"",ROUND(D75*E75,2)) -> 3.02 | G75: =IF($A75=0,"",ROUND(H75/F75,2)) -> 5.02 | H75: =IF($A75=0,"",ROUND(SUM(H76:H81)*'BASE M-OBRA'!$D$23,2)) -> 15.17
A76: 20002 | B76: =IF($A76=0,"",VLOOKUP($A76,'BASE M-OBRA'!$A:$D,2)) -> PEON | D76: 8 | E76: =IF($A76=0,"",VLOOKUP($A76,'BASE M-OBRA'!$A:$D,4)) -> 2.79 | F76: =IF($A76=0,"",ROUND(D76*E76,2)) -> 22.32 | G76: 1.1 | H76: =IF($A76=0,"",ROUND(G76*F76,2)) -> 24.55
A77: 20003 | B77: =IF($A77=0,"",VLOOKUP($A77,'BASE M-OBRA'!$A:$D,2)) -> ALBAÑIL | D77: 2 | E77: =IF($A77=0,"",VLOOKUP($A77,'BASE M-OBRA'!$A:$D,4)) -> 2.82 | F77: =IF($A77=0,"",ROUND(D77*E77,2)) -> 5.64 | G77: =+G76 -> 1.1 | H77: =IF($A77=0,"",ROUND(G77*F77,2)) -> 6.2
A78: 20004 | B78: =IF($A78=0,"",VLOOKUP($A78,'BASE M-OBRA'!$A:$D,2)) -> CARPINTERO | D78: 2 | E78: =IF($A78=0,"",VLOOKUP($A78,'BASE M-OBRA'!$A:$D,4)) -> 2.82 | F78: =IF($A78=0,"",ROUND(D78*E78,2)) -> 5.64 | G78: 8 | H78: =IF($A78=0,"",ROUND(G78*F78,2)) -> 45.12 | K78: =12*2.9 -> 34.8
B79: =IF($A79=0,"",VLOOKUP($A79,'BASE M-OBRA'!$A:$D,2)) | E79: =IF($A79=0,"",VLOOKUP($A79,'BASE M-OBRA'!$A:$D,4)) | F79: =IF($A79=0,"",ROUND(D79*E79,2)) | H79: =IF($A79=0,"",ROUND(G79*F79,2)) | K79: =F88*0.2 -> 0.8
B80: =IF($A80=0,"",VLOOKUP($A80,'BASE M-OBRA'!$A:$D,2)) | E80: =IF($A80=0,"",VLOOKUP($A80,'BASE M-OBRA'!$A:$D,4)) | F80: =IF($A80=0,"",ROUND(D80*E80,2)) | H80: =IF($A80=0,"",ROUND(G80*F80,2))
B81: =IF($A81=0,"",VLOOKUP($A81,'BASE M-OBRA'!$A:$D,2)) | E81: =IF($A81=0,"",VLOOKUP($A81,'BASE M-OBRA'!$A:$D,4)) | F81: =IF($A81=0,"",ROUND(D81*E81,2)) | H81: =IF($A81=0,"",ROUND(G81*F81,2))
B82: SUBTOTAL N | H82: =ROUND(SUM(H74:H81),2) -> 91.04
B83: MATERIALES
B84: DESCRIPCION | E84: UNIDAD | F84: CANTIDAD A | G84: UNITARIO B | H84: COSTO C=A*B
A85: 11008 | B85: =IF($A85=0,"",VLOOKUP($A85,'BASE MATERIAL'!$A:$D,2)) -> TABLA | E85: =IF($A85=0,"",VLOOKUP($A85,'BASE MATERIAL'!$A:$D,3)) -> U | F85: =ROUND(12*5/(4*3),2) -> 5 | G85: =IF($A85=0,"",VLOOKUP($A85,'BASE MATERIAL'!$A:$D,4)) -> 3.5 | H85: =IF($A85=0,"",ROUND(F85*G85,2)) -> 17.5
A86: 11009 | B86: =IF($A86=0,"",VLOOKUP($A86,'BASE MATERIAL'!$A:$D,2)) -> CUARTON | E86: =IF($A86=0,"",VLOOKUP($A86,'BASE MATERIAL'!$A:$D,3)) -> U | F86: =ROUND(12*8/(4*3),2) -> 8 | G86: =IF($A86=0,"",VLOOKUP($A86,'BASE MATERIAL'!$A:$D,4)) -> 2.42 | H86: =IF($A86=0,"",ROUND(F86*G86,2)) -> 19.36
A87: 11007 | B87: =IF($A87=0,"",VLOOKUP($A87,'BASE MATERIAL'!$A:$D,2)) -> CLAVO 2 1/2" | E87: =IF($A87=0,"",VLOOKUP($A87,'BASE MATERIAL'!$A:$D,3)) -> KG | F87: =ROUND(12*56/(178*1.5),2) -> 2.52 | G87: =IF($A87=0,"",VLOOKUP($A87,'BASE MATERIAL'!$A:$D,4)) -> 2.652 | H87: =IF($A87=0,"",ROUND(F87*G87,2)) -> 6.68
A88: 11010 | B88: =IF($A88=0,"",VLOOKUP($A88,'BASE MATERIAL'!$A:$D,2)) -> TIRA | E88: =IF($A88=0,"",VLOOKUP($A88,'BASE MATERIAL'!$A:$D,3)) -> U | F88: =ROUND(12*4/(4*3),2) -> 4 | G88: =IF($A88=0,"",VLOOKUP($A88,'BASE MATERIAL'!$A:$D,4)) -> 1.5 | H88: =IF($A88=0,"",ROUND(F88*G88,2)) -> 6
B89: =IF($A89=0,"",VLOOKUP($A89,'BASE MATERIAL'!$A:$D,2)) | E89: =IF($A89=0,"",VLOOKUP($A89,'BASE MATERIAL'!$A:$D,3)) | G89: =IF($A89=0,"",VLOOKUP($A89,'BASE MATERIAL'!$A:$D,4)) | H89: =IF($A89=0,"",ROUND(F89*G89,2))
A90: 11009 | B90: Hormg. Premezclado bombeable f'c=280 Kg/cm2 | E90: m3 | F90: 1.02 | G90: =106.7*1.12 -> 119.504 | H90: =IF($A90=0,"",ROUND(F90*G90,2)) -> 121.89
B91: =IF($A91=0,"",VLOOKUP($A91,'BASE MATERIAL'!$A:$D,2)) | E91: =IF($A91=0,"",VLOOKUP($A91,'BASE MATERIAL'!$A:$D,3)) | G91: =IF($A91=0,"",VLOOKUP($A91,'BASE MATERIAL'!$A:$D,4)) | H91: =IF($A91=0,"",ROUND(F91*G91,2))
B92: =IF($A92=0,"",VLOOKUP($A92,'BASE MATERIAL'!$A:$D,2)) | E92: =IF($A92=0,"",VLOOKUP($A92,'BASE MATERIAL'!$A:$D,3)) | G92: =IF($A92=0,"",VLOOKUP($A92,'BASE MATERIAL'!$A:$D,4)) | H92: =IF($A92=0,"",ROUND(F92*G92,2))
B93: =IF($A93=0,"",VLOOKUP($A93,'BASE MATERIAL'!$A:$D,2)) | E93: =IF($A93=0,"",VLOOKUP($A93,'BASE MATERIAL'!$A:$D,3)) | G93: =IF($A93=0,"",VLOOKUP($A93,'BASE MATERIAL'!$A:$D,4)) | H93: =IF($A93=0,"",ROUND(F93*G93,2))
B94: =IF($A94=0,"",VLOOKUP($A94,'BASE MATERIAL'!$A:$D,2)) | E94: =IF($A94=0,"",VLOOKUP($A94,'BASE MATERIAL'!$A:$D,3)) | G94: =IF($A94=0,"",VLOOKUP($A94,'BASE MATERIAL'!$A:$D,4)) | H94: =IF($A94=0,"",ROUND(F94*G94,2))
B95: =IF($A95=0,"",VLOOKUP($A95,'BASE MATERIAL'!$A:$D,2)) | E95: =IF($A95=0,"",VLOOKUP($A95,'BASE MATERIAL'!$A:$D,3)) | G95: =IF($A95=0,"",VLOOKUP($A95,'BASE MATERIAL'!$A:$D,4)) | H95: =IF($A95=0,"",ROUND(F95*G95,2))
B96: =IF($A96=0,"",VLOOKUP($A96,'BASE MATERIAL'!$A:$D,2)) | E96: =IF($A96=0,"",VLOOKUP($A96,'BASE MATERIAL'!$A:$D,3)) | G96: =IF($A96=0,"",VLOOKUP($A96,'BASE MATERIAL'!$A:$D,4)) | H96: =IF($A96=0,"",ROUND(F96*G96,2))
B97: =IF($A97=0,"",VLOOKUP($A97,'BASE MATERIAL'!$A:$D,2)) | E97: =IF($A97=0,"",VLOOKUP($A97,'BASE MATERIAL'!$A:$D,3)) | G97: =IF($A97=0,"",VLOOKUP($A97,'BASE MATERIAL'!$A:$D,4)) | H97: =IF($A97=0,"",ROUND(F97*G97,2))
B98: =IF($A98=0,"",VLOOKUP($A98,'BASE MATERIAL'!$A:$D,2)) | E98: =IF($A98=0,"",VLOOKUP($A98,'BASE MATERIAL'!$A:$D,3)) | G98: =IF($A98=0,"",VLOOKUP($A98,'BASE MATERIAL'!$A:$D,4)) | H98: =IF($A98=0,"",ROUND(F98*G98,2))
B99: =IF($A99=0,"",VLOOKUP($A99,'BASE MATERIAL'!$A:$D,2)) | E99: =IF($A99=0,"",VLOOKUP($A99,'BASE MATERIAL'!$A:$D,3)) | G99: =IF($A99=0,"",VLOOKUP($A99,'BASE MATERIAL'!$A:$D,4)) | H99: =IF($A99=0,"",ROUND(F99*G99,2))
B100: =IF($A100=0,"",VLOOKUP($A100,'BASE MATERIAL'!$A:$D,2)) | E100: =IF($A100=0,"",VLOOKUP($A100,'BASE MATERIAL'!$A:$D,3)) | G100: =IF($A100=0,"",VLOOKUP($A100,'BASE MATERIAL'!$A:$D,4)) | H100: =IF($A100=0,"",ROUND(E100*F100,2))
B101: SUBTOTAL O | H101: =ROUND(SUM(H84:H100),2) -> 171.43
B102: TRANSPORTE
...

Sheet 1.7
B1: NOMBRE DEL PROPONENTE: | D1: ='1.1'!$D$1 -> ESPOL | H1: FORM. #3 | L1: =A5 -> 2 | M1: =C6 -> Estructuras metalicas para cubiertas | N1: =H5 -> KG | O1: =H56 -> 2.69
B2: OBRA: | C2: ='1.1'!$C$2 -> 0 | G2: HOJA | I2: de
C3: ='1.1'!$C$3 -> 0
B4: ANALISIS DE PRECIOS UNITARIOS
A5: 2 | B5: RUBRO | C5: 1.7.1 | G5: UNIDAD: | H5: KG
B6: DETALLE | C6: Estructuras metalicas para cubiertas
B8: EQUIPOS
B9: DESCRIPCION | D9: CANTIDAD A | E9: TARIFA B | F9: COSTO HORA C= A*B | G9: RENDIMIENTO | H9: COSTO D=C*R
A10: 19015 | B10: =IF($A10=0,"",VLOOKUP($A10,'BASE EQUIPO'!$A:$D,2)) -> HERRAMIENTA MENOR | D10: 1 | E10: =IF($A10=0,"",VLOOKUP($A10,'BASE EQUIPO'!$A:$D,4)*H26) -> 0.0213 | F10: =IF($A10=0,"",ROUND(D10*E10,2)) -> 0.02 | G10: 1 | H10: =IF($A10=0,"",ROUND(G10*F10,2)) -> 0.02
A11: 19011 | B11: =IF($A11=0,"",VLOOKUP($A11,'BASE EQUIPO'!$A:$D,2)) -> SOLDADORA | D11: 1 | E11: =IF($A11=0,"",VLOOKUP($A11,'BASE EQUIPO'!$A:$D,4)) -> 2.5 | F11: =IF($A11=0,"",ROUND(D11*E11,2)) -> 2.5 | G11: =ROUND(G20*0.25,3) -> 0.013 | H11: =IF($A11=0,"",ROUND(G11*F11,2)) -> 0.03
A12: 19023 | B12: =IF($A12=0,"",VLOOKUP($A12,'BASE EQUIPO'!$A:$D,2)) -> COMPRESOR Y PISTOLA | D12: 1 | E12: =IF($A12=0,"",VLOOKUP($A12,'BASE EQUIPO'!$A:$D,4)) -> 1.875 | F12: =IF($A12=0,"",ROUND(D12*E12,2)) -> 1.88 | G12: =+G11 -> 0.013 | H12: =IF($A12=0,"",ROUND(G12*F12,2)) -> 0.02
B13: =IF($A13=0,"",VLOOKUP($A13,'BASE EQUIPO'!$A:$D,2)) | E13: =IF($A13=0,"",VLOOKUP($A13,'BASE EQUIPO'!$A:$D,4)) | F13: =IF($A13=0,"",ROUND(D13*E13,2)) | H13: =IF($A13=0,"",ROUND(G13*F13,2))
B14: =IF($A14=0,"",VLOOKUP($A14,'BASE EQUIPO'!$A:$D,2)) | E14: =IF($A14=0,"",VLOOKUP($A14,'BASE EQUIPO'!$A:$D,4)) | F14: =IF($A14=0,"",ROUND(D14*E14,2)) | H14: =IF($A14=0,"",ROUND(G14*F14,2))
B15: =IF($A15=0,"",VLOOKUP($A15,'BASE EQUIPO'!$A:$D,2)) | E15: =IF($A15=0,"",VLOOKUP($A15,'BASE EQUIPO'!$A:$D,4)) | F15: =IF($A15=0,"",ROUND(D15*E15,2)) | H15: =IF($A15=0,"",ROUND(G15*F15,2))
B16: SUBTOTAL M | H16: =ROUND(SUM(H9:H15),2) -> 0.07
B17: MANO DE OBRA
B18: DESCRIPCION (CATEG) | D18: CANTIDAD A | E18: JORNAL/HR B | F18: COSTO HORA C= A*B | G18: RENDIMIENTO | H18: COSTO D=C*R
B19: =IF($A19=0,"",VLOOKUP($A19,'BASE M-OBRA'!$A:$D,2)) | E19: =IF($A19=0,"",VLOOKUP($A19,'BASE M-OBRA'!$A:$D,4)) | F19: =IF($A19=0,"",ROUND(D19*E19,2)) | G19: =IF($A19=0,"",ROUND(H19/F19,2)) | H19: =IF($A19=0,"",ROUND(SUM(H20:H25)*'BASE M-OBRA'!$D$23,2))
A20: 20006 | B20: =IF($A20=0,"",VLOOKUP($A20,'BASE M-OBRA'!$A:$D,2)) -> MAESTRO SOLDADOR | D20: 1 | E20: =IF($A20=0,"",VLOOKUP($A20,'BASE M-OBRA'!$A:$D,4)) -> 3.02 | F20: =IF($A20=0,"",ROUND(D20*E20,2)) -> 3.02 | G20: 0.051 | H20: =IF($A20=0,"",ROUND(G20*F20,2)) -> 0.15
A21: 20011 | B21: =IF($A21=0,"",VLOOKUP($A21,'BASE M-OBRA'!$A:$D,2)) -> AYUDANTE ESPECIALISTA | D21: 2 | E21: =IF($A21=0,"",VLOOKUP($A21,'BASE M-OBRA'!$A:$D,4)) -> 2.79 | F21: =IF($A21=0,"",ROUND(D21*E21,2)) -> 5.58 | G21: =+G20 -> 0.051 | H21: =IF($A21=0,"",ROUND(G21*F21,2)) -> 0.28
A22: 20018 | B22: =IF($A22=0,"",VLOOKUP($A22,'BASE M-OBRA'!$A:$D,2)) -> PINTOR | D22: 1 | E22: =IF($A22=0,"",VLOOKUP($A22,'BASE M-OBRA'!$A:$D,4)) -> 2.82 | F22: =IF($A22=0,"",ROUND(D22*E22,2)) -> 2.82 | G22: =+G21 -> 0.051 | H22: =IF($A22=0,"",ROUND(G22*F22,2)) -> 0.14 | K22: =3*2.9 -> 8.7
A23: 20011 | B23: =IF($A23=0,"",VLOOKUP($A23,'BASE M-OBRA'!$A:$D,2)) -> AYUDANTE ESPECIALISTA | D23: 1 | E23: =IF($A23=0,"",VLOOKUP($A23,'BASE M-OBRA'!$A:$D,4)) -> 2.79 | F23: =IF($A23=0,"",ROUND(D23*E23,2)) -> 2.79 | G23: =+G22 -> 0.051 | H23: =IF($A23=0,"",ROUND(G23*F23,2)) -> 0.14 | K23: =70*0.15 -> 10.5
B24: =IF($A24=0,"",VLOOKUP($A24,'BASE M-OBRA'!$A:$D,2)) | E24: =IF($A24=0,"",VLOOKUP($A24,'BASE M-OBRA'!$A:$D,4)) | F24: =IF($A24=0,"",ROUND(D24*E24,2)) | H24: =IF($A24=0,"",ROUND(G24*F24,2))
B25: =IF($A25=0,"",VLOOKUP($A25,'BASE M-OBRA'!$A:$D,2)) | E25: =IF($A25=0,"",VLOOKUP($A25,'BASE M-OBRA'!$A:$D,4)) | F25: =IF($A25=0,"",ROUND(D25*E25,2)) | H25: =IF($A25=0,"",ROUND(G25*F25,2))
B26: SUBTOTAL N | H26: =ROUND(SUM(H18:H25),2) -> 0.71
B27: MATERIALES
B28: DESCRIPCION | E28: UNIDAD | F28: CANTIDAD A | G28: UNITARIO B | H28: COSTO C=A*B
A29: 14002 | B29: =IF($A29=0,"",VLOOKUP($A29,'BASE MATERIAL'!$A:$D,2)) -> SOLDADURA aga 60/11 | E29: =IF($A29=0,"",VLOOKUP($A29,'BASE MATERIAL'!$A:$D,3)) -> KG | F29: =ROUND(0.044*F30,4) -> 0.0462 | G29: =IF($A29=0,"",VLOOKUP($A29,'BASE MATERIAL'!$A:$D,4)) -> 3.65 | H29: =IF($A29=0,"",ROUND(F29*G29,2)) -> 0.17
A30: 1004 | B30: =IF($A30=0,"",VLOOKUP($A30,'BASE MATERIAL'!$A:$D,2)) -> PERFILERIA METALICA | E30: =IF($A30=0,"",VLOOKUP($A30,'BASE MATERIAL'!$A:$D,3)) -> KG | F30: 1.05 | G30: =IF($A30=0,"",VLOOKUP($A30,'BASE MATERIAL'!$A:$D,4)) -> 1.27 | H30: =IF($A30=0,"",ROUND(F30*G30,2)) -> 1.33
A31: 13001 | B31: =IF($A31=0,"",VLOOKUP($A31,'BASE MATERIAL'!$A:$D,2)) -> PINTURA PARA PROTECCION METALICA | E31: =IF($A31=0,"",VLOOKUP($A31,'BASE MATERIAL'!$A:$D,3)) -> GL | F31: =ROUND(0.0056*F30,4) -> 0.0059 | G31: =IF($A31=0,"",VLOOKUP($A31,'BASE MATERIAL'!$A:$D,4)) -> 37.72 | H31: =IF($A31=0,"",ROUND(F31*G31,2)) -> 0.22
A32: 13002 | B32: =IF($A32=0,"",VLOOKUP($A32,'BASE MATERIAL'!$A:$D,2)) -> PINTURA PARA ACABADO METALICO | E32: =IF($A32=0,"",VLOOKUP($A32,'BASE MATERIAL'!$A:$D,3)) -> GL | F32: =ROUND(0.0028*F30,4) -> 0.0029 | G32: =IF($A32=0,"",VLOOKUP($A32,'BASE MATERIAL'!$A:$D,4)) -> 38.52 | H32: =IF($A32=0,"",ROUND(F32*G32,2)) -> 0.11
A33: 13011 | B33: =IF($A33=0,"",VLOOKUP($A33,'BASE MATERIAL'!$A:$D,2)) -> DESOXIDANTE | E33: =IF($A33=0,"",VLOOKUP($A33,'BASE MATERIAL'!$A:$D,3)) -> GL | F33: =ROUND(0.2*(F31+F32),4) -> 0.0018 | G33: =IF($A33=0,"",VLOOKUP($A33,'BASE MATERIAL'!$A:$D,4)) -> 12 | H33: =IF($A33=0,"",ROUND(F33*G33,2)) -> 0.02
B34: =IF($A34=0,"",VLOOKUP($A34,'BASE MATERIAL'!$A:$D,2)) | E34: =IF($A34=0,"",VLOOKUP($A34,'BASE MATERIAL'!$A:$D,3)) | G34: =IF($A34=0,"",VLOOKUP($A34,'BASE MATERIAL'!$A:$D,4)) | H34: =IF($A34=0,"",ROUND(F34*G34,2))
B35: =IF($A35=0,"",VLOOKUP($A35,'BASE MATERIAL'!$A:$D,2)) | E35: =IF($A35=0,"",VLOOKUP($A35,'BASE MATERIAL'!$A:$D,3)) | G35: =IF($A35=0,"",VLOOKUP($A35,'BASE MATERIAL'!$A:$D,4)) | H35: =IF($A35=0,"",ROUND(F35*G35,2))
B36: =IF($A36=0,"",VLOOKUP($A36,'BASE MATERIAL'!$A:$D,2)) | E36: =IF($A36=0,"",VLOOKUP($A36,'BASE MATERIAL'!$A:$D,3)) | G36: =IF($A36=0,"",VLOOKUP($A36,'BASE MATERIAL'!$A:$D,4)) | H36: =IF($A36=0,"",ROUND(F36*G36,2))
B37: =IF($A37=0,"",VLOOKUP($A37,'BASE MATERIAL'!$A:$D,2)) | E37: =IF($A37=0,"",VLOOKUP($A37,'BASE MATERIAL'!$A:$D,3)) | G37: =IF($A37=0,"",VLOOKUP($A37,'BASE MATERIAL'!$A:$D,4)) | H37: =IF($A37=0,"",ROUND(F37*G37,2))
B38: =IF($A38=0,"",VLOOKUP($A38,'BASE MATERIAL'!$A:$D,2)) | E38: =IF($A38=0,"",VLOOKUP($A38,'BASE MATERIAL'!$A:$D,3)) | G38: =IF($A38=0,"",VLOOKUP($A38,'BASE MATERIAL'!$A:$D,4)) | H38: =IF($A38=0,"",ROUND(F38*G38,2))
B39: =IF($A39=0,"",VLOOKUP($A39,'BASE MATERIAL'!$A:$D,2)) | E39: =IF($A39=0,"",VLOOKUP($A39,'BASE MATERIAL'!$A:$D,3)) | G39: =IF($A39=0,"",VLOOKUP($A39,'BASE MATERIAL'!$A:$D,4)) | H39: =IF($A39=0,"",ROUND(F39*G39,2))
B40: =IF($A40=0,"",VLOOKUP($A40,'BASE MATERIAL'!$A:$D,2)) | E40: =IF($A40=0,"",VLOOKUP($A40,'BASE MATERIAL'!$A:$D,3)) | G40: =IF($A40=0,"",VLOOKUP($A40,'BASE MATERIAL'!$A:$D,4)) | H40: =IF($A40=0,"",ROUND(F40*G40,2))
B41: =IF($A41=0,"",VLOOKUP($A41,'BASE MATERIAL'!$A:$D,2)) | E41: =IF($A41=0,"",VLOOKUP($A41,'BASE MATERIAL'!$A:$D,3)) | G41: =IF($A41=0,"",VLOOKUP($A41,'BASE MATERIAL'!$A:$D,4)) | H41: =IF($A41=0,"",ROUND(F41*G41,2))
B42: =IF($A42=0,"",VLOOKUP($A42,'BASE MATERIAL'!$A:$D,2)) | E42: =IF($A42=0,"",VLOOKUP($A42,'BASE MATERIAL'!$A:$D,3)) | G42: =IF($A42=0,"",VLOOKUP($A42,'BASE MATERIAL'!$A:$D,4)) | H42: =IF($A42=0,"",ROUND(F42*G42,2))
B43: =IF($A43=0,"",VLOOKUP($A43,'BASE MATERIAL'!$A:$D,2)) | E43: =IF($A43=0,"",VLOOKUP($A43,'BASE MATERIAL'!$A:$D,3)) | G43: =IF($A43=0,"",VLOOKUP($A43,'BASE MATERIAL'!$A:$D,4)) | H43: =IF($A43=0,"",ROUND(F43*G43,2))
B44: =IF($A44=0,"",VLOOKUP($A44,'BASE MATERIAL'!$A:$D,2)) | E44: =IF($A44=0,"",VLOOKUP($A44,'BASE MATERIAL'!$A:$D,3)) | G44: =IF($A44=0,"",VLOOKUP($A44,'BASE MATERIAL'!$A:$D,4)) | H44: =IF($A44=0,"",ROUND(E44*F44,2))
B45: SUBTOTAL O | H45: =ROUND(SUM(H28:H44),2) -> 1.85
B46: TRANSPORTE
B47: DESCRIPCION | E47: UNIDAD | F47: CANTIDAD A | G47: TARIFA B | H47: COSTO C=A*B
A48: 19019 | B48: =IF($A48=0,"",VLOOKUP($A48,'BASE EQUIPO'!$A:$D,2)) -> TRANSPORTE DE MATERIAL | E48: =IF($A48=0,"",VLOOKUP($A48,'BASE EQUIPO'!$A:$D,3)) -> GLOBAL | F48: 1 | G48: =IF($A48=0,"",VLOOKUP($A48,'BASE EQUIPO'!$A:$D,4)*H45) -> 0.0555 | H48: =IF($A48=0,"",ROUND(F48*G48,2)) -> 0.06
B49: =IF($A49=0,"",VLOOKUP($A49,'BASE EQUIPO'!$A:$D,2)) | E49: =IF($A49=0,"",VLOOKUP($A49,'BASE EQUIPO'!$A:$D,3)) | G49: =IF($A49=0,"",VLOOKUP($A49,'BASE EQUIPO'!$A:$D,4)*H46) | H49: =IF($A49=0,"",ROUND(F49*G49,2))
B50: =IF($A50=0,"",VLOOKUP($A50,'BASE EQUIPO'!$A:$D,2)) | E50: =IF($A50=0,"",VLOOKUP($A50,'BASE EQUIPO'!$A:$D,3)) | G50: =IF($A50=0,"",VLOOKUP($A50,'BASE EQUIPO'!$A:$D,4)*H47) | H50: =IF($A50=0,"",ROUND(F50*G50,2))
B51: SUBTOTAL P | H51: =ROUND(SUM(H47:H50),2) -> 0.06
D52: TOTAL COSTO DIRECTO (M+N+O+P) | H52: =ROUND(SUM(H51,H45,H26,H16),2) -> 2.69
A53: 40002 | D53: INDIRECTOS Y UTILIDADES % | G53: =IF($A53=0,"",VLOOKUP($A53,'BASE MATERIAL'!$M:$P,4)) -> 0 | H53: =IF($A53=0,"",ROUND(G53*H52,2)) -> 0
A54: 40003 | D54: OTROS INDIRECTOS % | G54: =IF($A54=0,"",VLOOKUP($A54,'BASE MATERIAL'!$M:$P,4)) -> 0 | H54: =IF($A54=0,"",ROUND(G54*H52,2)) -> 0
D55: COSTO TOTAL DEL RUBRO | H55: =ROUND(SUM(H52:H54),2) -> 2.69
D56: VALOR OFERTADO | H56: =ROUND(H55,2) -> 2.69
B57: NOMBRE DEL PROPONENTE: | D57: ='1.1'!$D$1 -> ESPOL | H57: FORM. #3 | L57: =A61 -> 2 | M57: =C62 -> Cubierta Steel Panel e= 0,45mm | N57: =H61 -> m2 | O57: =H112 -> 13.5
B58: OBRA: | C58: ='1.1'!$C$2 -> 0 | G58: HOJA | I58: de
C59: ='1.1'!$C$3 -> 0
B60: ANALISIS DE PRECIOS UNITARIOS
A61: 2 | B61: RUBRO | G61: UNIDAD: | H61: m2
B62: DETALLE | C62: Cubierta Steel Panel e= 0,45mm
B64: EQUIPOS
B65: DESCRIPCION | D65: CANTIDAD A | E65: TARIFA B | F65: COSTO HORA C= A*B | G65: RENDIMIENTO | H65: COSTO D=C*R
A66: 19015 | B66: =IF($A66=0,"",VLOOKUP($A66,'BASE EQUIPO'!$A:$D,2)) -> HERRAMIENTA MENOR | D66: 1 | E66: =IF($A66=0,"",VLOOKUP($A66,'BASE EQUIPO'!$A:$D,4)*H82) -> 0.0507 | F66: =IF($A66=0,"",ROUND(D66*E66,2)) -> 0.05 | G66: 1 | H66: =IF($A66=0,"",ROUND(G66*F66,2)) -> 0.05
B67: =IF($A67=0,"",VLOOKUP($A67,'BASE EQUIPO'!$A:$D,2)) | E67: =IF($A67=0,"",VLOOKUP($A67,'BASE EQUIPO'!$A:$D,4)) | F67: =IF($A67=0,"",ROUND(D67*E67,2)) | H67: =IF($A67=0,"",ROUND(G67*F67,2))
B68: =IF($A68=0,"",VLOOKUP($A68,'BASE EQUIPO'!$A:$D,2)) | E68: =IF($A68=0,"",VLOOKUP($A68,'BASE EQUIPO'!$A:$D,4)) | F68: =IF($A68=0,"",ROUND(D68*E68,2)) | H68: =IF($A68=0,"",ROUND(G68*F68,2))
B69: =IF($A69=0,"",VLOOKUP($A69,'BASE EQUIPO'!$A:$D,2)) | E69: =IF($A69=0,"",VLOOKUP($A69,'BASE EQUIPO'!$A:$D,4)) | F69: =IF($A69=0,"",ROUND(D69*E69,2)) | H69: =IF($A69=0,"",ROUND(G69*F69,2))
B70: =IF($A70=0,"",VLOOKUP($A70,'BASE EQUIPO'!$A:$D,2)) | E70: =IF($A70=0,"",VLOOKUP($A70,'BASE EQUIPO'!$A:$D,4)) | F70: =IF($A70=0,"",ROUND(D70*E70,2)) | H70: =IF($A70=0,"",ROUND(G70*F70,2))
B71: =IF($A71=0,"",VLOOKUP($A71,'BASE EQUIPO'!$A:$D,2)) | E71: =IF($A71=0,"",VLOOKUP($A71,'BASE EQUIPO'!$A:$D,4)) | F71: =IF($A71=0,"",ROUND(D71*E71,2)) | H71: =IF($A71=0,"",ROUND(G71*F71,2))
B72: SUBTOTAL M | H72: =ROUND(SUM(H65:H71),2) -> 0.05
B73: MANO DE OBRA
B74: DESCRIPCION (CATEG) | D74: CANTIDAD A | E74: JORNAL/HR B | F74: COSTO HORA C= A*B | G74: RENDIMIENTO | H74: COSTO D=C*R
B75: =IF($A75=0,"",VLOOKUP($A75,'BASE M-OBRA'!$A:$D,2)) | E75: =IF($A75=0,"",VLOOKUP($A75,'BASE M-OBRA'!$A:$D,4)) | F75: =IF($A75=0,"",ROUND(D75*E75,2)) | G75: =IF($A75=0,"",ROUND(H75/F75,2)) | H75: =IF($A75=0,"",ROUND(SUM(H76:H81)*'BASE M-OBRA'!$D$23,2))
A76: 20019 | B76: =IF($A76=0,"",VLOOKUP($A76,'BASE M-OBRA'!$A:$D,2)) -> INSTALADOR | D76: 1 | E76: =IF($A76=0,"",VLOOKUP($A76,'BASE M-OBRA'!$A:$D,4)) -> 2.82 | F76: =IF($A76=0,"",ROUND(D76*E76,2)) -> 2.82 | G76: 0.3 | H76: =IF($A76=0,"",ROUND(G76*F76,2)) -> 0.85
A77: 20011 | B77: =IF($A77=0,"",VLOOKUP($A77,'BASE M-OBRA'!$A:$D,2)) -> AYUDANTE ESPECIALISTA | D77: 1 | E77: =IF($A77=0,"",VLOOKUP($A77,'BASE M-OBRA'!$A:$D,4)) -> 2.79 | F77: =IF($A77=0,"",ROUND(D77*E77,2)) -> 2.79 | G77: =+G76 -> 0.3 | H77: =IF($A77=0,"",ROUND(G77*F77,2)) -> 0.84
B78: =IF($A78=0,"",VLOOKUP($A78,'BASE M-OBRA'!$A:$D,2)) | E78: =IF($A78=0,"",VLOOKUP($A78,'BASE M-OBRA'!$A:$D,4)) | F78: =IF($A78=0,"",ROUND(D78*E78,2)) | H78: =IF($A78=0,"",ROUND(G78*F78,2))
B79: =IF($A79=0,"",VLOOKUP($A79,'BASE M-OBRA'!$A:$D,2)) | E79: =IF($A79=0,"",VLOOKUP($A79,'BASE M-OBRA'!$A:$D,4)) | F79: =IF($A79=0,"",ROUND(D79*E79,2)) | H79: =IF($A79=0,"",ROUND(G79*F79,2))
B80: =IF($A80=0,"",VLOOKUP($A80,'BASE M-OBRA'!$A:$D,2)) | E80: =IF($A80=0,"",VLOOKUP($A80,'BASE M-OBRA'!$A:$D,4)) | F80: =IF($A80=0,"",ROUND(D80*E80,2)) | H80: =IF($A80=0,"",ROUND(G80*F80,2))
B81: =IF($A81=0,"",VLOOKUP($A81,'BASE M-OBRA'!$A:$D,2)) | E81: =IF($A81=0,"",VLOOKUP($A81,'BASE M-OBRA'!$A:$D,4)) | F81: =IF($A81=0,"",ROUND(D81*E81,2)) | H81: =IF($A81=0,"",ROUND(G81*F81,2))
B82: SUBTOTAL N | H82: =ROUND(SUM(H74:H81),2) -> 1.69
B83: MATERIALES
B84: DESCRIPCION | E84: UNIDAD | F84: CANTIDAD A | G84: UNITARIO B | H84: COSTO C=A*B
A85: 14002 | B85: PLANCHA STEEL PANEL | E85: M2 | F85: 1.2 | G85: =8.5*1.12 -> 9.52 | H85: =IF($A85=0,"",ROUND(F85*G85,2)) -> 11.42
H86: =IF($A86=0,"",ROUND(F86*G86,2))
H87: =IF($A87=0,"",ROUND(F87*G87,2))
H88: =IF($A88=0,"",ROUND(F88*G88,2))
H89: =IF($A89=0,"",ROUND(F89*G89,2))
H90: =IF($A90=0,"",ROUND(F90*G90,2))
B91: =IF($A91=0,"",VLOOKUP($A91,'BASE MATERIAL'!$A:$D,2)) | E91: =IF($A91=0,"",VLOOKUP($A91,'BASE MATERIAL'!$A:$D,3)) | G91: =IF($A91=0,"",VLOOKUP($A91,'BASE MATERIAL'!$A:$D,4)) | H91: =IF($A91=0,"",ROUND(F91*G91,2))
H92: =IF($A92=0,"",ROUND(F92*G92,2))
H93: =IF($A93=0,"",ROUND(F93*G93,2))
H94: =IF($A94=0,"",ROUND(F94*G94,2))
H95: =IF($A95=0,"",ROUND(F95*G95,2)) | J95: =0.13*3 -> 0.39
B96: =IF($A96=0,"",VLOOKUP($A96,'BASE MATERIAL'!$A:$D,2)) | E96: =IF($A96=0,"",VLOOKUP($A96,'BASE MATERIAL'!$A:$D,3)) | G96: =IF($A96=0,"",VLOOKUP($A96,'BASE MATERIAL'!$A:$D,4)) | H96: =IF($A96=0,"",ROUND(F96*G96,2)) | J96: =0.1*2 -> 0.2
B97: =IF($A97=0,"",VLOOKUP($A97,'BASE MATERIAL'!$A:$D,2)) | E97: =IF($A97=0,"",VLOOKUP($A97,'BASE MATERIAL'!$A:$D,3)) | G97: =IF($A97=0,"",VLOOKUP($A97,'BASE MATERIAL'!$A:$D,4)) | H97: =IF($A97=0,"",ROUND(F97*G97,2)) | J97: =SUM(J95:J96) -> 0.59
B98: =IF($A98=0,"",VLOOKUP($A98,'BASE MATERIAL'!$A:$D,2)) | E98: =IF($A98=0,"",VLOOKUP($A98,'BASE MATERIAL'!$A:$D,3)) | G98: =IF($A98=0,"",VLOOKUP($A98,'BASE MATERIAL'!$A:$D,4)) | H98: =IF($A98=0,"",ROUND(F98*G98,2))
B99: =IF($A99=0,"",VLOOKUP($A99,'BASE MATERIAL'!$A:$D,2)) | E99: =IF($A99=0,"",VLOOKUP($A99,'BASE MATERIAL'!$A:$D,3)) | G99: =IF($A99=0,"",VLOOKUP($A99,'BASE MATERIAL'!$A:$D,4)) | H99: =IF($A99=0,"",ROUND(F99*G99,2))
B100: =IF($A100=0,"",VLOOKUP($A100,'BASE MATERIAL'!$A:$D,2)) | E100: =IF($A100=0,"",VLOOKUP($A100,'BASE MATERIAL'!$A:$D,3)) | G100: =IF($A100=0,"",VLOOKUP($A100,'BASE MATERIAL'!$A:$D,4)) | H100: =IF($A100=0,"",ROUND(E100*F100,2))
B101: SUBTOTAL O | H101: =ROUND(SUM(H84:H100),2) -> 11.42
B102: TRANSPORTE
...

Sheet 1.8
B1: NOMBRE DEL PROPONENTE: | D1: ='1.1'!$D$1 -> ESPOL | H1: FORM. #3 | L1: =A5 -> 1 | M1: =C6 -> Contrapiso hormigon simple e= 10cm | N1: =H5 -> m2 | O1: =H56 -> 9.61
B2: OBRA: | C2: ='1.1'!$C$2 -> 0 | G2: HOJA | I2: de
C3: ='1.1'!$C$3 -> 0
B4: ANALISIS DE PRECIOS UNITARIOS
A5: 1 | B5: RUBRO | G5: UNIDAD: | H5: m2
B6: DETALLE | C6: Contrapiso hormigon simple e= 10cm
B8: EQUIPOS
B9: DESCRIPCION | D9: CANTIDAD A | E9: TARIFA B | F9: COSTO HORA C= A*B | G9: RENDIMIENTO | H9: COSTO D=C*R
A10: 19015 | B10: =IF($A10=0,"",VLOOKUP($A10,'BASE EQUIPO'!$A:$D,2)) -> HERRAMIENTA MENOR | D10: 1 | E10: =IF($A10=0,"",VLOOKUP($A10,'BASE EQUIPO'!$A:$D,4)*H26) -> 0.0666 | F10: =IF($A10=0,"",ROUND(D10*E10,2)) -> 0.07 | G10: 1 | H10: =IF($A10=0,"",ROUND(G10*F10,2)) -> 0.07
A11: 19003 | B11: =IF($A11=0,"",VLOOKUP($A11,'BASE EQUIPO'!$A:$D,2)) -> CONCRETERA | D11: 1 | E11: =IF($A11=0,"",VLOOKUP($A11,'BASE EQUIPO'!$A:$D,4)) -> 3.5 | F11: =IF($A11=0,"",ROUND(D11*E11,2)) -> 3.5 | G11: =+G20*0.5 -> 0.0275 | H11: =IF($A11=0,"",ROUND(G11*F11,2)) -> 0.1
B12: =IF($A12=0,"",VLOOKUP($A12,'BASE EQUIPO'!$A:$D,2)) | E12: =IF($A12=0,"",VLOOKUP($A12,'BASE EQUIPO'!$A:$D,4)) | F12: =IF($A12=0,"",ROUND(D12*E12,2)) | H12: =IF($A12=0,"",ROUND(G12*F12,2))
B13: =IF($A13=0,"",VLOOKUP($A13,'BASE EQUIPO'!$A:$D,2)) | E13: =IF($A13=0,"",VLOOKUP($A13,'BASE EQUIPO'!$A:$D,4)) | F13: =IF($A13=0,"",ROUND(D13*E13,2)) | H13: =IF($A13=0,"",ROUND(G13*F13,2))
B14: =IF($A14=0,"",VLOOKUP($A14,'BASE EQUIPO'!$A:$D,2)) | E14: =IF($A14=0,"",VLOOKUP($A14,'BASE EQUIPO'!$A:$D,4)) | F14: =IF($A14=0,"",ROUND(D14*E14,2)) | H14: =IF($A14=0,"",ROUND(G14*F14,2))
B15: =IF($A15=0,"",VLOOKUP($A15,'BASE EQUIPO'!$A:$D,2)) | E15: =IF($A15=0,"",VLOOKUP($A15,'BASE EQUIPO'!$A:$D,4)) | F15: =IF($A15=0,"",ROUND(D15*E15,2)) | H15: =IF($A15=0,"",ROUND(G15*F15,2))
B16: SUBTOTAL M | H16: =ROUND(SUM(H9:H15),2) -> 0.17
B17: MANO DE OBRA
B18: DESCRIPCION (CATEG) | D18: CANTIDAD A | E18: JORNAL/HR B | F18: COSTO HORA C= A*B | G18: RENDIMIENTO | H18: COSTO D=C*R
A19: 20001 | B19: =IF($A19=0,"",VLOOKUP($A19,'BASE M-OBRA'!$A:$D,2)) -> MAESTRO | D19: 1 | E19: =IF($A19=0,"",VLOOKUP($A19,'BASE M-OBRA'!$A:$D,4)) -> 3.02 | F19: =IF($A19=0,"",ROUND(D19*E19,2)) -> 3.02 | G19: =IF($A19=0,"",ROUND(H19/F19,2)) -> 0.12 | H19: =IF($A19=0,"",ROUND(SUM(H20:H25)*'BASE M-OBRA'!$D$23,2)) -> 0.37
A20: 20002 | B20: =IF($A20=0,"",VLOOKUP($A20,'BASE M-OBRA'!$A:$D,2)) -> PEON | D20: 8 | E20: =IF($A20=0,"",VLOOKUP($A20,'BASE M-OBRA'!$A:$D,4)) -> 2.79 | F20: =IF($A20=0,"",ROUND(D20*E20,2)) -> 22.32 | G20: 0.055 | H20: =IF($A20=0,"",ROUND(G20*F20,2)) -> 1.23
A21: 20003 | B21: =IF($A21=0,"",VLOOKUP($A21,'BASE M-OBRA'!$A:$D,2)) -> ALBAÑIL | D21: 2 | E21: =IF($A21=0,"",VLOOKUP($A21,'BASE M-OBRA'!$A:$D,4)) -> 2.82 | F21: =IF($A21=0,"",ROUND(D21*E21,2)) -> 5.64 | G21: =+G20 -> 0.055 | H21: =IF($A21=0,"",ROUND(G21*F21,2)) -> 0.31
A22: 20004 | B22: =IF($A22=0,"",VLOOKUP($A22,'BASE M-OBRA'!$A:$D,2)) -> CARPINTERO | D22: 2 | E22: =IF($A22=0,"",VLOOKUP($A22,'BASE M-OBRA'!$A:$D,4)) -> 2.82 | F22: =IF($A22=0,"",ROUND(D22*E22,2)) -> 5.64 | G22: =+G21 -> 0.055 | H22: =IF($A22=0,"",ROUND(G22*F22,2)) -> 0.31
B23: =IF($A23=0,"",VLOOKUP($A23,'BASE M-OBRA'!$A:$D,2)) | E23: =IF($A23=0,"",VLOOKUP($A23,'BASE M-OBRA'!$A:$D,4)) | F23: =IF($A23=0,"",ROUND(D23*E23,2)) | H23: =IF($A23=0,"",ROUND(G23*F23,2))
B24: =IF($A24=0,"",VLOOKUP($A24,'BASE M-OBRA'!$A:$D,2)) | E24: =IF($A24=0,"",VLOOKUP($A24,'BASE M-OBRA'!$A:$D,4)) | F24: =IF($A24=0,"",ROUND(D24*E24,2)) | H24: =IF($A24=0,"",ROUND(G24*F24,2))
B25: =IF($A25=0,"",VLOOKUP($A25,'BASE M-OBRA'!$A:$D,2)) | E25: =IF($A25=0,"",VLOOKUP($A25,'BASE M-OBRA'!$A:$D,4)) | F25: =IF($A25=0,"",ROUND(D25*E25,2)) | H25: =IF($A25=0,"",ROUND(G25*F25,2))
B26: SUBTOTAL N | H26: =ROUND(SUM(H18:H25),2) -> 2.22
B27: MATERIALES
B28: DESCRIPCION | E28: UNIDAD | F28: CANTIDAD A | G28: UNITARIO B | H28: COSTO C=A*B
A29: 11009 | B29: =IF($A29=0,"",VLOOKUP($A29,'BASE MATERIAL'!$A:$D,2)) -> CUARTON | E29: =IF($A29=0,"",VLOOKUP($A29,'BASE MATERIAL'!$A:$D,3)) -> U | F29: =ROUND(0.13*8/(4*3),2) -> 0.09 | G29: =IF($A29=0,"",VLOOKUP($A29,'BASE MATERIAL'!$A:$D,4)) -> 2.42 | H29: =IF($A29=0,"",ROUND(F29*G29,2)) -> 0.22 | K29: =(0.1*3*4)/(3*3) -> 0.13333333
A30: 11007 | B30: =IF($A30=0,"",VLOOKUP($A30,'BASE MATERIAL'!$A:$D,2)) -> CLAVO 2 1/2" | E30: =IF($A30=0,"",VLOOKUP($A30,'BASE MATERIAL'!$A:$D,3)) -> KG | F30: =ROUND(0.13*56/(178*1.5),2) -> 0.03 | G30: =IF($A30=0,"",VLOOKUP($A30,'BASE MATERIAL'!$A:$D,4)) -> 2.652 | H30: =IF($A30=0,"",ROUND(F30*G30,2)) -> 0.08
A31: 4001 | B31: =IF($A31=0,"",VLOOKUP($A31,'BASE MATERIAL'!$A:$D,2)) -> CEMENTO | E31: =IF($A31=0,"",VLOOKUP($A31,'BASE MATERIAL'!$A:$D,3)) -> SACO | F31: =ROUND(7*1.03*0.1,2) -> 0.72 | G31: =IF($A31=0,"",VLOOKUP($A31,'BASE MATERIAL'!$A:$D,4)) -> 7.09 | H31: =IF($A31=0,"",ROUND(F31*G31,2)) -> 5.1
A32: 5004 | B32: =IF($A32=0,"",VLOOKUP($A32,'BASE MATERIAL'!$A:$D,2)) -> ARENA | E32: =IF($A32=0,"",VLOOKUP($A32,'BASE MATERIAL'!$A:$D,3)) -> M3 | F32: =ROUND(F31*0.032*2,2) -> 0.05 | G32: =IF($A32=0,"",VLOOKUP($A32,'BASE MATERIAL'!$A:$D,4)) -> 12.27625 | H32: =IF($A32=0,"",ROUND(F32*G32,2)) -> 0.61
A33: 5002 | B33: =IF($A33=0,"",VLOOKUP($A33,'BASE MATERIAL'!$A:$D,2)) -> PIEDRA 3-4 | E33: =IF($A33=0,"",VLOOKUP($A33,'BASE MATERIAL'!$A:$D,3)) -> M3 | F33: =ROUND(F31*0.032*3,2) -> 0.07 | G33: =IF($A33=0,"",VLOOKUP($A33,'BASE MATERIAL'!$A:$D,4)) -> 13.75 | H33: =IF($A33=0,"",ROUND(F33*G33,2)) -> 0.96
A34: 5005 | B34: =IF($A34=0,"",VLOOKUP($A34,'BASE MATERIAL'!$A:$D,2)) -> AGUA | E34: =IF($A34=0,"",VLOOKUP($A34,'BASE MATERIAL'!$A:$D,3)) -> LT | F34: =26*F31 -> 18.72 | G34: =IF($A34=0,"",VLOOKUP($A34,'BASE MATERIAL'!$A:$D,4)) -> 0.002 | H34: =IF($A34=0,"",ROUND(F34*G34,2)) -> 0.04
B35: =IF($A35=0,"",VLOOKUP($A35,'BASE MATERIAL'!$A:$D,2)) | E35: =IF($A35=0,"",VLOOKUP($A35,'BASE MATERIAL'!$A:$D,3)) | G35: =IF($A35=0,"",VLOOKUP($A35,'BASE MATERIAL'!$A:$D,4)) | H35: =IF($A35=0,"",ROUND(F35*G35,2))
B36: =IF($A36=0,"",VLOOKUP($A36,'BASE MATERIAL'!$A:$D,2)) | E36: =IF($A36=0,"",VLOOKUP($A36,'BASE MATERIAL'!$A:$D,3)) | G36: =IF($A36=0,"",VLOOKUP($A36,'BASE MATERIAL'!$A:$D,4)) | H36: =IF($A36=0,"",ROUND(F36*G36,2))
B37: =IF($A37=0,"",VLOOKUP($A37,'BASE MATERIAL'!$A:$D,2)) | E37: =IF($A37=0,"",VLOOKUP($A37,'BASE MATERIAL'!$A:$D,3)) | G37: =IF($A37=0,"",VLOOKUP($A37,'BASE MATERIAL'!$A:$D,4)) | H37: =IF($A37=0,"",ROUND(F37*G37,2))
B38: =IF($A38=0,"",VLOOKUP($A38,'BASE MATERIAL'!$A:$D,2)) | E38: =IF($A38=0,"",VLOOKUP($A38,'BASE MATERIAL'!$A:$D,3)) | G38: =IF($A38=0,"",VLOOKUP($A38,'BASE MATERIAL'!$A:$D,4)) | H38: =IF($A38=0,"",ROUND(F38*G38,2))
B39: =IF($A39=0,"",VLOOKUP($A39,'BASE MATERIAL'!$A:$D,2)) | E39: =IF($A39=0,"",VLOOKUP($A39,'BASE MATERIAL'!$A:$D,3)) | G39: =IF($A39=0,"",VLOOKUP($A39,'BASE MATERIAL'!$A:$D,4)) | H39: =IF($A39=0,"",ROUND(F39*G39,2))
B40: =IF($A40=0,"",VLOOKUP($A40,'BASE MATERIAL'!$A:$D,2)) | E40: =IF($A40=0,"",VLOOKUP($A40,'BASE MATERIAL'!$A:$D,3)) | G40: =IF($A40=0,"",VLOOKUP($A40,'BASE MATERIAL'!$A:$D,4)) | H40: =IF($A40=0,"",ROUND(F40*G40,2))
B41: =IF($A41=0,"",VLOOKUP($A41,'BASE MATERIAL'!$A:$D,2)) | E41: =IF($A41=0,"",VLOOKUP($A41,'BASE MATERIAL'!$A:$D,3)) | G41: =IF($A41=0,"",VLOOKUP($A41,'BASE MATERIAL'!$A:$D,4)) | H41: =IF($A41=0,"",ROUND(F41*G41,2))
B42: =IF($A42=0,"",VLOOKUP($A42,'BASE MATERIAL'!$A:$D,2)) | E42: =IF($A42=0,"",VLOOKUP($A42,'BASE MATERIAL'!$A:$D,3)) | G42: =IF($A42=0,"",VLOOKUP($A42,'BASE MATERIAL'!$A:$D,4)) | H42: =IF($A42=0,"",ROUND(F42*G42,2))
B43: =IF($A43=0,"",VLOOKUP($A43,'BASE MATERIAL'!$A:$D,2)) | E43: =IF($A43=0,"",VLOOKUP($A43,'BASE MATERIAL'!$A:$D,3)) | G43: =IF($A43=0,"",VLOOKUP($A43,'BASE MATERIAL'!$A:$D,4)) | H43: =IF($A43=0,"",ROUND(F43*G43,2))
